Workbook
Name nilan: 'Master Data'!$A$787
Name nolan: 'Master Data'!$B$788

Sheet Master Data
A1: Master Liste - Salsaflow Dance Company
A3: Mobile | B3: Vorname | C3: Name | D3: m/w | E3: Tarif | F3: Email | G3: Adresse | H3: Postleitzahl | I3: Quelle
A4: 0764032801 | B4: Adrian | C4: Bartella | F4: adrian.bartella@gmx.net | G4: stadthausgasse 15 | H4: 4051 Basel
A5: 0786855151 | B5: Adrian | C5: Baumeyer | F5: adrian.baumeyer@gmail.com | G5: Belchenring 53 | H5: 4123 Allschwil
B6: Aglaia | C6: Graf | F6: aglaiagraf@gmx.ch | G6: stadthausgasse 16 | H6: 4052 Basel
A7: 0765598635 | B7: alberto | C7: iannicca | F7: alberto.iannicca@gmx.ch | G7: Belchenring 54 | H7: 4124 Allschwil
A8: 0796882436 | B8: Aldiana | C8: Mazza | F8: aldiana.mazza@bluewin.ch | G8: stadthausgasse 17 | H8: 4053 Basel
A9: 0796191628 | B9: Aleksandra | C9: Heinrich | F9: aleksandra.heinrich@gmail.com | G9: Belchenring 55 | H9: 4125 Allschwil
A10: 0787964480 | B10: Alessandra | C10: Carlino | F10: a.carlino@gmx.ch | G10: stadthausgasse 18 | H10: 4054 Basel
A11: 0796647491 | B11: Aletta | C11: Kuhn | F11: aletta.kuhn@gmail.com | G11: Belchenring 56 | H11: 4126 Allschwil
A12: 0786861893 | B12: Alexander | C12: Dieter | F12: alex_dieter@hotmail.com | G12: stadthausgasse 19 | H12: 4055 Basel
A13: 0797848703 | B13: Alexander | C13: Fuentes | F13: fuental@gmx.net | G13: Belchenring 57 | H13: 4127 Allschwil
A14: 0033611926373 | B14: Alexandra | C14: Molnar | F14: Al-ex.m@hotmail.fr | G14: stadthausgasse 20 | H14: 4056 Basel
A15: 0794648772 | B15: Alexandra | C15: Bunge | F15: alexandrabunge@bluewin.ch | G15: Belchenring 58 | H15: 4128 Allschwil
A16: 0792673275 | B16: Alexandra | C16: Plattner | F16: alexandra.plattner@hotmail.com | G16: stadthausgasse 21 | H16: 4057 Basel
A17: 0792227006 | B17: Alexandra | C17: Jenal | F17: Alexandra.jenal@gmail.com | G17: Belchenring 59 | H17: 4129 Allschwil
A18: 0797801501 | B18: Alexandra | C18: Siegenthaler | F18: a.siegenthaler@hotmail.com | G18: stadthausgasse 22 | H18: 4058 Basel
... A21: 0791201078 | B21: Alicia | C21: Kerbrat | F21: shoupi4@hotmail.com | G21: Belchenring 61 | H21: 4131 Allschwil
B22: Alison | C22: Lamb | F22: alison.lamb@roche.com | G22: stadthausgasse 24 | H22: 4060 Basel
A23: 0795453654 | B23: Alma | C23: Voser | F23: alma_voser@yahoo.de | G23: Belchenring 62 | H23: 4132 Allschwil
A24: 0787050829 | B24: Amanda | C24: Scott | F24: amandaes@hotmail.com | G24: stadthausgasse 25 | H24: 4061 Basel
A25: 0795978220 | B25: Ana | C25: da Silva Correia | F25: anadsc@gmail.com | G25: Belchenring 63 | H25: 4133 Allschwil
A26: 0787171226 | B26: Ana | C26: Morales | F26: anaestermorales@ymail.com | G26: stadthausgasse 26 | H26: 4062 Basel
A27: 0799543183 | B27: Ana | C27: Lopes | F27: alopes.rust@gmail.com | G27: Belchenring 64 | H27: 4134 Allschwil
B28: Ana Maria | C28: Carrillo | F28: anica1979@hotmail.com | G28: stadthausgasse 27 | H28: 4063 Basel
A29: 0797506526 | B29: Andi | C29: Meier | F29: and_meier@hotmail.com | G29: stadthausgasse 28 | H29: 4064 Basel
A30: 0017221892089 | B30: Andrea | C30: Theis | F30: andrea_theis@yahoo.de | G30: Belchenring 66 | H30: 4136 Allschwil
B31: Andrea | C31: Häberlin | F31: ahaeberlin@gmx.ch | G31: stadthausgasse 29 | H31: 4065 Basel
B32: Andrea | C32: Schäfer | F32: andrea.schaefer@gmx.ch | G32: Belchenring 67 | H32: 4137 Allschwil
A33: 0765062732 | B33: Andrea | C33: Schmitter | F33: andrea.schmitter@hotmail.com | G33: stadthausgasse 30 | H33: 4066 Basel
A34: 0491774479811 | B34: Andrea | C34: Collatz | F34: andreacollatz@gmx.de | G34: Belchenring 68 | H34: 4138 Allschwil
A35: 0774549009 | B35: Annina | C35: Stooss | F35: Annina@stooss.ch | G35: stadthausgasse 31 | H35: 4067 Basel
A36: 0763270815 | B36: Annina | C36: Striebel | F36: a.striebel@gmx.ch | G36: Belchenring 69 | H36: 4139 Allschwil
A37: 0787731548 | B37: Antonio / Desirée | C37: Perla | F37: a.perla@bluewin.ch | G37: stadthausgasse 32 | H37: 4068 Basel
A38: 0767759451 | B38: Araceli | C38: Lamelas Cabello | F38: araceli.lamelas@unibas.ch | G38: Belchenring 70 | H38: 4140 Allschwil
A39: 0796680215 | B39: Armin | C39: Barandun | F39: arminbarandun@datacomm.ch | G39: stadthausgasse 33 | H39: 4069 Basel
A40: 0786768889 | B40: Arun (männlich) | C40: Wadhawan | F40: poloarun@yahoo.com | G40: Belchenring 71 | H40: 4141 Allschwil
A41: 0797070796 | B41: Astrid | C41: Zubler | F41: astrid.zubler@bluewin.ch | G41: stadthausgasse 34 | H41: 4070 Basel
B42: Astrid | C42: Fink | F42: juerg.fink@bluewin.ch | G42: Belchenring 72 | H42: 4142 Allschwil
A43: 0793867737 | B43: Atiya | C43: Özkaya | F43: atiya_oezkaya@hotmail.com | G43: stadthausgasse 35 | H43: 4071 Basel
A44: 0786001845 | B44: Azucena | C44: Blanco | F44: azucena@bluewin.ch | G44: Belchenring 73 | H44: 4143 Allschwil
A45: 0762468783 | B45: Balazs | C45: Szenzenstein | F45: szenzibalazs@gmail.com | G45: stadthausgasse 36 | H45: 4072 Basel
B46: Barbara | C46: Heil | F46: barbara.heil@mails.ch | G46: Belchenring 74 | H46: 4144 Allschwil
A47: 0786859037 | B47: Barbara | C47: Reuteler | F47: bareuteler@hispeed.ch | G47: stadthausgasse 37 | H47: 4073 Basel
A48: 0796868752 | B48: Barbara | C48: Bottazzini | F48: bottazzini77@yahoo.de | G48: Belchenring 75 | H48: 4145 Allschwil
B49: Barbara | C49: Senger | F49: barbara.senger@gmx.de | G49: stadthausgasse 38 | H49: 4074 Basel
B50: Barbara | C50: Kehrli | F50: barbara.kehrli@bluemail.ch | G50: Belchenring 76 | H50: 4146 Allschwil
A51: 0795465474 | B51: Barbara | C51: Tank | F51: b.tank@gmx.ch | G51: stadthausgasse 39 | H51: 4075 Basel
A52: 0764364056 | B52: Barbara | C52: Ballmer | F52: bkouadio@gmx.ch | G52: Belchenring 77 | H52: 4147 Allschwil
B53: Beat | C53: Michel | F53: michelmichel@bluewin.ch | G53: stadthausgasse 40 | H53: 4076 Basel
B54: Beat | C54: Schönenberger | F54: bs67@bluewin.ch | G54: Belchenring 78 | H54: 4148 Allschwil
A55: 0796859151 | B55: Beatrice | C55: Moser | F55: bea-moser@bluewin.ch | G55: stadthausgasse 41 | H55: 4077 Basel
A56: 0763471717 | B56: Beatrice | C56: Alioth | F56: bfifty2@sunrise.ch | G56: Belchenring 79 | H56: 4149 Allschwil
B57: Ben | C57: Gregor-Smith | F57: bengregorsmith@hotmail.com | G57: stadthausgasse 42 | H57: 4078 Basel
A58: 004917650875000 | B58: Benedikt | C58: Simons | F58: benedikt.simons@gmx.ch | G58: Belchenring 80 | H58: 4150 Allschwil
A59: 0793287870 | B59: Benjamin | C59: Schmeitzky | F59: benjamin.schmeitzky@gmail.com | G59: stadthausgasse 43 | H59: 4079 Basel
A60: 0787252760 | B60: Bethan | C60: Johnson | F60: bethan_caroline.johnson@novartis.com | G60: Belchenring 81 | H60: 4151 Allschwil
B61: Bianca | C61: Pfarr | F61: bianca_pfarr@gmx.de | G61: stadthausgasse 44 | H61: 4080 Basel
A62: 0763873190 | B62: Björn | C62: Thoma | F62: bjoernthoma@gmx.ch | G62: Belchenring 82 | H62: 4152 Allschwil
A63: 004917621526059 | B63: Britta | C63: Schweinlin | F63: BrittaSchweinlin@web.de | G63: stadthausgasse 45 | H63: 4081 Basel
A64: 0041616817431 | B64: Britta | C64: Knapp | F64: britta.knapp@gmx.de | G64: Belchenring 83 | H64: 4153 Allschwil
A65: 0796657243 | B65: Candida | C65: Knüsel | F65: knuesel@hotmail.com | G65: stadthausgasse 46 | H65: 4082 Basel
A66: 0764200272 | B66: Canelli | C66: Maria | F66: maria_c_76@yahoo.fr | G66: Belchenring 84 | H66: 4154 Allschwil
A67: 0762182198 | B67: Carballo | C67: Sebastian | F67: sebascarballo86@hotmail.com | G67: stadthausgasse 47 | H67: 4083 Basel
B68: Carina | C68: Lebherz | F68: dadari@gmx.at | G68: Belchenring 85 | H68: 4155 Allschwil
B69: Carine | C69: Manschott | F69: carinemanschott@hotmail.com | G69: stadthausgasse 48 | H69: 4084 Basel
A70: 0764951508 | B70: Carlo | C70: Wolf | F70: wolfi.c@gmx.ch | G70: Belchenring 86 | H70: 4156 Allschwil
A71: 0788076700 | B71: carlos | C71: amstutz | F71: doncarlosgabriel@hotmail.com | G71: stadthausgasse 49 | H71: 4085 Basel
A72: 0763714864 | B72: Carmen | C72: Held | F72: c.held@hispeed.ch | G72: Belchenring 87 | H72: 4157 Allschwil
A73: 0798276374 | B73: Carmen | C73: Zuber | F73: hexe.86@hotmail.com | G73: stadthausgasse 50 | H73: 4086 Basel
A74: 0792632781 | B74: Carolina | C74: Francos | F74: carolina.francos@hotmail.ch | G74: Belchenring 88 | H74: 4158 Allschwil
B75: Caterina | C75: Capaccioli | F75: caterina.capaccioli@novartis.com | G75: stadthausgasse 51 | H75: 4087 Basel
A76: 0793355005 | B76: Catherine | C76: Droeser | F76: cd@eg-architekten.ch | G76: Belchenring 89 | H76: 4159 Allschwil
A77: 0788501732 | B77: Catherine | C77: Thommen | D77: w | E77: Normal | F77: catherine.thommen@yahoo.de | G77: stadthausgasse 52 | H77: 4088 Basel
A78: 0793430413 | B78: Celine | C78: Leroux | F78: agnes.leroux@bluewin.ch | G78: Belchenring 90 | H78: 4160 Allschwil
A79: 0788368825 | B79: Celine | C79: Pokorny | F79: C.pokorny@gmx.ch | G79: stadthausgasse 53 | H79: 4089 Basel
B80: Chantal | C80: Ruf | F80: chantal.ruf@gmx.ch | G80: Belchenring 91 | H80: 4161 Allschwil
A81: 0795784915 | B81: Chantal | C81: Wirz | F81: chantal_wirz@bluewin.ch | G81: stadthausgasse 54 | H81: 4090 Basel
B82: Charlotte | C82: Walder | F82: charlotte.walder@gmx.ch | G82: Belchenring 92 | H82: 4162 Allschwil
B83: Christa | C83: Bürki | F83: christa.buerki@teleport.ch | G83: stadthausgasse 55 | H83: 4091 Basel
B84: Christian | C84: Neumann | F84: christian.neumann@hispeed.ch | G84: Belchenring 93 | H84: 4163 Allschwil
A85: 0794574848 | B85: Christian | C85: Stuker | F85: c.stuker@gmx.ch | G85: stadthausgasse 56 | H85: 4092 Basel
A86: 793729046 | B86: Christian | C86: Steiner | F86: christian.steiner@bman.ch | G86: Belchenring 94 | H86: 4164 Allschwil
A87: 0764171701 | B87: Christian | C87: Müller | F87: chrimu76@yahoo.com | G87: stadthausgasse 57 | H87: 4093 Basel
B88: Christian | C88: Friscic | F88: c.friscic@web.de | G88: Belchenring 95 | H88: 4165 Allschwil
A89: 0774014927 | B89: Christian | C89: Manicke | F89: Christian.Manicke@gmx.de | G89: stadthausgasse 58 | H89: 4094 Basel
A90: 0764587206 | B90: Christian | C90: Kammer | F90: c_kammer@vtxmail.ch | G90: Belchenring 96 | H90: 4166 Allschwil
A91: 004915123050820 | B91: Christian | C91: von Nell | F91: christian.vonnell@web.de | G91: stadthausgasse 59 | H91: 4095 Basel
A92: 0774481546 | B92: Christian | C92: Widmer | F92: Christian.widmer@roche.com | G92: Belchenring 97 | H92: 4167 Allschwil
A93: 0797990789 | B93: Christian | C93: Keller | F93: kellerchristiando@yahoo.de | G93: stadthausgasse 60 | H93: 4096 Basel
A94: 0799075278 | B94: Christiane | C94: Zieschang | F94: chriszie@web.de | G94: Belchenring 98 | H94: 4168 Allschwil
A95: 01786934409 | B95: Christiane | C95: Schiel | F95: Christiane.Schiel@web.de | G95: stadthausgasse 61 | H95: 4097 Basel
A96: 0799223171 | B96: Christina | C96: Junvik | F96: christinajunvik@hotmail.com | G96: Belchenring 99 | H96: 4169 Allschwil
A97: 001731537430 | B97: Christina | C97: Gebel | F97: gebelchristina@gmx.de | G97: stadthausgasse 62 | H97: 4098 Basel
B98: Christine | C98: Korkmaz | F98: christinekorkmaz@hotmail.com | G98: Belchenring 100 | H98: 4170 Allschwil
B99: Christine | C99: Keutler | F99: chr.keutler@t-online.de | G99: stadthausgasse 63 | H99: 4099 Basel
A100: 0765303655 | B100: Christine | C100: Haselbach | F100: ogbovoh-haselbach@bluewin.ch | G100: Belchenring 101 | H100: 4171 Allschwil
B101: Christoph | C101: Lütolf | F101: chluetolf@freesurf.ch | G101: stadthausgasse 64 | H101: 4100 Basel
B102: Christoph | C102: Berger | F102: bs.feldenkrais@bluewin.ch | G102: Belchenring 102 | H102: 4172 Allschwil
A103: 0774272706 | B103: Claire-lise | C103: Spinnler-Jenne | F103: clspinnler@hotmail.com | G103: stadthausgasse 65 | H103: 4101 Basel
...

Sheet Mo_Salsa Intermediate Stufe 11
A1: Anmeldungen - Salsa Intermediate Stufe 11
A3: Datum: | B3: 05.01.2026 - 02.03.2026 | D3: Kurstag: | E3: Montag | G3: Lehrer: | H3: Viviana & Sebastian
A4: Zeit: | B4: 18:30 - 19:30 | D4: Ort: | E4: Elisabethenanlage 7 | G4: Preis: | H4: CHF 190.- / CHF 160.-
A6: Vorname | B6: Name | C6: E-Mail | D6: Mobile | E6: Bemerkungen | F6: m/w | G6: Tarif | H6: Betrag | I6: Anwesenheit
A7: =VLOOKUP(D7,'Master Data'!A:F,2,FALSE) -> Dominik | B7: =VLOOKUP(D7,'Master Data'!A:F,3,FALSE) -> Mann | C7: =VLOOKUP(D7,'Master Data'!A:F,6,FALSE) -> dominik.mann@icloud.com | D7: 0795694012 | F7: =VLOOKUP(D7,'Master Data'!A:F,4,FALSE) -> m | G7: =VLOOKUP(D7,'Master Data'!A:F,5,FALSE) -> Normal | H7: 160 | I7: X | J7: - | K7: X | L7: - | M7: X
A8: =VLOOKUP(D8,'Master Data'!A:F,2,FALSE) -> Daniel | B8: =VLOOKUP(D8,'Master Data'!A:F,3,FALSE) -> Hoffmann | C8: =VLOOKUP(D8,'Master Data'!A:F,6,FALSE) -> daniel.pascal.hoffmann@gmail.com | D8: 0765055780 | F8: =VLOOKUP(D8,'Master Data'!A:F,4,FALSE) -> m | G8: =VLOOKUP(D8,'Master Data'!A:F,5,FALSE) -> Normal | H8: 240 | I8: X | J8: X | K8: X | M8: X
A9: =VLOOKUP(D9,'Master Data'!A:F,2,FALSE) -> Selina | B9: =VLOOKUP(D9,'Master Data'!A:F,3,FALSE) -> Schenker | C9: =VLOOKUP(D9,'Master Data'!A:F,6,FALSE) -> selina.schenker@live.de | D9: 0793283745 | F9: =VLOOKUP(D9,'Master Data'!A:F,4,FALSE) -> w | G9: =VLOOKUP(D9,'Master Data'!A:F,5,FALSE) -> Normal | H9: 240 | I9: X | J9: X | K9: X | M9: X
A10: =VLOOKUP(D10,'Master Data'!A:F,2,FALSE) -> Onur | B10: =VLOOKUP(D10,'Master Data'!A:F,3,FALSE) -> Erdem | C10: =VLOOKUP(D10,'Master Data'!A:F,6,FALSE) -> erdem-onur@hotmail.com | D10: 0786111634 | F10: =VLOOKUP(D10,'Master Data'!A:F,4,FALSE) -> m | G10: =VLOOKUP(D10,'Master Data'!A:F,5,FALSE) -> Normal | I10: X | J10: X | K10: X | M10: X
A11: =VLOOKUP(D11,'Master Data'!A:F,2,FALSE) -> Alexandra | B11: =VLOOKUP(D11,'Master Data'!A:F,3,FALSE) -> Daniel | C11: =VLOOKUP(D11,'Master Data'!A:F,6,FALSE) -> danielalexandra970@gmail.com | D11: 0768150705 | F11: =VLOOKUP(D11,'Master Data'!A:F,4,FALSE) -> w | G11: =VLOOKUP(D11,'Master Data'!A:F,5,FALSE) -> Paar | H11: 160 | I11: X | J11: X | K11: X | M11: X
A12: =VLOOKUP(D12,'Master Data'!A:F,2,FALSE) -> Laszlo | B12: =VLOOKUP(D12,'Master Data'!A:F,3,FALSE) -> Lukacs | C12: =VLOOKUP(D12,'Master Data'!A:F,6,FALSE) -> laci91128@gmail.com | D12: 0036703794124 | F12: =VLOOKUP(D12,'Master Data'!A:F,4,FALSE) -> m | G12: =VLOOKUP(D12,'Master Data'!A:F,5,FALSE) -> Normal | H12: 410 | I12: - | J12: X | K12: X | M12: X | N12: -
A13: =VLOOKUP(D13,'Master Data'!A:F,2,FALSE) -> Alicja | B13: =VLOOKUP(D13,'Master Data'!A:F,3,FALSE) -> Dziedzic | C13: =VLOOKUP(D13,'Master Data'!A:F,6,FALSE) -> alicja.dziedzic99@gmail.com | D13: 0779146940 | F13: =VLOOKUP(D13,'Master Data'!A:F,4,FALSE) -> w | G13: =VLOOKUP(D13,'Master Data'!A:F,5,FALSE) -> Normal | H13: 190 | I13: X | J13: X | K13: X | M13: X | O13: -
A14: =VLOOKUP(D14,'Master Data'!A:F,2,FALSE) -> Karolina | B14: =VLOOKUP(D14,'Master Data'!A:F,3,FALSE) -> Dziedzic | C14: =VLOOKUP(D14,'Master Data'!A:F,6,FALSE) -> kdziedzic09@gmail.com | D14: 0779507623 | F14: =VLOOKUP(D14,'Master Data'!A:F,4,FALSE) -> w | G14: =VLOOKUP(D14,'Master Data'!A:F,5,FALSE) -> Normal | H14: 285 | I14: X | J14: X | K14: X | M14: X | N14: -
A15: =VLOOKUP(D15,'Master Data'!A:F,2,FALSE) -> Lisa | B15: =VLOOKUP(D15,'Master Data'!A:F,3,FALSE) -> Velte | C15: =VLOOKUP(D15,'Master Data'!A:F,6,FALSE) -> lisa_velte@hotmail.com | D15: 0765703203 | F15: =VLOOKUP(D15,'Master Data'!A:F,4,FALSE) -> w | G15: =VLOOKUP(D15,'Master Data'!A:F,5,FALSE) -> Normal | H15: 190 | I15: - | J15: X | K15: - | M15: X | N15: - | P15: -
A16: =VLOOKUP(D16,'Master Data'!A:F,2,FALSE) -> Marina | B16: =VLOOKUP(D16,'Master Data'!A:F,3,FALSE) -> Despotovic | C16: =VLOOKUP(D16,'Master Data'!A:F,6,FALSE) -> marina.despotovic@gmx.ch | D16: 0797907059 | F16: =VLOOKUP(D16,'Master Data'!A:F,4,FALSE) -> w | G16: =VLOOKUP(D16,'Master Data'!A:F,5,FALSE) -> Normal | H16: 190 | I16: - | J16: X | K16: X | M16: X
A17: =VLOOKUP(D17,'Master Data'!A:F,2,FALSE) -> Nikola | B17: =VLOOKUP(D17,'Master Data'!A:F,3,FALSE) -> Jevtic | C17: =VLOOKUP(D17,'Master Data'!A:F,6,FALSE) -> nikola.jevtic@bluewin.ch | D17: 0796971944 | F17: =VLOOKUP(D17,'Master Data'!A:F,4,FALSE) -> m | G17: =VLOOKUP(D17,'Master Data'!A:F,5,FALSE) -> Normal | H17: 285 | I17: X | J17: - | K17: X | M17: X
A18: =VLOOKUP(D18,'Master Data'!A:F,2,FALSE) -> Tobias | B18: =VLOOKUP(D18,'Master Data'!A:F,3,FALSE) -> Thommen | C18: =VLOOKUP(D18,'Master Data'!A:F,6,FALSE) -> tobithommen@hotmail.com | D18: 0798115348 | F18: =VLOOKUP(D18,'Master Data'!A:F,4,FALSE) -> m | G18: =VLOOKUP(D18,'Master Data'!A:F,5,FALSE) -> Normal | H18: 240 | I18: X | J18: - | K18: - | M18: X | N18: - | O18: -
A19: =VLOOKUP(D19,'Master Data'!A:F,2,FALSE) -> Myriam | B19: =VLOOKUP(D19,'Master Data'!A:F,3,FALSE) -> Aouadi | C19: =VLOOKUP(D19,'Master Data'!A:F,6,FALSE) -> aouadme@gmail.com | D19: 0795404172 | F19: =VLOOKUP(D19,'Master Data'!A:F,4,FALSE) -> w | G19: =VLOOKUP(D19,'Master Data'!A:F,5,FALSE) -> Normal | H19: 410 | I19: X | J19: X | K19: - | M19: X
A20: =VLOOKUP(D20,'Master Data'!A:F,2,FALSE) -> Burak | B20: =VLOOKUP(D20,'Master Data'!A:F,3,FALSE) -> Yildirim | C20: =VLOOKUP(D20,'Master Data'!A:F,6,FALSE) -> burak.yildirim@gmx.ch | D20: 0795584011 | F20: =VLOOKUP(D20,'Master Data'!A:F,4,FALSE) -> m | G20: =VLOOKUP(D20,'Master Data'!A:F,5,FALSE) -> Normal | I20: - | J20: X | K20: X | M20: X | O20: -
A21: =VLOOKUP(D21,'Master Data'!A:F,2,FALSE) -> Estelle | B21: =VLOOKUP(D21,'Master Data'!A:F,3,FALSE) -> Pierrot | C21: =VLOOKUP(D21,'Master Data'!A:F,6,FALSE) -> stella110@hotmail.fr | D21: 0765235926 | F21: =VLOOKUP(D21,'Master Data'!A:F,4,FALSE) -> w | G21: =VLOOKUP(D21,'Master Data'!A:F,5,FALSE) -> Normal | H21: 410 | I21: X | J21: X | K21: X | M21: X
A22: =VLOOKUP(D22,'Master Data'!A:F,2,FALSE) -> Malin | B22: =VLOOKUP(D22,'Master Data'!A:F,3,FALSE) -> Kirschke | C22: =VLOOKUP(D22,'Master Data'!A:F,6,FALSE) -> malin@m-kirschke.de | D22: 004915735499550 | F22: =VLOOKUP(D22,'Master Data'!A:F,4,FALSE) -> w | G22: =VLOOKUP(D22,'Master Data'!A:F,5,FALSE) -> Normal | H22: 190 | I22: - | J22: - | K22: - | M22: X | O22: - | P22: -
A23: =VLOOKUP(D23,'Master Data'!A:F,2,FALSE) -> Syria | B23: =VLOOKUP(D23,'Master Data'!A:F,3,FALSE) -> Savary | C23: =VLOOKUP(D23,'Master Data'!A:F,6,FALSE) -> syria.savary@hotmail.ch | D23: 0798724080 | F23: =VLOOKUP(D23,'Master Data'!A:F,4,FALSE) -> w | G23: =VLOOKUP(D23,'Master Data'!A:F,5,FALSE) -> Paar | H23: 340 | I23: X | J23: X | K23: X | L23: - | M23: X | N23: -
A24: =VLOOKUP(D24,'Master Data'!A:F,2,FALSE) -> Johanna | B24: =VLOOKUP(D24,'Master Data'!A:F,3,FALSE) -> Broschei | C24: =VLOOKUP(D24,'Master Data'!A:F,6,FALSE) -> jo.broschei@web.de | D24: 004915141238841 | F24: =VLOOKUP(D24,'Master Data'!A:F,4,FALSE) -> w | G24: =VLOOKUP(D24,'Master Data'!A:F,5,FALSE) -> Normal | H24: 190 | I24: - | J24: X | K24: X | L24: - | M24: X
A25: =VLOOKUP(D25,'Master Data'!A:F,2,FALSE) -> Mathias | B25: =VLOOKUP(D25,'Master Data'!A:F,3,FALSE) -> Landsrath | C25: =VLOOKUP(D25,'Master Data'!A:F,6,FALSE) -> matila@gmx.de | D25: 0766413136 | F25: =VLOOKUP(D25,'Master Data'!A:F,4,FALSE) -> m | G25: =VLOOKUP(D25,'Master Data'!A:F,5,FALSE) -> Normal | I25: - | J25: X | K25: - | M25: X | N25: -
A26: =VLOOKUP(D26,'Master Data'!A:F,2,FALSE) -> Michelle | B26: =VLOOKUP(D26,'Master Data'!A:F,3,FALSE) -> Harder | C26: =VLOOKUP(D26,'Master Data'!A:F,6,FALSE) -> michelle.harder@sunrise.ch | D26: 0763031188 | F26: =VLOOKUP(D26,'Master Data'!A:F,4,FALSE) -> w | G26: =VLOOKUP(D26,'Master Data'!A:F,5,FALSE) -> Normal | H26: 135 | I26: X | J26: - | K26: X | L26: - | M26: X | P26: -
A27: =VLOOKUP(D27,'Master Data'!A:F,2,FALSE) -> Umut | B27: =VLOOKUP(D27,'Master Data'!A:F,3,FALSE) -> Paldir | C27: =VLOOKUP(D27,'Master Data'!A:F,6,FALSE) -> umut.paldir@gmail.com | D27: 0798569600 | F27: =VLOOKUP(D27,'Master Data'!A:F,4,FALSE) -> m | G27: =VLOOKUP(D27,'Master Data'!A:F,5,FALSE) -> Normal | H27: 190 | I27: X | J27: - | K27: - | M27: X | O27: - | P27: -
A28: =VLOOKUP(D28,'Master Data'!A:F,2,FALSE) -> Haimo | B28: =VLOOKUP(D28,'Master Data'!A:F,3,FALSE) -> Jöhri | C28: =VLOOKUP(D28,'Master Data'!A:F,6,FALSE) -> paps1408@gmail.com | D28: 0763662642 | E28: Salsaflow Pass | F28: =VLOOKUP(D28,'Master Data'!A:F,4,FALSE) -> m | G28: =VLOOKUP(D28,'Master Data'!A:F,5,FALSE) -> Normal | H28: 410 | I28: X | J28: X | K28: X | M28: X | P28: -
A29: =VLOOKUP(D29,'Master Data'!A:F,2,FALSE) -> Sara | B29: =VLOOKUP(D29,'Master Data'!A:F,3,FALSE) -> Bettonte | C29: =VLOOKUP(D29,'Master Data'!A:F,6,FALSE) -> mattiabert93@gmail.com | D29: 0762326073 | F29: =VLOOKUP(D29,'Master Data'!A:F,4,FALSE) -> w | G29: =VLOOKUP(D29,'Master Data'!A:F,5,FALSE) -> Paar | H29: 190 | I29: - | J29: - | K29: X | M29: X | N29: -
A30: =VLOOKUP(D30,'Master Data'!A:F,2,FALSE) -> #N/A | B30: =VLOOKUP(D30,'Master Data'!A:F,3,FALSE) -> #N/A | C30: =VLOOKUP(D30,'Master Data'!A:F,6,FALSE) -> #N/A | F30: =VLOOKUP(D30,'Master Data'!A:F,4,FALSE) -> #N/A | G30: =VLOOKUP(D30,'Master Data'!A:F,5,FALSE) -> #N/A
A31: =VLOOKUP(D31,'Master Data'!A:F,2,FALSE) -> #N/A | B31: =VLOOKUP(D31,'Master Data'!A:F,3,FALSE) -> #N/A | C31: =VLOOKUP(D31,'Master Data'!A:F,5,FALSE) -> #N/A | F31: =VLOOKUP(D31,'Master Data'!A:F,4,FALSE) -> #N/A | G31: =VLOOKUP(D31,'Master Data'!A:F,5,FALSE) -> #N/A
A32: =VLOOKUP(D32,'Master Data'!A:F,2,FALSE) -> #N/A | B32: =VLOOKUP(D32,'Master Data'!A:F,3,FALSE) -> #N/A | C32: =VLOOKUP(D32,'Master Data'!A:F,5,FALSE) -> #N/A | G32: Einnahmen | H32: =SUM(H7:H31) -> 5055

Sheet Mo_Salsa Intermediate Stufe 8
A1: Anmeldungen - Salsa Intermediate 8
A3: Datum: | B3: 05.01.2026 - 02.03.2026 | D3: Kurstag: | E3: Montag | G3: Lehrer: | H3: Claudia & Maarten
A4: Zeit: | B4: 18:30 - 19:30 | D4: Ort: | E4: Elisabethenanlage 7 | G4: Preis: | H4: CHF 190.- / CHF 160.-
A6: Vorname | B6: Name | C6: E-Mail | D6: Mobile | E6: Bemerkungen | F6: m/w | G6: Tarif | H6: Betrag | I6: Anwesenheit
A7: =VLOOKUP(D7,'Master Data'!A:F,2,FALSE) -> Carmen | B7: =VLOOKUP(D7,'Master Data'!A:F,3,FALSE) -> Magno | C7: =VLOOKUP(D7,'Master Data'!A:F,6,FALSE) -> carmen_magno4@hotmail.com | D7: 0764535573 | F7: =VLOOKUP(D7,'Master Data'!A:F,4,FALSE) -> w | G7: =VLOOKUP(D7,'Master Data'!A:F,5,FALSE) -> Paar | H7: 160 | I7: X | J7: X | K7: - | M7: X | N7: - | O7: - | P7: -
A8: =VLOOKUP(D8,'Master Data'!A:F,2,FALSE) -> Lukas | B8: =VLOOKUP(D8,'Master Data'!A:F,3,FALSE) -> Kofmehl | C8: =VLOOKUP(D8,'Master Data'!A:F,6,FALSE) -> lkofmehl.lk@gmail.ch | D8: 0774063151 | F8: =VLOOKUP(D8,'Master Data'!A:F,4,FALSE) -> m | G8: =VLOOKUP(D8,'Master Data'!A:F,5,FALSE) -> Paar | H8: 160 | I8: X | J8: X | K8: - | M8: X | N8: - | O8: - | P8: -
A9: =VLOOKUP(D9,'Master Data'!A:F,2,FALSE) -> Eliane | B9: =VLOOKUP(D9,'Master Data'!A:F,3,FALSE) -> Schneeberger | C9: =VLOOKUP(D9,'Master Data'!A:F,6,FALSE) -> eliane.schneeberger@gmail.com | D9: 0795572430 | F9: =VLOOKUP(D9,'Master Data'!A:F,4,FALSE) -> w | G9: =VLOOKUP(D9,'Master Data'!A:F,5,FALSE) -> Normal | H9: 285 | I9: X | J9: X | K9: X | M9: X | N9: - | O9: -
A10: =VLOOKUP(D10,'Master Data'!A:F,2,FALSE) -> Alexandra | B10: =VLOOKUP(D10,'Master Data'!A:F,3,FALSE) -> Meyer | C10: =VLOOKUP(D10,'Master Data'!A:F,6,FALSE) -> lexxx.lexxx@gmail.com | D10: 0796580395 | E10: 2. Kurse | F10: =VLOOKUP(D10,'Master Data'!A:F,4,FALSE) -> w | G10: =VLOOKUP(D10,'Master Data'!A:F,5,FALSE) -> Normal | H10: 285 | I10: X | J10: X | K10: - | L10: - | M10: X | O10: -
A11: =VLOOKUP(D11,'Master Data'!A:F,2,FALSE) -> Katrin | B11: =VLOOKUP(D11,'Master Data'!A:F,3,FALSE) -> Schläpfer | C11: =VLOOKUP(D11,'Master Data'!A:F,6,FALSE) -> katrin.schlaepfer@edubs.ch | D11: 0792626602 | F11: =VLOOKUP(D11,'Master Data'!A:F,4,FALSE) -> w | G11: =VLOOKUP(D11,'Master Data'!A:F,5,FALSE) -> Normal | H11: 190 | I11: X | J11: X | K11: X | M11: X
A12: =VLOOKUP(D12,'Master Data'!A:F,2,FALSE) -> Elisa | B12: =VLOOKUP(D12,'Master Data'!A:F,3,FALSE) -> Benitez | C12: =VLOOKUP(D12,'Master Data'!A:F,6,FALSE) -> ebenitezgarcia@gmail.com | D12: 0782042740 | F12: =VLOOKUP(D12,'Master Data'!A:F,4,FALSE) -> w | G12: =VLOOKUP(D12,'Master Data'!A:F,5,FALSE) -> Normal | H12: 190 | I12: X | J12: X | K12: - | M12: X
A13: =VLOOKUP(D13,'Master Data'!A:F,2,FALSE) -> Fabio | B13: =VLOOKUP(D13,'Master Data'!A:F,3,FALSE) -> Vaschetto | C13: =VLOOKUP(D13,'Master Data'!A:F,6,FALSE) -> fabio.vaschetto@gmail.com | D13: 0796904915 | F13: =VLOOKUP(D13,'Master Data'!A:F,4,FALSE) -> m | G13: =VLOOKUP(D13,'Master Data'!A:F,5,FALSE) -> Normal | H13: 190 | I13: X | J13: X | K13: X | M13: -
A14: =VLOOKUP(D14,'Master Data'!A:F,2,FALSE) -> Kristijan | B14: =VLOOKUP(D14,'Master Data'!A:F,3,FALSE) -> Markovic | C14: =VLOOKUP(D14,'Master Data'!A:F,6,FALSE) -> kristijan1.markovic@gmail.com | D14: 0765608884 | F14: =VLOOKUP(D14,'Master Data'!A:F,4,FALSE) -> m | G14: =VLOOKUP(D14,'Master Data'!A:F,5,FALSE) -> Paar | H14: 190 | I14: X | J14: - | K14: - | L14: - | M14: X
A15: =VLOOKUP(D15,'Master Data'!A:F,2,FALSE) -> Lucyann | B15: =VLOOKUP(D15,'Master Data'!A:F,3,FALSE) -> Ceballos | C15: =VLOOKUP(D15,'Master Data'!A:F,6,FALSE) -> ceballos.lucyann@gmail.com | D15: 0017875053395 | E15: 2 halbe Kurse | F15: =VLOOKUP(D15,'Master Data'!A:F,4,FALSE) -> w | G15: =VLOOKUP(D15,'Master Data'!A:F,5,FALSE) -> Normal | H15: 240 | I15: - | J15: X | K15: X | M15: X
A16: =VLOOKUP(D16,'Master Data'!A:F,2,FALSE) -> Lana | B16: =VLOOKUP(D16,'Master Data'!A:F,3,FALSE) -> Vinigradova | C16: =VLOOKUP(D16,'Master Data'!A:F,6,FALSE) -> lanavin@gmail.com | D16: 0798866124 | E16: 2 halbe Kurse | F16: =VLOOKUP(D16,'Master Data'!A:F,4,FALSE) -> w | G16: =VLOOKUP(D16,'Master Data'!A:F,5,FALSE) -> Normal | H16: 190 | I16: X | J16: X | K16: X | M16: - | N16: - | O16: - | P16: -
A17: =VLOOKUP(D17,'Master Data'!A:F,2,FALSE) -> Sara | B17: =VLOOKUP(D17,'Master Data'!A:F,3,FALSE) -> Branca | C17: =VLOOKUP(D17,'Master Data'!A:F,6,FALSE) -> sara.branca@hotmail.com | D17: 0763739954 | F17: =VLOOKUP(D17,'Master Data'!A:F,4,FALSE) -> w | G17: =VLOOKUP(D17,'Master Data'!A:F,5,FALSE) -> Normal | H17: 160 | I17: X | J17: X | K17: X | M17: -
A18: =VLOOKUP(D18,'Master Data'!A:F,2,FALSE) -> Melina | B18: =VLOOKUP(D18,'Master Data'!A:F,3,FALSE) -> Götschi | C18: =VLOOKUP(D18,'Master Data'!A:F,6,FALSE) -> melinagoetschi@outlook.com | D18: 0795371219 | E18: 2. Kurse | F18: =VLOOKUP(D18,'Master Data'!A:F,4,FALSE) -> w | G18: =VLOOKUP(D18,'Master Data'!A:F,5,FALSE) -> Normal | I18: - | J18: X | K18: X | M18: X | N18: -
A19: =VLOOKUP(D19,'Master Data'!A:F,2,FALSE) -> Jacov | B19: =VLOOKUP(D19,'Master Data'!A:F,3,FALSE) -> Bludnikov | C19: =VLOOKUP(D19,'Master Data'!A:F,6,FALSE) -> 04jakov.bludnikov@gmail.com | D19: 0762630712 | F19: =VLOOKUP(D19,'Master Data'!A:F,4,FALSE) -> m | G19: =VLOOKUP(D19,'Master Data'!A:F,5,FALSE) -> Paar | H19: 160 | I19: X | J19: X | K19: X | M19: X
A20: =VLOOKUP(D20,'Master Data'!A:F,2,FALSE) -> Bianca | B20: =VLOOKUP(D20,'Master Data'!A:F,3,FALSE) -> Eichler | C20: =VLOOKUP(D20,'Master Data'!A:F,6,FALSE) -> bianca_eich.woelpp@hotmail.de | D20: 004915208262666 | F20: =VLOOKUP(D20,'Master Data'!A:F,4,FALSE) -> w | G20: =VLOOKUP(D20,'Master Data'!A:F,5,FALSE) -> Normal | H20: 190 | I20: X | J20: X | K20: - | M20: X
A21: =VLOOKUP(D21,'Master Data'!A:F,2,FALSE) -> Sabrina | B21: =VLOOKUP(D21,'Master Data'!A:F,3,FALSE) -> Grube | C21: =VLOOKUP(D21,'Master Data'!A:F,6,FALSE) -> Sabrina.Grube@gmx.net | D21: 00491795531616 | E21: Fehlt 1. Tag | F21: =VLOOKUP(D21,'Master Data'!A:F,4,FALSE) -> w | G21: =VLOOKUP(D21,'Master Data'!A:F,5,FALSE) -> Normal | H21: 190 | I21: - | J21: X | K21: X | M21: -
A22: =VLOOKUP(D22,'Master Data'!A:F,2,FALSE) -> Björn | B22: =VLOOKUP(D22,'Master Data'!A:F,3,FALSE) -> Friebe | C22: =VLOOKUP(D22,'Master Data'!A:F,6,FALSE) -> 0 | D22: 0762141635 | F22: =VLOOKUP(D22,'Master Data'!A:F,4,FALSE) -> m | G22: =VLOOKUP(D22,'Master Data'!A:F,5,FALSE) -> Paar | H22: 410 | I22: X | J22: X | K22: X | M22: x
A23: =VLOOKUP(D23,'Master Data'!A:F,2,FALSE) -> Lea | B23: =VLOOKUP(D23,'Master Data'!A:F,3,FALSE) -> Weibel | C23: =VLOOKUP(D23,'Master Data'!A:F,6,FALSE) -> lw23@bluewin.ch | D23: 0798729078 | F23: =VLOOKUP(D23,'Master Data'!A:F,4,FALSE) -> w | G23: =VLOOKUP(D23,'Master Data'!A:F,5,FALSE) -> Normal | H23: 190 | I23: X | J23: X | K23: X | M23: X | O23: -
A24: =VLOOKUP(D24,'Master Data'!A:F,2,FALSE) -> Marco Alessandro | B24: =VLOOKUP(D24,'Master Data'!A:F,3,FALSE) -> Pedrazzoli | C24: =VLOOKUP(D24,'Master Data'!A:F,6,FALSE) -> pedrazzolimarco07@gmail.com | D24: 0795764947 | E24: 2. Kurse | F24: =VLOOKUP(D24,'Master Data'!A:F,4,FALSE) -> m | G24: =VLOOKUP(D24,'Master Data'!A:F,5,FALSE) -> Normal | H24: 150 | I24: X | J24: X | K24: - | M24: X
A25: =VLOOKUP(D25,'Master Data'!A:F,2,FALSE) -> Magdalena | B25: =VLOOKUP(D25,'Master Data'!A:F,3,FALSE) -> Siedlok | C25: =VLOOKUP(D25,'Master Data'!A:F,6,FALSE) -> magdalena.siedlok@gmail.com | D25: 0767964603 | E25: Vom Freitag nachholen | F25: =VLOOKUP(D25,'Master Data'!A:F,4,FALSE) -> w | G25: =VLOOKUP(D25,'Master Data'!A:F,5,FALSE) -> Normal | H25: 145 | I25: x | J25: x | K25: - | L25: - | M25: - | N25: - | O25: - | P25: -
A26: =VLOOKUP(D26,'Master Data'!A:F,2,FALSE) -> #N/A | B26: =VLOOKUP(D26,'Master Data'!A:F,3,FALSE) -> #N/A | C26: =VLOOKUP(D26,'Master Data'!A:F,6,FALSE) -> #N/A | F26: =VLOOKUP(D26,'Master Data'!A:F,4,FALSE) -> #N/A | G26: =VLOOKUP(D26,'Master Data'!A:F,5,FALSE) -> #N/A
A27: =VLOOKUP(D27,'Master Data'!A:F,2,FALSE) -> #N/A | B27: =VLOOKUP(D27,'Master Data'!A:F,3,FALSE) -> #N/A | C27: =VLOOKUP(D27,'Master Data'!A:F,6,FALSE) -> #N/A | F27: =VLOOKUP(D27,'Master Data'!A:F,4,FALSE) -> #N/A | G27: =VLOOKUP(D27,'Master Data'!A:F,5,FALSE) -> #N/A
A28: =VLOOKUP(D28,'Master Data'!A:F,2,FALSE) -> #N/A | B28: =VLOOKUP(D28,'Master Data'!A:F,3,FALSE) -> #N/A | C28: =VLOOKUP(D28,'Master Data'!A:F,6,FALSE) -> #N/A | F28: =VLOOKUP(D28,'Master Data'!A:F,4,FALSE) -> #N/A | G28: =VLOOKUP(D28,'Master Data'!A:F,5,FALSE) -> #N/A
A29: =VLOOKUP(D29,'Master Data'!A:F,2,FALSE) -> #N/A | B29: =VLOOKUP(D29,'Master Data'!A:F,3,FALSE) -> #N/A | C29: =VLOOKUP(D29,'Master Data'!A:F,6,FALSE) -> #N/A | F29: =VLOOKUP(D29,'Master Data'!A:F,4,FALSE) -> #N/A | G29: =VLOOKUP(D29,'Master Data'!A:F,5,FALSE) -> #N/A
A30: =VLOOKUP(D30,'Master Data'!A:F,2,FALSE) -> #N/A | B30: =VLOOKUP(D30,'Master Data'!A:F,3,FALSE) -> #N/A | C30: =VLOOKUP(D30,'Master Data'!A:F,6,FALSE) -> #N/A | F30: =VLOOKUP(D30,'Master Data'!A:F,4,FALSE) -> #N/A | G30: =VLOOKUP(D30,'Master Data'!A:F,5,FALSE) -> #N/A
A31: =VLOOKUP(D31,'Master Data'!A:F,2,FALSE) -> #N/A | B31: =VLOOKUP(D31,'Master Data'!A:F,3,FALSE) -> #N/A | C31: =VLOOKUP(D31,'Master Data'!A:F,6,FALSE) -> #N/A | F31: =VLOOKUP(D31,'Master Data'!A:F,4,FALSE) -> #N/A | G31: =VLOOKUP(D31,'Master Data'!A:F,5,FALSE) -> #N/A
A32: =VLOOKUP(D32,'Master Data'!A:F,2,FALSE) -> #N/A | B32: =VLOOKUP(D32,'Master Data'!A:F,3,FALSE) -> #N/A | C32: =VLOOKUP(D32,'Master Data'!A:F,5,FALSE) -> #N/A | G32: Einnahmen | H32: =SUM(H7:H31) -> 3675

Sheet Mo_Salsa Beginner Stufe 3
A1: Anmeldungen - Salsa Beginner Stufe 3
A3: Datum: | B3: 05.01.2026 - 02.03.2026 | D3: Kurstag: | E3: Montag | G3: Lehrer: | H3: John
A4: Zeit: | B4: 18:30 - 19:30 | D4: Ort: | E4: Elisabethenanlage 7 | G4: Preis: | H4: CHF 190.- / CHF 160.-
A6: Vorname | B6: Name | C6: E-Mail | D6: Mobile | E6: Bemerkungen | F6: m/w | G6: Tarif | H6: Betrag | I6: Anwesenheit
A7: =VLOOKUP(D7,'Master Data'!A:F,2,FALSE) -> Simone | B7: =VLOOKUP(D7,'Master Data'!A:F,3,FALSE) -> Frey | C7: =VLOOKUP(D7,'Master Data'!A:F,6,FALSE) -> simone-frey@hotmail.de | D7: 0798881391 | F7: =VLOOKUP(D7,'Master Data'!A:F,4,FALSE) -> w | G7: =VLOOKUP(D7,'Master Data'!A:F,5,FALSE) -> Normal | H7: 190 | I7: X | J7: - | L7: - | M7: X | P7: -
A8: =VLOOKUP(D8,'Master Data'!A:F,2,FALSE) -> Nadja | B8: =VLOOKUP(D8,'Master Data'!A:F,3,FALSE) -> Agreda | C8: =VLOOKUP(D8,'Master Data'!A:F,6,FALSE) -> nadja_agreda@hotmail.com | D8: 0787271733 | E8: Helvetia | F8: =VLOOKUP(D8,'Master Data'!A:F,4,FALSE) -> w | G8: =VLOOKUP(D8,'Master Data'!A:F,5,FALSE) -> Paar | H8: 160 | J8: X | M8: X
A9: =VLOOKUP(D9,'Master Data'!A:F,2,FALSE) -> Christian | B9: =VLOOKUP(D9,'Master Data'!A:F,3,FALSE) -> Perren | C9: =VLOOKUP(D9,'Master Data'!A:F,6,FALSE) -> 0 | D9: 0787271733-1 | E9: Helvetia | F9: =VLOOKUP(D9,'Master Data'!A:F,4,FALSE) -> m | G9: =VLOOKUP(D9,'Master Data'!A:F,5,FALSE) -> Paar | H9: 160 | J9: X | M9: X
A10: =VLOOKUP(D10,'Master Data'!A:F,2,FALSE) -> Yasmin | B10: =VLOOKUP(D10,'Master Data'!A:F,3,FALSE) -> Blum | C10: =VLOOKUP(D10,'Master Data'!A:F,6,FALSE) -> blumyas@gmail.com | D10: 0764186668 | F10: =VLOOKUP(D10,'Master Data'!A:F,4,FALSE) -> w | G10: =VLOOKUP(D10,'Master Data'!A:F,5,FALSE) -> Normal | H10: 170 | J10: X | M10: -
A11: =VLOOKUP(D11,'Master Data'!A:F,2,FALSE) -> Marija | B11: =VLOOKUP(D11,'Master Data'!A:F,3,FALSE) -> Milenkovic | C11: =VLOOKUP(D11,'Master Data'!A:F,6,FALSE) -> marijamilenkovic7@hotmail.com | D11: 0788325297 | E11: Salsaflow Pass | F11: =VLOOKUP(D11,'Master Data'!A:F,4,FALSE) -> w | G11: =VLOOKUP(D11,'Master Data'!A:F,5,FALSE) -> Normal | H11: 410 | I11: X | J11: X | M11: X | O11: -
A12: =VLOOKUP(D12,'Master Data'!A:F,2,FALSE) -> Esther | B12: =VLOOKUP(D12,'Master Data'!A:F,3,FALSE) -> Matt | C12: =VLOOKUP(D12,'Master Data'!A:F,6,FALSE) -> ematt@gmx.ch | D12: 0795873438 | F12: m | G12: =VLOOKUP(D12,'Master Data'!A:F,5,FALSE) -> Normal | I12: X | J12: - | M12: X
A13: =VLOOKUP(D13,'Master Data'!A:F,2,FALSE) -> Simão Pedro | B13: =VLOOKUP(D13,'Master Data'!A:F,3,FALSE) -> Oliveira | C13: =VLOOKUP(D13,'Master Data'!A:F,6,FALSE) -> spedro.oliveira@gmail.com | D13: 0033681301330 | F13: =VLOOKUP(D13,'Master Data'!A:F,4,FALSE) -> m | G13: =VLOOKUP(D13,'Master Data'!A:F,5,FALSE) -> Normal | I13: X | J13: X | M13: X
A14: =VLOOKUP(D14,'Master Data'!A:F,2,FALSE) -> Julie | B14: =VLOOKUP(D14,'Master Data'!A:F,3,FALSE) -> Pfenninger | C14: =VLOOKUP(D14,'Master Data'!A:F,6,FALSE) -> j.pfenninger@hotmail.com | D14: 0786277824 | F14: =VLOOKUP(D14,'Master Data'!A:F,4,FALSE) -> w | G14: =VLOOKUP(D14,'Master Data'!A:F,5,FALSE) -> Normal | H14: 285 | I14: X | J14: X | M14: X
A15: =VLOOKUP(D15,'Master Data'!A:F,2,FALSE) -> Simone | B15: =VLOOKUP(D15,'Master Data'!A:F,3,FALSE) -> Schmutz | C15: =VLOOKUP(D15,'Master Data'!A:F,6,FALSE) -> simi_s_88@hotmail.com | D15: 0797374604 | E15: Zahlen später | F15: =VLOOKUP(D15,'Master Data'!A:F,4,FALSE) -> w | G15: =VLOOKUP(D15,'Master Data'!A:F,5,FALSE) -> Normal | H15: 160 | I15: X | J15: X | M15: X
A16: =VLOOKUP(D16,'Master Data'!A:F,2,FALSE) -> Pascal | B16: =VLOOKUP(D16,'Master Data'!A:F,3,FALSE) -> Howald | C16: =VLOOKUP(D16,'Master Data'!A:F,6,FALSE) -> 0 | D16: 0764484023 | E16: Zahlen später | F16: =VLOOKUP(D16,'Master Data'!A:F,4,FALSE) -> m | G16: =VLOOKUP(D16,'Master Data'!A:F,5,FALSE) -> Paar | H16: 160 | I16: X | J16: X | M16: X
A17: =VLOOKUP(D17,'Master Data'!A:F,2,FALSE) -> Inigo | B17: =VLOOKUP(D17,'Master Data'!A:F,3,FALSE) -> de la Maza | C17: =VLOOKUP(D17,'Master Data'!A:F,6,FALSE) -> i.delamaza.prieto@gmail.com | D17: 0795541328 | F17: =VLOOKUP(D17,'Master Data'!A:F,4,FALSE) -> m | G17: =VLOOKUP(D17,'Master Data'!A:F,5,FALSE) -> Normal | H17: 285 | I17: X | J17: X | M17: X
A18: =VLOOKUP(D18,'Master Data'!A:F,2,FALSE) -> Simon | B18: =VLOOKUP(D18,'Master Data'!A:F,3,FALSE) -> Burri | C18: =VLOOKUP(D18,'Master Data'!A:F,6,FALSE) -> simon.henry.burri@gmail.com | D18: 0774461136 | F18: =VLOOKUP(D18,'Master Data'!A:F,4,FALSE) -> m | G18: =VLOOKUP(D18,'Master Data'!A:F,5,FALSE) -> Normal | I18: - | J18: X | L18: - | M18: X | P18: -
A19: =VLOOKUP(D19,'Master Data'!A:F,2,FALSE) -> Christoph | B19: =VLOOKUP(D19,'Master Data'!A:F,3,FALSE) -> Isele | C19: =VLOOKUP(D19,'Master Data'!A:F,6,FALSE) -> christoph.isele@hotmail.de | D19: 0767056863 | F19: =VLOOKUP(D19,'Master Data'!A:F,4,FALSE) -> m | G19: =VLOOKUP(D19,'Master Data'!A:F,5,FALSE) -> Normal | H19: 190 | I19: X | J19: X | M19: X
A20: =VLOOKUP(D20,'Master Data'!A:F,2,FALSE) -> Ivan | B20: =VLOOKUP(D20,'Master Data'!A:F,3,FALSE) -> Zuparic | C20: =VLOOKUP(D20,'Master Data'!A:F,6,FALSE) -> ivan.zuparic@gmx.ch | D20: 0793691732 | E20: 2. Kurse | F20: =VLOOKUP(D20,'Master Data'!A:F,4,FALSE) -> m | G20: =VLOOKUP(D20,'Master Data'!A:F,5,FALSE) -> Normal | I20: - | J20: X | M20: - | N20: - | P20: -
A21: =VLOOKUP(D21,'Master Data'!A:F,2,FALSE) -> Antonio | B21: =VLOOKUP(D21,'Master Data'!A:F,3,FALSE) -> Piazza | C21: =VLOOKUP(D21,'Master Data'!A:F,6,FALSE) -> anpiazza@bluewin.ch | D21: 0793750430 | E21: 0.2 | F21: =VLOOKUP(D21,'Master Data'!A:F,4,FALSE) -> m | G21: =VLOOKUP(D21,'Master Data'!A:F,5,FALSE) -> Paar | H21: 256 | I21: X | J21: X | M21: X
A22: =VLOOKUP(D22,'Master Data'!A:F,2,FALSE) -> Angela | B22: =VLOOKUP(D22,'Master Data'!A:F,3,FALSE) -> Piazza | C22: =VLOOKUP(D22,'Master Data'!A:F,6,FALSE) -> 0 | D22: 0793750430-1 | E22: 0.2 | F22: =VLOOKUP(D22,'Master Data'!A:F,4,FALSE) -> w | G22: =VLOOKUP(D22,'Master Data'!A:F,5,FALSE) -> Paar | I22: X | J22: X | M22: X
A23: =VLOOKUP(D23,'Master Data'!A:F,2,FALSE) -> Alexander | B23: =VLOOKUP(D23,'Master Data'!A:F,3,FALSE) -> Egger | C23: =VLOOKUP(D23,'Master Data'!A:F,6,FALSE) -> 0 | D23: 0774087049 | F23: =VLOOKUP(D23,'Master Data'!A:F,4,FALSE) -> m | G23: =VLOOKUP(D23,'Master Data'!A:F,5,FALSE) -> Paar | H23: 160 | I23: X | J23: X | M23: X
A24: =VLOOKUP(D24,'Master Data'!A:F,2,FALSE) -> Daniela | B24: =VLOOKUP(D24,'Master Data'!A:F,3,FALSE) -> Egger | C24: =VLOOKUP(D24,'Master Data'!A:F,6,FALSE) -> daniela.schaffner@hotmail.com | D24: 0774087049-1 | F24: =VLOOKUP(D24,'Master Data'!A:F,4,FALSE) -> w | G24: =VLOOKUP(D24,'Master Data'!A:F,5,FALSE) -> Paar | H24: 160 | I24: X | J24: X | M24: X
A25: Alexandra soare | B25: =VLOOKUP(D25,'Master Data'!A:F,3,FALSE) -> Soare | C25: =VLOOKUP(D25,'Master Data'!A:F,6,FALSE) -> soare.alexandra95@yahoo.com | D25: 0795606944 | F25: =VLOOKUP(D25,'Master Data'!A:F,4,FALSE) -> w | G25: =VLOOKUP(D25,'Master Data'!A:F,5,FALSE) -> Normal | H25: 190 | I25: X | J25: X | M25: X
A26: =VLOOKUP(D26,'Master Data'!A:F,2,FALSE) -> Ivan | B26: =VLOOKUP(D26,'Master Data'!A:F,3,FALSE) -> Glushenkov | C26: =VLOOKUP(D26,'Master Data'!A:F,6,FALSE) -> ivan.glushenkov.data@gmail.com | D26: 0762636496 | E26: Salsaflow Pass | F26: =VLOOKUP(D26,'Master Data'!A:F,4,FALSE) -> m | G26: =VLOOKUP(D26,'Master Data'!A:F,5,FALSE) -> Normal | J26: X | M26: X
A27: =VLOOKUP(D27,'Master Data'!A:F,2,FALSE) -> Ben | B27: =VLOOKUP(D27,'Master Data'!A:F,3,FALSE) -> Böke | C27: =VLOOKUP(D27,'Master Data'!A:F,6,FALSE) -> ben25boeke@gmail.com | D27: 00491602122888 | E27: Salsaflow Pass | F27: =VLOOKUP(D27,'Master Data'!A:F,4,FALSE) -> m | G27: =VLOOKUP(D27,'Master Data'!A:F,5,FALSE) -> Normal | J27: X | M27: X
A28: =VLOOKUP(D28,'Master Data'!A:F,2,FALSE) -> Meral | B28: =VLOOKUP(D28,'Master Data'!A:F,3,FALSE) -> Bozkiraç | C28: =VLOOKUP(D28,'Master Data'!A:F,6,FALSE) -> meral.bozkirac@gmail.com | D28: 0783342600 | E28: 2. Kurse | F28: =VLOOKUP(D28,'Master Data'!A:F,4,FALSE) -> w | G28: =VLOOKUP(D28,'Master Data'!A:F,5,FALSE) -> Normal | H28: 190 | M28: X
A29: =VLOOKUP(D29,'Master Data'!A:F,2,FALSE) -> David | B29: =VLOOKUP(D29,'Master Data'!A:F,3,FALSE) -> Schwegler | C29: =VLOOKUP(D29,'Master Data'!A:F,6,FALSE) -> davidschweg@gmail.com | D29: 0774907360 | F29: =VLOOKUP(D29,'Master Data'!A:F,4,FALSE) -> m | G29: =VLOOKUP(D29,'Master Data'!A:F,5,FALSE) -> Normal | H29: 190 | M29: X
A30: =VLOOKUP(D30,'Master Data'!A:F,2,FALSE) -> #N/A | B30: =VLOOKUP(D30,'Master Data'!A:F,3,FALSE) -> #N/A | C30: =VLOOKUP(D30,'Master Data'!A:F,6,FALSE) -> #N/A | F30: =VLOOKUP(D30,'Master Data'!A:F,4,FALSE) -> #N/A | G30: =VLOOKUP(D30,'Master Data'!A:F,5,FALSE) -> #N/A
A31: =VLOOKUP(D31,'Master Data'!A:F,2,FALSE) -> #N/A | B31: =VLOOKUP(D31,'Master Data'!A:F,3,FALSE) -> #N/A | C31: =VLOOKUP(D31,'Master Data'!A:F,6,FALSE) -> #N/A | F31: =VLOOKUP(D31,'Master Data'!A:F,4,FALSE) -> #N/A | G31: =VLOOKUP(D31,'Master Data'!A:F,5,FALSE) -> #N/A | M31: .
A32: =VLOOKUP(D32,'Master Data'!A:F,2,FALSE) -> #N/A | B32: =VLOOKUP(D32,'Master Data'!A:F,3,FALSE) -> #N/A | C32: =VLOOKUP(D32,'Master Data'!A:F,5,FALSE) -> #N/A | F32: =VLOOKUP(D32,'Master Data'!A:F,4,FALSE) -> #N/A | G32: =VLOOKUP(D32,'Master Data'!A:F,5,FALSE) -> #N/A | H32: =SUM(H7:H31) -> 3316

Sheet Mo_Salsa Advanced Stufe 17
A1: Anmeldungen - Salsa Advanced Stufe 17
A3: Datum: | B3: 05.01.2026 - 02.03.2026 | D3: Kurstag: | E3: Montag | G3: Lehrer: | H3: Viviana & Sebastian
A4: Zeit: | B4: 19:30 - 20:30 | D4: Ort: | E4: Elisabethenanlage 7 | G4: Preis: | H4: CHF 190.- / CHF 160.-
A6: Vorname | B6: Name | C6: E-Mail | D6: Mobile | E6: Bemerkungen | F6: m/w | G6: Tarif | H6: Betrag | I6: Anwesenheit
A7: =VLOOKUP(D7,'Master Data'!A:F,2,FALSE) -> Manuel | B7: =VLOOKUP(D7,'Master Data'!A:F,3,FALSE) -> Field | C7: =VLOOKUP(D7,'Master Data'!A:F,6,FALSE) -> manu@cantab.net | D7: 0795392476 | F7: =VLOOKUP(D7,'Master Data'!A:F,4,FALSE) -> m | G7: =VLOOKUP(D7,'Master Data'!A:F,5,FALSE) -> Normal | H7: 190 | I7: X | J7: X | K7: X | M7: X | O7: -
A8: =VLOOKUP(D8,'Master Data'!A:F,2,FALSE) -> Gensan | B8: =VLOOKUP(D8,'Master Data'!A:F,3,FALSE) -> Thavarajah | C8: =VLOOKUP(D8,'Master Data'!A:F,6,FALSE) -> gensan.t@hotmail.ch | D8: 0793676399 | F8: =VLOOKUP(D8,'Master Data'!A:F,4,FALSE) -> m | G8: =VLOOKUP(D8,'Master Data'!A:F,5,FALSE) -> Normal | H8: 285 | I8: X | J8: X | K8: X | M8: X
A9: =VLOOKUP(D9,'Master Data'!A:F,2,FALSE) -> Theresa | B9: =VLOOKUP(D9,'Master Data'!A:F,3,FALSE) -> Reiker | C9: =VLOOKUP(D9,'Master Data'!A:F,6,FALSE) -> gvilanovaa@gmail.com | D9: 0799208215 | F9: =VLOOKUP(D9,'Master Data'!A:F,4,FALSE) -> w | G9: =VLOOKUP(D9,'Master Data'!A:F,5,FALSE) -> Paar | H9: 190 | I9: X | J9: X | K9: - | M9: X
A10: =VLOOKUP(D10,'Master Data'!A:F,2,FALSE) -> Mathias | B10: =VLOOKUP(D10,'Master Data'!A:F,3,FALSE) -> Landsrath | C10: =VLOOKUP(D10,'Master Data'!A:F,6,FALSE) -> matila@gmx.de | D10: 0766413136 | F10: =VLOOKUP(D10,'Master Data'!A:F,4,FALSE) -> m | G10: =VLOOKUP(D10,'Master Data'!A:F,5,FALSE) -> Normal | I10: - | J10: X | K10: - | M10: X | N10: -
A11: =VLOOKUP(D11,'Master Data'!A:F,2,FALSE) -> Sarah | B11: =VLOOKUP(D11,'Master Data'!A:F,3,FALSE) -> Imhof | C11: =VLOOKUP(D11,'Master Data'!A:F,6,FALSE) -> sarah.imhof60@gmail.com | D11: 0787478553 | F11: =VLOOKUP(D11,'Master Data'!A:F,4,FALSE) -> w | G11: =VLOOKUP(D11,'Master Data'!A:F,5,FALSE) -> Paar | I11: X | J11: X | K11: X | M11: X | N11: -
A12: =VLOOKUP(D12,'Master Data'!A:F,2,FALSE) -> Moritz | B12: =VLOOKUP(D12,'Master Data'!A:F,3,FALSE) -> Bachmann | C12: =VLOOKUP(D12,'Master Data'!A:F,6,FALSE) -> moritz.bachmann@roche.com | D12: 0033642737725 | F12: =VLOOKUP(D12,'Master Data'!A:F,4,FALSE) -> m | G12: =VLOOKUP(D12,'Master Data'!A:F,5,FALSE) -> Normal | H12: 410 | I12: X | J12: X | K12: - | M12: X | O12: -
A13: =VLOOKUP(D13,'Master Data'!A:F,2,FALSE) -> Merlin | B13: =VLOOKUP(D13,'Master Data'!A:F,3,FALSE) -> Zeugin | C13: =VLOOKUP(D13,'Master Data'!A:F,6,FALSE) -> 0 | D13: 0794542820 | F13: =VLOOKUP(D13,'Master Data'!A:F,4,FALSE) -> m | G13: =VLOOKUP(D13,'Master Data'!A:F,5,FALSE) -> Normal | H13: 190 | I13: - | J13: X | K13: - | L13: - | M13: - | N13: - | O13: -
A14: =VLOOKUP(D14,'Master Data'!A:F,2,FALSE) -> Stephanie | B14: =VLOOKUP(D14,'Master Data'!A:F,3,FALSE) -> Csendes | C14: =VLOOKUP(D14,'Master Data'!A:F,6,FALSE) -> stephanie.csendes@gmail.com | D14: 0764177421 | F14: =VLOOKUP(D14,'Master Data'!A:F,4,FALSE) -> w | G14: =VLOOKUP(D14,'Master Data'!A:F,5,FALSE) -> Normal | I14: X | J14: X | K14: X | M14: X
A15: =VLOOKUP(D15,'Master Data'!A:F,2,FALSE) -> Myriam | B15: =VLOOKUP(D15,'Master Data'!A:F,3,FALSE) -> Aouadi | C15: =VLOOKUP(D15,'Master Data'!A:F,6,FALSE) -> aouadme@gmail.com | D15: 0795404172 | F15: =VLOOKUP(D15,'Master Data'!A:F,4,FALSE) -> w | G15: =VLOOKUP(D15,'Master Data'!A:F,5,FALSE) -> Normal | I15: - | J15: X | K15: X | M15: X
A16: =VLOOKUP(D16,'Master Data'!A:F,2,FALSE) -> #N/A | B16: =VLOOKUP(D16,'Master Data'!A:F,3,FALSE) -> #N/A | C16: =VLOOKUP(D16,'Master Data'!A:F,6,FALSE) -> #N/A | F16: =VLOOKUP(D16,'Master Data'!A:F,4,FALSE) -> #N/A | G16: =VLOOKUP(D16,'Master Data'!A:F,5,FALSE) -> #N/A
A17: =VLOOKUP(D17,'Master Data'!A:F,2,FALSE) -> #N/A | B17: =VLOOKUP(D17,'Master Data'!A:F,3,FALSE) -> #N/A | C17: =VLOOKUP(D17,'Master Data'!A:F,6,FALSE) -> #N/A | F17: =VLOOKUP(D17,'Master Data'!A:F,4,FALSE) -> #N/A | G17: =VLOOKUP(D17,'Master Data'!A:F,5,FALSE) -> #N/A
A18: =VLOOKUP(D18,'Master Data'!A:F,2,FALSE) -> #N/A | B18: =VLOOKUP(D18,'Master Data'!A:F,3,FALSE) -> #N/A | C18: =VLOOKUP(D18,'Master Data'!A:F,6,FALSE) -> #N/A | F18: =VLOOKUP(D18,'Master Data'!A:F,4,FALSE) -> #N/A | G18: =VLOOKUP(D18,'Master Data'!A:F,5,FALSE) -> #N/A
A19: =VLOOKUP(D19,'Master Data'!A:F,2,FALSE) -> #N/A | B19: =VLOOKUP(D19,'Master Data'!A:F,3,FALSE) -> #N/A | C19: =VLOOKUP(D19,'Master Data'!A:F,6,FALSE) -> #N/A | F19: =VLOOKUP(D19,'Master Data'!A:F,4,FALSE) -> #N/A | G19: =VLOOKUP(D19,'Master Data'!A:F,5,FALSE) -> #N/A
A20: =VLOOKUP(D20,'Master Data'!A:F,2,FALSE) -> #N/A | B20: =VLOOKUP(D20,'Master Data'!A:F,3,FALSE) -> #N/A | C20: =VLOOKUP(D20,'Master Data'!A:F,6,FALSE) -> #N/A | F20: =VLOOKUP(D20,'Master Data'!A:F,4,FALSE) -> #N/A | G20: =VLOOKUP(D20,'Master Data'!A:F,5,FALSE) -> #N/A
A21: =VLOOKUP(D21,'Master Data'!A:F,2,FALSE) -> #N/A | B21: =VLOOKUP(D21,'Master Data'!A:F,3,FALSE) -> #N/A | C21: =VLOOKUP(D21,'Master Data'!A:F,6,FALSE) -> #N/A | F21: =VLOOKUP(D21,'Master Data'!A:F,4,FALSE) -> #N/A | G21: =VLOOKUP(D21,'Master Data'!A:F,5,FALSE) -> #N/A
A22: =VLOOKUP(D22,'Master Data'!A:F,2,FALSE) -> #N/A | B22: =VLOOKUP(D22,'Master Data'!A:F,3,FALSE) -> #N/A | C22: =VLOOKUP(D22,'Master Data'!A:F,6,FALSE) -> #N/A | F22: =VLOOKUP(D22,'Master Data'!A:F,4,FALSE) -> #N/A | G22: =VLOOKUP(D22,'Master Data'!A:F,5,FALSE) -> #N/A
A23: =VLOOKUP(D23,'Master Data'!A:F,2,FALSE) -> #N/A | B23: =VLOOKUP(D23,'Master Data'!A:F,3,FALSE) -> #N/A | C23: =VLOOKUP(D23,'Master Data'!A:F,6,FALSE) -> #N/A | F23: =VLOOKUP(D23,'Master Data'!A:F,4,FALSE) -> #N/A | G23: =VLOOKUP(D23,'Master Data'!A:F,5,FALSE) -> #N/A
A24: =VLOOKUP(D24,'Master Data'!A:F,2,FALSE) -> #N/A | B24: =VLOOKUP(D24,'Master Data'!A:F,3,FALSE) -> #N/A | C24: =VLOOKUP(D24,'Master Data'!A:F,6,FALSE) -> #N/A | F24: =VLOOKUP(D24,'Master Data'!A:F,4,FALSE) -> #N/A | G24: =VLOOKUP(D24,'Master Data'!A:F,5,FALSE) -> #N/A
A25: =VLOOKUP(D25,'Master Data'!A:F,2,FALSE) -> #N/A | B25: =VLOOKUP(D25,'Master Data'!A:F,3,FALSE) -> #N/A | C25: =VLOOKUP(D25,'Master Data'!A:F,6,FALSE) -> #N/A | F25: =VLOOKUP(D25,'Master Data'!A:F,4,FALSE) -> #N/A | G25: =VLOOKUP(D25,'Master Data'!A:F,5,FALSE) -> #N/A
A26: =VLOOKUP(D26,'Master Data'!A:F,2,FALSE) -> #N/A | B26: =VLOOKUP(D26,'Master Data'!A:F,3,FALSE) -> #N/A | C26: =VLOOKUP(D26,'Master Data'!A:F,6,FALSE) -> #N/A | F26: =VLOOKUP(D26,'Master Data'!A:F,4,FALSE) -> #N/A | G26: =VLOOKUP(D26,'Master Data'!A:F,5,FALSE) -> #N/A
A27: =VLOOKUP(D27,'Master Data'!A:F,2,FALSE) -> #N/A | B27: =VLOOKUP(D27,'Master Data'!A:F,3,FALSE) -> #N/A | C27: =VLOOKUP(D27,'Master Data'!A:F,6,FALSE) -> #N/A | F27: =VLOOKUP(D27,'Master Data'!A:F,4,FALSE) -> #N/A | G27: =VLOOKUP(D27,'Master Data'!A:F,5,FALSE) -> #N/A
... A31: =VLOOKUP(D31,'Master Data'!A:F,2,FALSE) -> #N/A | B31: =VLOOKUP(D31,'Master Data'!A:F,3,FALSE) -> #N/A | C31: =VLOOKUP(D31,'Master Data'!A:F,6,FALSE) -> #N/A | F31: =VLOOKUP(D31,'Master Data'!A:F,4,FALSE) -> #N/A | G31: =VLOOKUP(D31,'Master Data'!A:F,5,FALSE) -> #N/A
A32: =VLOOKUP(D32,'Master Data'!A:F,2,FALSE) -> #N/A | B32: =VLOOKUP(D32,'Master Data'!A:F,3,FALSE) -> #N/A | C32: =VLOOKUP(D32,'Master Data'!A:F,5,FALSE) -> #N/A | G32: Einnahmen | H32: =SUM(H7:H31) -> 1265

Sheet Mo_Salsa Intermediate Flow
A1: Anmeldungen - Salsa Intermediate Flow
A3: Datum: | B3: 05.01.2026 - 02.03.2026 | D3: Kurstag: | E3: Montag | G3: Lehrer: | H3: Claudia & Maarten
A4: Zeit: | B4: 19:30 - 20:30 | D4: Ort: | E4: Elisabethenanlage 7 | G4: Preis: | H4: CHF 190.- / CHF 160.-
A6: Vorname | B6: Name | C6: E-Mail | D6: Mobile | E6: Bemerkungen | F6: m/w | G6: Tarif | H6: Betrag | I6: Anwesenheit
A7: =VLOOKUP(D7,'Master Data'!A:F,2,FALSE) -> Michelle | B7: =VLOOKUP(D7,'Master Data'!A:F,3,FALSE) -> Wülser | C7: =VLOOKUP(D7,'Master Data'!A:F,6,FALSE) -> michellew@gmx.ch | D7: 0774406365 | F7: =VLOOKUP(D7,'Master Data'!A:F,4,FALSE) -> w | G7: =VLOOKUP(D7,'Master Data'!A:F,5,FALSE) -> Normal | H7: 160 | J7: X | L7: x | M7: x | N7: -
A8: =VLOOKUP(D8,'Master Data'!A:F,2,FALSE) -> Nora | B8: =VLOOKUP(D8,'Master Data'!A:F,3,FALSE) -> Weber | C8: =VLOOKUP(D8,'Master Data'!A:F,6,FALSE) -> nora.weber@outlook.com | D8: 0798536344 | F8: =VLOOKUP(D8,'Master Data'!A:F,4,FALSE) -> w | G8: =VLOOKUP(D8,'Master Data'!A:F,5,FALSE) -> Normal | H8: 190 | I8: X | J8: X | L8: - | M8: x | P8: -
A9: =VLOOKUP(D9,'Master Data'!A:F,2,FALSE) -> Nikki | B9: =VLOOKUP(D9,'Master Data'!A:F,3,FALSE) -> Parsons | C9: =VLOOKUP(D9,'Master Data'!A:F,6,FALSE) -> nikk.a.parsons@gmail.com | D9: 0792229499 | F9: =VLOOKUP(D9,'Master Data'!A:F,4,FALSE) -> w | G9: =VLOOKUP(D9,'Master Data'!A:F,5,FALSE) -> Normal | H9: 90 | I9: X | J9: X | M9: - | N9: - | O9: - | P9: -
A10: =VLOOKUP(D10,'Master Data'!A:F,2,FALSE) -> Helena | B10: =VLOOKUP(D10,'Master Data'!A:F,3,FALSE) -> Comas | C10: =VLOOKUP(D10,'Master Data'!A:F,6,FALSE) -> helenaccreus@gmail.com | D10: 0767812471 | F10: =VLOOKUP(D10,'Master Data'!A:F,4,FALSE) -> w | G10: =VLOOKUP(D10,'Master Data'!A:F,5,FALSE) -> Normal | H10: 190 | I10: - | J10: - | M10: x | N10: - | P10: -
A11: =VLOOKUP(D11,'Master Data'!A:F,2,FALSE) -> Afaf | B11: =VLOOKUP(D11,'Master Data'!A:F,3,FALSE) -> Elkurdi | C11: =VLOOKUP(D11,'Master Data'!A:F,6,FALSE) -> elkurdi_afaf@hotmail.com | D11: 0766035326 | F11: =VLOOKUP(D11,'Master Data'!A:F,4,FALSE) -> w | G11: =VLOOKUP(D11,'Master Data'!A:F,5,FALSE) -> Normal | H11: 228 | I11: x | J11: x | K11: x | L11: x | M11: x | N11: x
A12: =VLOOKUP(D12,'Master Data'!A:F,2,FALSE) -> Daniel | B12: =VLOOKUP(D12,'Master Data'!A:F,3,FALSE) -> Hoffmann | C12: =VLOOKUP(D12,'Master Data'!A:F,6,FALSE) -> daniel.pascal.hoffmann@gmail.com | D12: 0765055780 | F12: =VLOOKUP(D12,'Master Data'!A:F,4,FALSE) -> m | G12: =VLOOKUP(D12,'Master Data'!A:F,5,FALSE) -> Normal | I12: X | J12: X | M12: x
A13: =VLOOKUP(D13,'Master Data'!A:F,2,FALSE) -> Selina | B13: =VLOOKUP(D13,'Master Data'!A:F,3,FALSE) -> Schenker | C13: =VLOOKUP(D13,'Master Data'!A:F,6,FALSE) -> selina.schenker@live.de | D13: 0793283745 | F13: =VLOOKUP(D13,'Master Data'!A:F,4,FALSE) -> w | G13: =VLOOKUP(D13,'Master Data'!A:F,5,FALSE) -> Normal | I13: X | J13: X | M13: x
A14: =VLOOKUP(D14,'Master Data'!A:F,2,FALSE) -> Luca | B14: =VLOOKUP(D14,'Master Data'!A:F,3,FALSE) -> Pertoldi | C14: =VLOOKUP(D14,'Master Data'!A:F,6,FALSE) -> pertoldi@gmx.net | D14: 0763887046 | F14: =VLOOKUP(D14,'Master Data'!A:F,4,FALSE) -> m | G14: =VLOOKUP(D14,'Master Data'!A:F,5,FALSE) -> Normal | H14: 190 | I14: - | J14: X | M14: -
A15: =VLOOKUP(D15,'Master Data'!A:F,2,FALSE) -> Tobias | B15: =VLOOKUP(D15,'Master Data'!A:F,3,FALSE) -> Thommen | C15: =VLOOKUP(D15,'Master Data'!A:F,6,FALSE) -> tobithommen@hotmail.com | D15: 0798115348 | F15: =VLOOKUP(D15,'Master Data'!A:F,4,FALSE) -> m | G15: =VLOOKUP(D15,'Master Data'!A:F,5,FALSE) -> Normal | I15: X | J15: - | K15: - | M15: x | N15: - | O15: -
A16: =VLOOKUP(D16,'Master Data'!A:F,2,FALSE) -> Esther | B16: =VLOOKUP(D16,'Master Data'!A:F,3,FALSE) -> Matt | C16: =VLOOKUP(D16,'Master Data'!A:F,6,FALSE) -> ematt@gmx.ch | D16: 0795873438 | F16: =VLOOKUP(D16,'Master Data'!A:F,4,FALSE) -> w | G16: =VLOOKUP(D16,'Master Data'!A:F,5,FALSE) -> Normal | H16: 285 | I16: X | J16: X | M16: -
A17: =VLOOKUP(D17,'Master Data'!A:F,2,FALSE) -> Lukas | B17: =VLOOKUP(D17,'Master Data'!A:F,3,FALSE) -> Erni | C17: =VLOOKUP(D17,'Master Data'!A:F,6,FALSE) -> ernilweber@icloud.com | D17: 0792141383 | F17: =VLOOKUP(D17,'Master Data'!A:F,4,FALSE) -> m | G17: =VLOOKUP(D17,'Master Data'!A:F,5,FALSE) -> Normal | I17: X | J17: X | M17: x
A18: =VLOOKUP(D18,'Master Data'!A:F,2,FALSE) -> Isabel | B18: =VLOOKUP(D18,'Master Data'!A:F,3,FALSE) -> Reiss | C18: =VLOOKUP(D18,'Master Data'!A:F,6,FALSE) -> Isabelreiss@gmx.de | D18: 00491742016011 | F18: =VLOOKUP(D18,'Master Data'!A:F,4,FALSE) -> w | G18: =VLOOKUP(D18,'Master Data'!A:F,5,FALSE) -> Normal | H18: 190 | I18: X | J18: X | M18: x
A19: =VLOOKUP(D19,'Master Data'!A:F,2,FALSE) -> Sven | B19: =VLOOKUP(D19,'Master Data'!A:F,3,FALSE) -> Hopf | C19: =VLOOKUP(D19,'Master Data'!A:F,6,FALSE) -> svenhopf@hotmail.com | D19: 0795325644 | F19: =VLOOKUP(D19,'Master Data'!A:F,4,FALSE) -> m | G19: =VLOOKUP(D19,'Master Data'!A:F,5,FALSE) -> Normal | H19: 190 | I19: X | J19: X | M19: x
A20: =VLOOKUP(D20,'Master Data'!A:F,2,FALSE) -> Johanna | B20: =VLOOKUP(D20,'Master Data'!A:F,3,FALSE) -> Hoffmann | C20: =VLOOKUP(D20,'Master Data'!A:F,6,FALSE) -> johanna-hoffmann@outlook.com | D20: 0789094058 | F20: =VLOOKUP(D20,'Master Data'!A:F,4,FALSE) -> w | G20: =VLOOKUP(D20,'Master Data'!A:F,5,FALSE) -> Normal | H20: 190 | I20: X | J20: X | M20: x | O20: -
A21: =VLOOKUP(D21,'Master Data'!A:F,2,FALSE) -> Manuela | B21: =VLOOKUP(D21,'Master Data'!A:F,3,FALSE) -> Heymoz | C21: =VLOOKUP(D21,'Master Data'!A:F,6,FALSE) -> m.heymoz@gmx.ch | D21: 0764262929 | F21: =VLOOKUP(D21,'Master Data'!A:F,4,FALSE) -> w | G21: =VLOOKUP(D21,'Master Data'!A:F,5,FALSE) -> Normal | H21: 190 | I21: X | J21: X | K21: - | M21: x
A22: =VLOOKUP(D22,'Master Data'!A:F,2,FALSE) -> Ivan | B22: =VLOOKUP(D22,'Master Data'!A:F,3,FALSE) -> Zuparic | C22: =VLOOKUP(D22,'Master Data'!A:F,6,FALSE) -> ivan.zuparic@gmx.ch | D22: 0793691732 | E22: 2. Kurse | F22: =VLOOKUP(D22,'Master Data'!A:F,4,FALSE) -> m | G22: =VLOOKUP(D22,'Master Data'!A:F,5,FALSE) -> Normal | H22: 285 | I22: - | J22: X | M22: - | N22: - | P22: -
A23: =VLOOKUP(D23,'Master Data'!A:F,2,FALSE) -> Marco Alessandro | B23: =VLOOKUP(D23,'Master Data'!A:F,3,FALSE) -> Pedrazzoli | C23: =VLOOKUP(D23,'Master Data'!A:F,6,FALSE) -> pedrazzolimarco07@gmail.com | D23: 0795764947 | E23: 2. Kurse | F23: =VLOOKUP(D23,'Master Data'!A:F,4,FALSE) -> m | G23: =VLOOKUP(D23,'Master Data'!A:F,5,FALSE) -> Normal | I23: X | J23: X | M23: x
A24: =VLOOKUP(D24,'Master Data'!A:F,2,FALSE) -> Iryna | B24: =VLOOKUP(D24,'Master Data'!A:F,3,FALSE) -> Marrini | C24: =VLOOKUP(D24,'Master Data'!A:F,6,FALSE) -> iryna@marrini.com | D24: 0772655009 | E24: Salsaflow Pass | F24: =VLOOKUP(D24,'Master Data'!A:F,4,FALSE) -> w | G24: =VLOOKUP(D24,'Master Data'!A:F,5,FALSE) -> Normal | I24: X | J24: X | M24: x
A25: =VLOOKUP(D25,'Master Data'!A:F,2,FALSE) -> Nikola | B25: =VLOOKUP(D25,'Master Data'!A:F,3,FALSE) -> Jevtic | C25: =VLOOKUP(D25,'Master Data'!A:F,6,FALSE) -> nikola.jevtic@bluewin.ch | D25: 0796971944 | F25: =VLOOKUP(D25,'Master Data'!A:F,4,FALSE) -> m | G25: =VLOOKUP(D25,'Master Data'!A:F,5,FALSE) -> Normal | I25: X | J25: - | M25: x
A26: =VLOOKUP(D26,'Master Data'!A:F,2,FALSE) -> Ivan | B26: =VLOOKUP(D26,'Master Data'!A:F,3,FALSE) -> Glushenkov | C26: =VLOOKUP(D26,'Master Data'!A:F,6,FALSE) -> ivan.glushenkov.data@gmail.com | D26: 0762636496 | E26: Salsaflow Pass | F26: =VLOOKUP(D26,'Master Data'!A:F,4,FALSE) -> m | G26: =VLOOKUP(D26,'Master Data'!A:F,5,FALSE) -> Normal | I26: X | J26: X | M26: x
A27: =VLOOKUP(D27,'Master Data'!A:F,2,FALSE) -> Burak | B27: =VLOOKUP(D27,'Master Data'!A:F,3,FALSE) -> Yildirim | C27: =VLOOKUP(D27,'Master Data'!A:F,6,FALSE) -> burak.yildirim@gmx.ch | D27: 0795584011 | F27: =VLOOKUP(D27,'Master Data'!A:F,4,FALSE) -> m | G27: =VLOOKUP(D27,'Master Data'!A:F,5,FALSE) -> Normal | I27: - | J27: X | M27: x
A28: =VLOOKUP(D28,'Master Data'!A:F,2,FALSE) -> Yael | B28: =VLOOKUP(D28,'Master Data'!A:F,3,FALSE) -> Hofmann | C28: =VLOOKUP(D28,'Master Data'!A:F,6,FALSE) -> yael_hofmann@hotmail.com | D28: 0794000823 | F28: =VLOOKUP(D28,'Master Data'!A:F,4,FALSE) -> w | G28: =VLOOKUP(D28,'Master Data'!A:F,5,FALSE) -> Student | H28: 190 | I28: X | J28: X | K28: - | L28: - | M28: x
A29: =VLOOKUP(D29,'Master Data'!A:F,2,FALSE) -> Haimo | B29: =VLOOKUP(D29,'Master Data'!A:F,3,FALSE) -> Jöhri | C29: =VLOOKUP(D29,'Master Data'!A:F,6,FALSE) -> paps1408@gmail.com | D29: 0763662642 | F29: =VLOOKUP(D29,'Master Data'!A:F,4,FALSE) -> m | G29: =VLOOKUP(D29,'Master Data'!A:F,5,FALSE) -> Normal | I29: X | J29: X | M29: x | P29: -
A30: =VLOOKUP(D30,'Master Data'!A:F,2,FALSE) -> Jonhattan | B30: =VLOOKUP(D30,'Master Data'!A:F,3,FALSE) -> da Luz | C30: =VLOOKUP(D30,'Master Data'!A:F,6,FALSE) -> jon.daluz@gmail.com | D30: 004915141395445 | F30: =VLOOKUP(D30,'Master Data'!A:F,4,FALSE) -> m | G30: =VLOOKUP(D30,'Master Data'!A:F,5,FALSE) -> Normal | I30: X | J30: X | K30: - | M30: x | O30: -
A31: =VLOOKUP(D31,'Master Data'!A:F,2,FALSE) -> Jill | B31: =VLOOKUP(D31,'Master Data'!A:F,3,FALSE) -> Hoffmann | C31: =VLOOKUP(D31,'Master Data'!A:F,6,FALSE) -> jill.hoffmann@bluewin.ch | D31: 0798730344 | F31: =VLOOKUP(D31,'Master Data'!A:F,4,FALSE) -> w | G31: =VLOOKUP(D31,'Master Data'!A:F,5,FALSE) -> Normal | H31: 190 | I31: X | J31: X | M31: -
A32: =VLOOKUP(D32,'Master Data'!A:F,2,FALSE) -> Leonie | B32: =VLOOKUP(D32,'Master Data'!A:F,3,FALSE) -> Baur | C32: =VLOOKUP(D32,'Master Data'!A:F,6,FALSE) -> leoniebaur@gmx.de | D32: 004915128752067 | F32: =VLOOKUP(D32,'Master Data'!A:F,4,FALSE) -> w | G32: =VLOOKUP(D32,'Master Data'!A:F,5,FALSE) -> Normal | H32: 190 | I32: X | J32: X | M32: x | P32: -
A33: =VLOOKUP(D33,'Master Data'!A:F,2,FALSE) -> Estelle | B33: =VLOOKUP(D33,'Master Data'!A:F,3,FALSE) -> Pierrot | C33: =VLOOKUP(D33,'Master Data'!A:F,6,FALSE) -> stella110@hotmail.fr | D33: 0765235926 | F33: =VLOOKUP(D33,'Master Data'!A:F,4,FALSE) -> w | G33: =VLOOKUP(D33,'Master Data'!A:F,5,FALSE) -> Normal | I33: X | J33: X | M33: x
A34: =VLOOKUP(D34,'Master Data'!A:F,2,FALSE) -> #N/A | B34: =VLOOKUP(D34,'Master Data'!A:F,3,FALSE) -> #N/A | C34: =VLOOKUP(D34,'Master Data'!A:F,5,FALSE) -> #N/A | G34: Einnahmen | H34: =SUM(H7:H33) -> 2948

Sheet Mo_Salsa Beginner Stufe 2
A1: Anmeldungen - Salsa Beginner Stufe 2
A3: Datum: | B3: 05.01.2026 - 02.03.2026 | D3: Kurstag: | E3: Montag | G3: Lehrer: | H3: John
A4: Zeit: | B4: 19:30 - 20:30 | D4: Ort: | E4: Elisabethenanlage 7 | G4: Preis: | H4: CHF 190.- / CHF 160.-
A6: Vorname | B6: Name | C6: E-Mail | D6: Mobile | E6: Bemerkungen | F6: m/w | G6: Tarif | H6: Betrag | I6: Anwesenheit
A7: =VLOOKUP(D7,'Master Data'!A:F,2,FALSE) -> Maria | B7: =VLOOKUP(D7,'Master Data'!A:F,3,FALSE) -> Tapken | C7: =VLOOKUP(D7,'Master Data'!A:F,6,FALSE) -> tapkenmj@gmail.com | D7: 004915168467107 | F7: =VLOOKUP(D7,'Master Data'!A:F,4,FALSE) -> w | G7: =VLOOKUP(D7,'Master Data'!A:F,5,FALSE) -> Normal | H7: 190 | J7: X | M7: -
A8: =VLOOKUP(D8,'Master Data'!A:F,2,FALSE) -> Ben | B8: =VLOOKUP(D8,'Master Data'!A:F,3,FALSE) -> Böke | C8: =VLOOKUP(D8,'Master Data'!A:F,6,FALSE) -> ben25boeke@gmail.com | D8: 00491602122888 | E8: Salsaflow Pass | F8: =VLOOKUP(D8,'Master Data'!A:F,4,FALSE) -> m | G8: =VLOOKUP(D8,'Master Data'!A:F,5,FALSE) -> Normal | J8: X | M8: X
A9: =VLOOKUP(D9,'Master Data'!A:F,2,FALSE) -> Daniel | B9: =VLOOKUP(D9,'Master Data'!A:F,3,FALSE) -> Gysi | C9: =VLOOKUP(D9,'Master Data'!A:F,6,FALSE) -> ehcb.daniel@hotmail.com | D9: 0774037180 | F9: =VLOOKUP(D9,'Master Data'!A:F,4,FALSE) -> m | G9: =VLOOKUP(D9,'Master Data'!A:F,5,FALSE) -> Normal | H9: 135 | I9: X | J9: X | M9: X | N9: - | O9: -
A10: =VLOOKUP(D10,'Master Data'!A:F,2,FALSE) -> Lea | B10: =VLOOKUP(D10,'Master Data'!A:F,3,FALSE) -> Jurisic | C10: =VLOOKUP(D10,'Master Data'!A:F,6,FALSE) -> jurisic_lea@hotmail.com | D10: 0766811821 | F10: =VLOOKUP(D10,'Master Data'!A:F,4,FALSE) -> w | G10: =VLOOKUP(D10,'Master Data'!A:F,5,FALSE) -> Normal | H10: 135 | I10: X | J10: X | M10: X | O10: -
A11: =VLOOKUP(D11,'Master Data'!A:F,2,FALSE) -> Alex | B11: =VLOOKUP(D11,'Master Data'!A:F,3,FALSE) -> Carol Camprecios | C11: =VLOOKUP(D11,'Master Data'!A:F,6,FALSE) -> picard150@gmail.com | D11: 0762007485 | F11: =VLOOKUP(D11,'Master Data'!A:F,4,FALSE) -> m | G11: =VLOOKUP(D11,'Master Data'!A:F,5,FALSE) -> Normal | H11: 100 | I11: X | J11: - | M11: - | N11: - | O11: - | P11: -
A12: =VLOOKUP(D12,'Master Data'!A:F,2,FALSE) -> Marija | B12: =VLOOKUP(D12,'Master Data'!A:F,3,FALSE) -> Milenkovic | C12: =VLOOKUP(D12,'Master Data'!A:F,6,FALSE) -> marijamilenkovic7@hotmail.com | D12: 0788325297 | E12: Salsaflow Pass | F12: =VLOOKUP(D12,'Master Data'!A:F,4,FALSE) -> w | G12: =VLOOKUP(D12,'Master Data'!A:F,5,FALSE) -> Normal | J12: X | M12: X | N12: - | O12: -
A13: =VLOOKUP(D13,'Master Data'!A:F,2,FALSE) -> Sina Maria | B13: =VLOOKUP(D13,'Master Data'!A:F,3,FALSE) -> Schurban | C13: =VLOOKUP(D13,'Master Data'!A:F,6,FALSE) -> sina.schurban@gmx.de | D13: 00491639821908 | F13: =VLOOKUP(D13,'Master Data'!A:F,4,FALSE) -> w | G13: =VLOOKUP(D13,'Master Data'!A:F,5,FALSE) -> Normal | H13: 160 | J13: X | K13: - | M13: X
A14: =VLOOKUP(D14,'Master Data'!A:F,2,FALSE) -> Helena | B14: =VLOOKUP(D14,'Master Data'!A:F,3,FALSE) -> Gens | C14: =VLOOKUP(D14,'Master Data'!A:F,6,FALSE) -> helena.cgens@gmail.com | D14: 0784454023 | E14: halber Kurs | F14: =VLOOKUP(D14,'Master Data'!A:F,4,FALSE) -> w | G14: =VLOOKUP(D14,'Master Data'!A:F,5,FALSE) -> Normal | H14: 95 | I14: - | J14: - | K14: - | L14: X | M14: X | N14: X | O14: X | P14: -
A15: =VLOOKUP(D15,'Master Data'!A:F,2,FALSE) -> Meral | B15: =VLOOKUP(D15,'Master Data'!A:F,3,FALSE) -> Bozkiraç | C15: =VLOOKUP(D15,'Master Data'!A:F,6,FALSE) -> meral.bozkirac@gmail.com | D15: 0783342600 | E15: 2. Kurse | F15: =VLOOKUP(D15,'Master Data'!A:F,4,FALSE) -> w | G15: =VLOOKUP(D15,'Master Data'!A:F,5,FALSE) -> Normal | H15: 95 | J15: X | M15: -
A16: =VLOOKUP(D16,'Master Data'!A:F,2,FALSE) -> Paul | B16: =VLOOKUP(D16,'Master Data'!A:F,3,FALSE) -> Geser | C16: =VLOOKUP(D16,'Master Data'!A:F,6,FALSE) -> paul.geser03@gmail.com | D16: 0796023990 | F16: =VLOOKUP(D16,'Master Data'!A:F,4,FALSE) -> m | G16: =VLOOKUP(D16,'Master Data'!A:F,5,FALSE) -> Paar | H16: 135 | I16: X | J16: X | M16: - | N16: -
A17: =VLOOKUP(D17,'Master Data'!A:F,2,FALSE) -> Raquel | B17: =VLOOKUP(D17,'Master Data'!A:F,3,FALSE) -> Lima | C17: =VLOOKUP(D17,'Master Data'!A:F,6,FALSE) -> rrlima.raquel@gmail.com | D17: 0786682455 | F17: =VLOOKUP(D17,'Master Data'!A:F,4,FALSE) -> w | G17: =VLOOKUP(D17,'Master Data'!A:F,5,FALSE) -> Paar | H17: 135 | I17: X | J17: X | M17: - | N17: -
A18: =VLOOKUP(D18,'Master Data'!A:F,2,FALSE) -> Simon | B18: =VLOOKUP(D18,'Master Data'!A:F,3,FALSE) -> Amstutz | C18: =VLOOKUP(D18,'Master Data'!A:F,6,FALSE) -> simonamstutz96@gmail.com | D18: 0794515889 | F18: =VLOOKUP(D18,'Master Data'!A:F,4,FALSE) -> m | G18: =VLOOKUP(D18,'Master Data'!A:F,5,FALSE) -> Paar | H18: 80 | I18: X | J18: X | M18: X
A19: =VLOOKUP(D19,'Master Data'!A:F,2,FALSE) -> Paloma | B19: =VLOOKUP(D19,'Master Data'!A:F,3,FALSE) -> Castillo Espinoza | C19: =VLOOKUP(D19,'Master Data'!A:F,6,FALSE) -> paloma.castillo@hotmail.com | D19: 0767434494 | F19: =VLOOKUP(D19,'Master Data'!A:F,4,FALSE) -> w | G19: =VLOOKUP(D19,'Master Data'!A:F,5,FALSE) -> Paar | H19: 80 | I19: X | J19: X | M19: -
A20: =VLOOKUP(D20,'Master Data'!A:F,2,FALSE) -> Suelem | B20: =VLOOKUP(D20,'Master Data'!A:F,3,FALSE) -> Izidoro | C20: =VLOOKUP(D20,'Master Data'!A:F,6,FALSE) -> suelem.izidoro@gmx.com | D20: 0798749914 | F20: =VLOOKUP(D20,'Master Data'!A:F,4,FALSE) -> w | G20: =VLOOKUP(D20,'Master Data'!A:F,5,FALSE) -> Normal | H20: 190 | I20: X | J20: X | M20: X
A21: =VLOOKUP(D21,'Master Data'!A:F,2,FALSE) -> Ani | B21: =VLOOKUP(D21,'Master Data'!A:F,3,FALSE) -> Rukhadze | C21: =VLOOKUP(D21,'Master Data'!A:F,6,FALSE) -> ani_rukhadze@yahoo.com | D21: 0767497456 | F21: w | G21: Normal | H21: 190 | I21: X | J21: X | M21: X
A22: =VLOOKUP(D22,'Master Data'!A:F,2,FALSE) -> Valentina | B22: =VLOOKUP(D22,'Master Data'!A:F,3,FALSE) -> Rodriguez | C22: =VLOOKUP(D22,'Master Data'!A:F,6,FALSE) -> valentina.rezia@bluewin.ch | D22: 0799573945 | F22: =VLOOKUP(D22,'Master Data'!A:F,4,FALSE) -> w | G22: =VLOOKUP(D22,'Master Data'!A:F,5,FALSE) -> Paar | H22: 160 | I22: X | J22: X | M22: X
A23: =VLOOKUP(D23,'Master Data'!A:F,2,FALSE) -> Javier | B23: =VLOOKUP(D23,'Master Data'!A:F,3,FALSE) -> Rodriguez | C23: =VLOOKUP(D23,'Master Data'!A:F,6,FALSE) -> jjrv1987@hotmail.com | D23: 0764202316 | F23: =VLOOKUP(D23,'Master Data'!A:F,4,FALSE) -> m | G23: =VLOOKUP(D23,'Master Data'!A:F,5,FALSE) -> Paar | H23: 160 | I23: X | J23: X | L23: - | M23: X | N23: -
A24: =VLOOKUP(D24,'Master Data'!A:F,2,FALSE) -> Bülent | B24: =VLOOKUP(D24,'Master Data'!A:F,3,FALSE) -> Ekinci | C24: =VLOOKUP(D24,'Master Data'!A:F,6,FALSE) -> buelentekinci24@gamil.com | D24: 00491637919721 | E24: Salsaflow Pass | F24: =VLOOKUP(D24,'Master Data'!A:F,4,FALSE) -> m | G24: =VLOOKUP(D24,'Master Data'!A:F,5,FALSE) -> Normal | I24: X | J24: X | M24: X
A25: =VLOOKUP(D25,'Master Data'!A:F,2,FALSE) -> David | B25: =VLOOKUP(D25,'Master Data'!A:F,3,FALSE) -> Schwegler | C25: =VLOOKUP(D25,'Master Data'!A:F,6,FALSE) -> davidschweg@gmail.com | D25: 0774907360 | F25: =VLOOKUP(D25,'Master Data'!A:F,4,FALSE) -> m | G25: =VLOOKUP(D25,'Master Data'!A:F,5,FALSE) -> Normal | M25: X
A26: =VLOOKUP(D26,'Master Data'!A:F,2,FALSE) -> #N/A | B26: =VLOOKUP(D26,'Master Data'!A:F,3,FALSE) -> #N/A | C26: =VLOOKUP(D26,'Master Data'!A:F,6,FALSE) -> #N/A | F26: =VLOOKUP(D26,'Master Data'!A:F,4,FALSE) -> #N/A | G26: =VLOOKUP(D26,'Master Data'!A:F,5,FALSE) -> #N/A
A27: =VLOOKUP(D27,'Master Data'!A:F,2,FALSE) -> #N/A | B27: =VLOOKUP(D27,'Master Data'!A:F,3,FALSE) -> #N/A | C27: =VLOOKUP(D27,'Master Data'!A:F,6,FALSE) -> #N/A | F27: =VLOOKUP(D27,'Master Data'!A:F,4,FALSE) -> #N/A | G27: =VLOOKUP(D27,'Master Data'!A:F,5,FALSE) -> #N/A
A28: =VLOOKUP(D28,'Master Data'!A:F,2,FALSE) -> #N/A | B28: =VLOOKUP(D28,'Master Data'!A:F,3,FALSE) -> #N/A | C28: =VLOOKUP(D28,'Master Data'!A:F,6,FALSE) -> #N/A | F28: =VLOOKUP(D28,'Master Data'!A:F,4,FALSE) -> #N/A | G28: =VLOOKUP(D28,'Master Data'!A:F,5,FALSE) -> #N/A
A29: =VLOOKUP(D29,'Master Data'!A:F,2,FALSE) -> #N/A | B29: =VLOOKUP(D29,'Master Data'!A:F,3,FALSE) -> #N/A | C29: =VLOOKUP(D29,'Master Data'!A:F,6,FALSE) -> #N/A | F29: =VLOOKUP(D29,'Master Data'!A:F,4,FALSE) -> #N/A | G29: =VLOOKUP(D29,'Master Data'!A:F,5,FALSE) -> #N/A
A30: =VLOOKUP(D30,'Master Data'!A:F,2,FALSE) -> #N/A | B30: =VLOOKUP(D30,'Master Data'!A:F,3,FALSE) -> #N/A | C30: =VLOOKUP(D30,'Master Data'!A:F,6,FALSE) -> #N/A | F30: =VLOOKUP(D30,'Master Data'!A:F,4,FALSE) -> #N/A | G30: =VLOOKUP(D30,'Master Data'!A:F,5,FALSE) -> #N/A
A31: =VLOOKUP(D31,'Master Data'!A:F,2,FALSE) -> #N/A | B31: =VLOOKUP(D31,'Master Data'!A:F,3,FALSE) -> #N/A | C31: =VLOOKUP(D31,'Master Data'!A:F,6,FALSE) -> #N/A | F31: =VLOOKUP(D31,'Master Data'!A:F,4,FALSE) -> #N/A | G31: =VLOOKUP(D31,'Master Data'!A:F,5,FALSE) -> #N/A
A32: =VLOOKUP(D32,'Master Data'!A:F,2,FALSE) -> #N/A | B32: =VLOOKUP(D32,'Master Data'!A:F,3,FALSE) -> #N/A | C32: =VLOOKUP(D32,'Master Data'!A:F,5,FALSE) -> #N/A | F32: =VLOOKUP(D32,'Master Data'!A:F,4,FALSE) -> #N/A | G32: =VLOOKUP(D32,'Master Data'!A:F,5,FALSE) -> #N/A | H32: =SUM(H7:H31) -> 2040

Sheet Mo_Salsa Advanced 15
A1: Anmeldungen - Salsa Advanced Stufe 15
A3: Datum: | B3: 05.01.2026 - 02.03.2026 | D3: Kurstag: | E3: Montag | G3: Lehrer: | H3: Viviana & Sebastian
A4: Zeit: | B4: 20:30 - 21:30 | D4: Ort: | E4: Elisabethenanlage 7 | G4: Preis: | H4: CHF 190.- / CHF 160.-
A6: Vorname | B6: Name | C6: E-Mail | D6: Mobile | E6: Bemerkungen | F6: m/w | G6: Tarif | H6: Betrag | I6: Anwesenheit
A7: =VLOOKUP(D7,'Master Data'!A:F,2,FALSE) -> Severine | B7: =VLOOKUP(D7,'Master Data'!A:F,3,FALSE) -> Bonjour | C7: =VLOOKUP(D7,'Master Data'!A:F,6,FALSE) -> Sevi_6738@hotmail.com | D7: 0763030959 | F7: =VLOOKUP(D7,'Master Data'!A:F,4,FALSE) -> w | G7: =VLOOKUP(D7,'Master Data'!A:F,5,FALSE) -> Paar | H7: 190 | I7: X | J7: X | K7: X | M7: X
A8: =VLOOKUP(D8,'Master Data'!A:F,2,FALSE) -> Carlos | B8: =VLOOKUP(D8,'Master Data'!A:F,3,FALSE) -> Garcia | C8: =VLOOKUP(D8,'Master Data'!A:F,6,FALSE) -> rmcagb@yahoo.es | D8: 0786110875 | F8: =VLOOKUP(D8,'Master Data'!A:F,4,FALSE) -> m | G8: =VLOOKUP(D8,'Master Data'!A:F,5,FALSE) -> Normal | H8: 190 | I8: X | J8: X | K8: - | M8: X
A9: =VLOOKUP(D9,'Master Data'!A:F,2,FALSE) -> Mathias | B9: =VLOOKUP(D9,'Master Data'!A:F,3,FALSE) -> Landsrath | C9: =VLOOKUP(D9,'Master Data'!A:F,6,FALSE) -> matila@gmx.de | D9: 0766413136 | F9: =VLOOKUP(D9,'Master Data'!A:F,4,FALSE) -> m | G9: =VLOOKUP(D9,'Master Data'!A:F,5,FALSE) -> Normal | I9: - | J9: X | K9: - | M9: X
A10: =VLOOKUP(D10,'Master Data'!A:F,2,FALSE) -> Jonhattan | B10: =VLOOKUP(D10,'Master Data'!A:F,3,FALSE) -> da Luz | C10: =VLOOKUP(D10,'Master Data'!A:F,6,FALSE) -> jon.daluz@gmail.com | D10: 004915141395445 | F10: =VLOOKUP(D10,'Master Data'!A:F,4,FALSE) -> m | G10: =VLOOKUP(D10,'Master Data'!A:F,5,FALSE) -> Normal | H10: 255 | I10: X | J10: X | K10: - | M10: X | O10: -
A11: =VLOOKUP(D11,'Master Data'!A:F,2,FALSE) -> Lorena | B11: =VLOOKUP(D11,'Master Data'!A:F,3,FALSE) -> von Büren | C11: =VLOOKUP(D11,'Master Data'!A:F,6,FALSE) -> lorena_98@live.de | D11: 0796219577 | F11: =VLOOKUP(D11,'Master Data'!A:F,4,FALSE) -> m | G11: =VLOOKUP(D11,'Master Data'!A:F,5,FALSE) -> Paar | H11: 190 | I11: X | J11: X | K11: X | M11: X | N11: -
A12: =VLOOKUP(D12,'Master Data'!A:F,2,FALSE) -> Elena | B12: =VLOOKUP(D12,'Master Data'!A:F,3,FALSE) -> Buss | C12: =VLOOKUP(D12,'Master Data'!A:F,6,FALSE) -> elena.buss@gmx.ch | D12: 0792656810 | F12: =VLOOKUP(D12,'Master Data'!A:F,4,FALSE) -> w | G12: =VLOOKUP(D12,'Master Data'!A:F,5,FALSE) -> Normal | H12: 120 | I12: X | J12: X | K12: X | M12: X | N12: - | O12: -
A13: =VLOOKUP(D13,'Master Data'!A:F,2,FALSE) -> Sarah | B13: =VLOOKUP(D13,'Master Data'!A:F,3,FALSE) -> Imhof | C13: =VLOOKUP(D13,'Master Data'!A:F,6,FALSE) -> sarah.imhof60@gmail.com | D13: 0787478553 | F13: =VLOOKUP(D13,'Master Data'!A:F,4,FALSE) -> w | G13: =VLOOKUP(D13,'Master Data'!A:F,5,FALSE) -> Paar | I13: - | J13: X | K13: X | M13: X | N13: -
A14: =VLOOKUP(D14,'Master Data'!A:F,2,FALSE) -> Diana | B14: =VLOOKUP(D14,'Master Data'!A:F,3,FALSE) -> Reznik | C14: =VLOOKUP(D14,'Master Data'!A:F,6,FALSE) -> reznikdiana@hotmail.com | D14: 0787134724 | F14: =VLOOKUP(D14,'Master Data'!A:F,4,FALSE) -> w | G14: =VLOOKUP(D14,'Master Data'!A:F,5,FALSE) -> Normal | H14: 285 | I14: X | J14: X | K14: X | M14: X | N14: -
A15: =VLOOKUP(D15,'Master Data'!A:F,2,FALSE) -> Osman | B15: =VLOOKUP(D15,'Master Data'!A:F,3,FALSE) -> Bukari | C15: =VLOOKUP(D15,'Master Data'!A:F,6,FALSE) -> abusco@hotmail.de | D15: 0772225899 | F15: =VLOOKUP(D15,'Master Data'!A:F,4,FALSE) -> m | G15: =VLOOKUP(D15,'Master Data'!A:F,5,FALSE) -> Normal | H15: 190 | I15: - | J15: - | K15: - | M15: X
A16: =VLOOKUP(D16,'Master Data'!A:F,2,FALSE) -> Nicholas | B16: =VLOOKUP(D16,'Master Data'!A:F,3,FALSE) -> Wiedmaier | C16: =VLOOKUP(D16,'Master Data'!A:F,6,FALSE) -> nicholasrwiedmaier@web.de | D16: 004915782965840 | F16: =VLOOKUP(D16,'Master Data'!A:F,4,FALSE) -> m | G16: =VLOOKUP(D16,'Master Data'!A:F,5,FALSE) -> Paar | H16: 160 | I16: X | J16: X | K16: X | M16: X
A17: =VLOOKUP(D17,'Master Data'!A:F,2,FALSE) -> Laura | B17: =VLOOKUP(D17,'Master Data'!A:F,3,FALSE) -> Wiedmaier | C17: =VLOOKUP(D17,'Master Data'!A:F,6,FALSE) -> laurasrsan@gmail.com | D17: 004915786102101 | F17: =VLOOKUP(D17,'Master Data'!A:F,4,FALSE) -> w | G17: =VLOOKUP(D17,'Master Data'!A:F,5,FALSE) -> Paar | H17: 160 | I17: X | J17: X | K17: X | M17: X
A18: =VLOOKUP(D18,'Master Data'!A:F,2,FALSE) -> Valentin | B18: =VLOOKUP(D18,'Master Data'!A:F,3,FALSE) -> Lopez | C18: =VLOOKUP(D18,'Master Data'!A:F,6,FALSE) -> lopez.b.valentin@gmail.com | D18: 0789356789 | F18: =VLOOKUP(D18,'Master Data'!A:F,4,FALSE) -> m | G18: =VLOOKUP(D18,'Master Data'!A:F,5,FALSE) -> Normal | H18: 190 | I18: X | J18: X | K18: X | M18: X
A19: =VLOOKUP(D19,'Master Data'!A:F,2,FALSE) -> Rayan | B19: =VLOOKUP(D19,'Master Data'!A:F,3,FALSE) -> Kieffer | C19: =VLOOKUP(D19,'Master Data'!A:F,6,FALSE) -> rayan.kieffer@gmail.com | D19: 0774619836 | E19: 2. Kurse | F19: =VLOOKUP(D19,'Master Data'!A:F,4,FALSE) -> m | G19: =VLOOKUP(D19,'Master Data'!A:F,5,FALSE) -> Normal | H19: 285 | I19: X | J19: - | K19: - | M19: X
A20: =VLOOKUP(D20,'Master Data'!A:F,2,FALSE) -> Anke | B20: =VLOOKUP(D20,'Master Data'!A:F,3,FALSE) -> Gnann | C20: =VLOOKUP(D20,'Master Data'!A:F,6,FALSE) -> AnkeGnann@gmx.de | D20: 0799093818 | F20: =VLOOKUP(D20,'Master Data'!A:F,4,FALSE) -> w | G20: =VLOOKUP(D20,'Master Data'!A:F,5,FALSE) -> Normal | H20: 160 | I20: - | J20: X | K20: X | M20: X
A21: =VLOOKUP(D21,'Master Data'!A:F,2,FALSE) -> Stephan | B21: =VLOOKUP(D21,'Master Data'!A:F,3,FALSE) -> Helmecke | C21: =VLOOKUP(D21,'Master Data'!A:F,6,FALSE) -> McByte@gmx.de | D21: 0795995529 | F21: =VLOOKUP(D21,'Master Data'!A:F,4,FALSE) -> m | G21: =VLOOKUP(D21,'Master Data'!A:F,5,FALSE) -> Normal | H21: 160 | I21: X | J21: - | K21: X | M21: X
A22: =VLOOKUP(D22,'Master Data'!A:F,2,FALSE) -> #N/A | B22: =VLOOKUP(D22,'Master Data'!A:F,3,FALSE) -> #N/A | C22: =VLOOKUP(D22,'Master Data'!A:F,6,FALSE) -> #N/A | F22: =VLOOKUP(D22,'Master Data'!A:F,4,FALSE) -> #N/A | G22: =VLOOKUP(D22,'Master Data'!A:F,5,FALSE) -> #N/A
A23: =VLOOKUP(D23,'Master Data'!A:F,2,FALSE) -> #N/A | B23: =VLOOKUP(D23,'Master Data'!A:F,3,FALSE) -> #N/A | C23: =VLOOKUP(D23,'Master Data'!A:F,6,FALSE) -> #N/A | F23: =VLOOKUP(D23,'Master Data'!A:F,4,FALSE) -> #N/A | G23: =VLOOKUP(D23,'Master Data'!A:F,5,FALSE) -> #N/A
A24: =VLOOKUP(D24,'Master Data'!A:F,2,FALSE) -> #N/A | B24: =VLOOKUP(D24,'Master Data'!A:F,3,FALSE) -> #N/A | C24: =VLOOKUP(D24,'Master Data'!A:F,6,FALSE) -> #N/A | F24: =VLOOKUP(D24,'Master Data'!A:F,4,FALSE) -> #N/A | G24: =VLOOKUP(D24,'Master Data'!A:F,5,FALSE) -> #N/A
A25: =VLOOKUP(D25,'Master Data'!A:F,2,FALSE) -> #N/A | B25: =VLOOKUP(D25,'Master Data'!A:F,3,FALSE) -> #N/A | C25: =VLOOKUP(D25,'Master Data'!A:F,6,FALSE) -> #N/A | F25: =VLOOKUP(D25,'Master Data'!A:F,4,FALSE) -> #N/A | G25: =VLOOKUP(D25,'Master Data'!A:F,5,FALSE) -> #N/A
A26: =VLOOKUP(D26,'Master Data'!A:F,2,FALSE) -> #N/A | B26: =VLOOKUP(D26,'Master Data'!A:F,3,FALSE) -> #N/A | C26: =VLOOKUP(D26,'Master Data'!A:F,6,FALSE) -> #N/A | F26: =VLOOKUP(D26,'Master Data'!A:F,4,FALSE) -> #N/A | G26: =VLOOKUP(D26,'Master Data'!A:F,5,FALSE) -> #N/A
A27: =VLOOKUP(D27,'Master Data'!A:F,2,FALSE) -> #N/A | B27: =VLOOKUP(D27,'Master Data'!A:F,3,FALSE) -> #N/A | C27: =VLOOKUP(D27,'Master Data'!A:F,6,FALSE) -> #N/A | F27: =VLOOKUP(D27,'Master Data'!A:F,4,FALSE) -> #N/A | G27: =VLOOKUP(D27,'Master Data'!A:F,5,FALSE) -> #N/A
A28: =VLOOKUP(D28,'Master Data'!A:F,2,FALSE) -> #N/A | B28: =VLOOKUP(D28,'Master Data'!A:F,3,FALSE) -> #N/A | C28: =VLOOKUP(D28,'Master Data'!A:F,6,FALSE) -> #N/A | F28: =VLOOKUP(D28,'Master Data'!A:F,4,FALSE) -> #N/A | G28: =VLOOKUP(D28,'Master Data'!A:F,5,FALSE) -> #N/A
A29: =VLOOKUP(D29,'Master Data'!A:F,2,FALSE) -> #N/A | B29: =VLOOKUP(D29,'Master Data'!A:F,3,FALSE) -> #N/A | C29: =VLOOKUP(D29,'Master Data'!A:F,6,FALSE) -> #N/A | F29: =VLOOKUP(D29,'Master Data'!A:F,4,FALSE) -> #N/A | G29: =VLOOKUP(D29,'Master Data'!A:F,5,FALSE) -> #N/A
A30: =VLOOKUP(D30,'Master Data'!A:F,2,FALSE) -> #N/A | B30: =VLOOKUP(D30,'Master Data'!A:F,3,FALSE) -> #N/A | C30: =VLOOKUP(D30,'Master Data'!A:F,6,FALSE) -> #N/A | F30: =VLOOKUP(D30,'Master Data'!A:F,4,FALSE) -> #N/A | G30: =VLOOKUP(D30,'Master Data'!A:F,5,FALSE) -> #N/A
A31: =VLOOKUP(D31,'Master Data'!A:F,2,FALSE) -> #N/A | B31: =VLOOKUP(D31,'Master Data'!A:F,3,FALSE) -> #N/A | C31: =VLOOKUP(D31,'Master Data'!A:F,6,FALSE) -> #N/A | F31: =VLOOKUP(D31,'Master Data'!A:F,4,FALSE) -> #N/A | G31: =VLOOKUP(D31,'Master Data'!A:F,5,FALSE) -> #N/A
A32: =VLOOKUP(D32,'Master Data'!A:F,2,FALSE) -> #N/A | B32: =VLOOKUP(D32,'Master Data'!A:F,3,FALSE) -> #N/A | C32: =VLOOKUP(D32,'Master Data'!A:F,5,FALSE) -> #N/A | G32: Einnahmen | H32: =SUM(H7:H31) -> 2535

Sheet Mo_Salsa Intermediate Stufe 10
A1: Anmeldungen - Salsa Intermediate Stufe 10
A3: Datum: | B3: 05.01.2026 - 02.03.2026 | D3: Kurstag: | E3: Montag | G3: Lehrer: | H3: Claudia & Maarten
A4: Zeit: | B4: 20:30 - 21:30 | D4: Ort: | E4: Elisabethenanlage 7 | G4: Preis: | H4: CHF 190.- / CHF 160.-
A6: Vorname | B6: Name | C6: E-Mail | D6: Mobile | E6: Bemerkungen | F6: m/w | G6: Tarif | H6: Betrag | I6: Anwesenheit
A7: =VLOOKUP(D7,'Master Data'!A:F,2,FALSE) -> János | B7: =VLOOKUP(D7,'Master Data'!A:F,3,FALSE) -> Hatos | C7: =VLOOKUP(D7,'Master Data'!A:F,6,FALSE) -> hatosjanos18@gmail.com | D7: 0766509733 | F7: =VLOOKUP(D7,'Master Data'!A:F,4,FALSE) -> m | G7: =VLOOKUP(D7,'Master Data'!A:F,5,FALSE) -> Normal | H7: 190 | I7: X | J7: X | K7: X | M7: X
A8: =VLOOKUP(D8,'Master Data'!A:F,2,FALSE) -> Marina | B8: =VLOOKUP(D8,'Master Data'!A:F,3,FALSE) -> Pradas Sanchez | C8: =VLOOKUP(D8,'Master Data'!A:F,6,FALSE) -> marinapradassanchez@gmail.com | D8: 0762631508 | F8: =VLOOKUP(D8,'Master Data'!A:F,4,FALSE) -> w | G8: =VLOOKUP(D8,'Master Data'!A:F,5,FALSE) -> Normal | H8: 170 | I8: - | J8: X | K8: X | M8: -
A9: =VLOOKUP(D9,'Master Data'!A:F,2,FALSE) -> Deniz | B9: =VLOOKUP(D9,'Master Data'!A:F,3,FALSE) -> Kaymak | C9: =VLOOKUP(D9,'Master Data'!A:F,6,FALSE) -> deniz.kaymak@unibas.ch | D9: 0764261453 | F9: =VLOOKUP(D9,'Master Data'!A:F,4,FALSE) -> m | G9: =VLOOKUP(D9,'Master Data'!A:F,5,FALSE) -> Paar | H9: 135 | I9: X | J9: X | K9: X | M9: X
A10: =VLOOKUP(D10,'Master Data'!A:F,2,FALSE) -> Nerymar Alejandra | B10: =VLOOKUP(D10,'Master Data'!A:F,3,FALSE) -> Ramirez | C10: =VLOOKUP(D10,'Master Data'!A:F,6,FALSE) -> nervil73@hotmail.com | D10: 0764604695 | F10: =VLOOKUP(D10,'Master Data'!A:F,4,FALSE) -> w | G10: =VLOOKUP(D10,'Master Data'!A:F,5,FALSE) -> Paar | H10: 135 | I10: X | J10: X | K10: X | M10: X
A11: =VLOOKUP(D11,'Master Data'!A:F,2,FALSE) -> Haimo | B11: =VLOOKUP(D11,'Master Data'!A:F,3,FALSE) -> Jöhri | C11: =VLOOKUP(D11,'Master Data'!A:F,6,FALSE) -> paps1408@gmail.com | D11: 0763662642 | E11: Salsaflow Pass | F11: =VLOOKUP(D11,'Master Data'!A:F,4,FALSE) -> m | G11: =VLOOKUP(D11,'Master Data'!A:F,5,FALSE) -> Normal | I11: X | J11: X | K11: X | M11: X | P11: -
A12: =VLOOKUP(D12,'Master Data'!A:F,2,FALSE) -> Onur | B12: =VLOOKUP(D12,'Master Data'!A:F,3,FALSE) -> Erdem | C12: =VLOOKUP(D12,'Master Data'!A:F,6,FALSE) -> erdem-onur@hotmail.com | D12: 0786111634 | F12: =VLOOKUP(D12,'Master Data'!A:F,4,FALSE) -> m | G12: =VLOOKUP(D12,'Master Data'!A:F,5,FALSE) -> Normal | H12: 285 | I12: X | J12: X | K12: X | M12: - | P12: -
A13: =VLOOKUP(D13,'Master Data'!A:F,2,FALSE) -> Burak | B13: =VLOOKUP(D13,'Master Data'!A:F,3,FALSE) -> Yildirim | C13: =VLOOKUP(D13,'Master Data'!A:F,6,FALSE) -> burak.yildirim@gmx.ch | D13: 0795584011 | F13: =VLOOKUP(D13,'Master Data'!A:F,4,FALSE) -> m | G13: =VLOOKUP(D13,'Master Data'!A:F,5,FALSE) -> Normal | I13: - | J13: X | K13: X | M13: X
A14: =VLOOKUP(D14,'Master Data'!A:F,2,FALSE) -> Zita | B14: =VLOOKUP(D14,'Master Data'!A:F,3,FALSE) -> Magyar | C14: =VLOOKUP(D14,'Master Data'!A:F,6,FALSE) -> zita.magyar@yahoo.com | D14: 0798877550 | F14: =VLOOKUP(D14,'Master Data'!A:F,4,FALSE) -> w | G14: =VLOOKUP(D14,'Master Data'!A:F,5,FALSE) -> Normal | H14: 75 | I14: - | J14: X | K14: X | L14: - | M14: - | N14: - | O14: - | P14: -
A15: =VLOOKUP(D15,'Master Data'!A:F,2,FALSE) -> Lorena | B15: =VLOOKUP(D15,'Master Data'!A:F,3,FALSE) -> Mangold | C15: =VLOOKUP(D15,'Master Data'!A:F,6,FALSE) -> lmangold@breitband.ch | D15: 0795279590 | F15: =VLOOKUP(D15,'Master Data'!A:F,4,FALSE) -> w | G15: =VLOOKUP(D15,'Master Data'!A:F,5,FALSE) -> Normal | H15: 285 | I15: X | J15: X | K15: - | M15: X
A16: =VLOOKUP(D16,'Master Data'!A:F,2,FALSE) -> Laura | B16: =VLOOKUP(D16,'Master Data'!A:F,3,FALSE) -> Guercio | C16: =VLOOKUP(D16,'Master Data'!A:F,6,FALSE) -> 0 | D16: 0795553452 | F16: =VLOOKUP(D16,'Master Data'!A:F,4,FALSE) -> w | G16: =VLOOKUP(D16,'Master Data'!A:F,5,FALSE) -> Paar | H16: 190 | I16: - | J16: X | K16: X | M16: X | O16: -
A17: =VLOOKUP(D17,'Master Data'!A:F,2,FALSE) -> Martin | B17: =VLOOKUP(D17,'Master Data'!A:F,3,FALSE) -> Zimmermann | C17: =VLOOKUP(D17,'Master Data'!A:F,6,FALSE) -> info@metzgerei-zimmermann.ch | D17: 0765751964 | F17: =VLOOKUP(D17,'Master Data'!A:F,4,FALSE) -> m | G17: =VLOOKUP(D17,'Master Data'!A:F,5,FALSE) -> Normal | H17: 190 | I17: X | J17: X | K17: X | M17: X
A18: =VLOOKUP(D18,'Master Data'!A:F,2,FALSE) -> Iryna | B18: =VLOOKUP(D18,'Master Data'!A:F,3,FALSE) -> Marrini | C18: =VLOOKUP(D18,'Master Data'!A:F,6,FALSE) -> iryna@marrini.com | D18: 0772655009 | E18: Salsaflow Pass | F18: =VLOOKUP(D18,'Master Data'!A:F,4,FALSE) -> w | G18: =VLOOKUP(D18,'Master Data'!A:F,5,FALSE) -> Normal | H18: 410 | I18: X | J18: X | K18: X | M18: X | O18: -
A19: =VLOOKUP(D19,'Master Data'!A:F,2,FALSE) -> Ivan | B19: =VLOOKUP(D19,'Master Data'!A:F,3,FALSE) -> Glushenkov | C19: =VLOOKUP(D19,'Master Data'!A:F,6,FALSE) -> ivan.glushenkov.data@gmail.com | D19: 0762636496 | E19: SUM UP | F19: =VLOOKUP(D19,'Master Data'!A:F,4,FALSE) -> m | G19: =VLOOKUP(D19,'Master Data'!A:F,5,FALSE) -> Normal | H19: 345 | I19: X | J19: X | K19: X | M19: X
A20: =VLOOKUP(D20,'Master Data'!A:F,2,FALSE) -> #N/A | B20: =VLOOKUP(D20,'Master Data'!A:F,3,FALSE) -> #N/A | C20: =VLOOKUP(D20,'Master Data'!A:F,6,FALSE) -> #N/A | F20: =VLOOKUP(D20,'Master Data'!A:F,4,FALSE) -> #N/A | G20: =VLOOKUP(D20,'Master Data'!A:F,5,FALSE) -> #N/A
A21: =VLOOKUP(D21,'Master Data'!A:F,2,FALSE) -> #N/A | B21: =VLOOKUP(D21,'Master Data'!A:F,3,FALSE) -> #N/A | C21: =VLOOKUP(D21,'Master Data'!A:F,6,FALSE) -> #N/A | F21: =VLOOKUP(D21,'Master Data'!A:F,4,FALSE) -> #N/A | G21: =VLOOKUP(D21,'Master Data'!A:F,5,FALSE) -> #N/A
A22: =VLOOKUP(D22,'Master Data'!A:F,2,FALSE) -> #N/A | B22: =VLOOKUP(D22,'Master Data'!A:F,3,FALSE) -> #N/A | C22: =VLOOKUP(D22,'Master Data'!A:F,6,FALSE) -> #N/A | F22: =VLOOKUP(D22,'Master Data'!A:F,4,FALSE) -> #N/A | G22: =VLOOKUP(D22,'Master Data'!A:F,5,FALSE) -> #N/A
A23: =VLOOKUP(D23,'Master Data'!A:F,2,FALSE) -> #N/A | B23: =VLOOKUP(D23,'Master Data'!A:F,3,FALSE) -> #N/A | C23: =VLOOKUP(D23,'Master Data'!A:F,6,FALSE) -> #N/A | F23: =VLOOKUP(D23,'Master Data'!A:F,4,FALSE) -> #N/A | G23: =VLOOKUP(D23,'Master Data'!A:F,5,FALSE) -> #N/A
A24: =VLOOKUP(D24,'Master Data'!A:F,2,FALSE) -> #N/A | B24: =VLOOKUP(D24,'Master Data'!A:F,3,FALSE) -> #N/A | C24: =VLOOKUP(D24,'Master Data'!A:F,6,FALSE) -> #N/A | F24: =VLOOKUP(D24,'Master Data'!A:F,4,FALSE) -> #N/A | G24: =VLOOKUP(D24,'Master Data'!A:F,5,FALSE) -> #N/A
A25: =VLOOKUP(D25,'Master Data'!A:F,2,FALSE) -> #N/A | B25: =VLOOKUP(D25,'Master Data'!A:F,3,FALSE) -> #N/A | C25: =VLOOKUP(D25,'Master Data'!A:F,6,FALSE) -> #N/A | F25: =VLOOKUP(D25,'Master Data'!A:F,4,FALSE) -> #N/A | G25: =VLOOKUP(D25,'Master Data'!A:F,5,FALSE) -> #N/A
A26: =VLOOKUP(D26,'Master Data'!A:F,2,FALSE) -> #N/A | B26: =VLOOKUP(D26,'Master Data'!A:F,3,FALSE) -> #N/A | C26: =VLOOKUP(D26,'Master Data'!A:F,6,FALSE) -> #N/A | F26: =VLOOKUP(D26,'Master Data'!A:F,4,FALSE) -> #N/A | G26: =VLOOKUP(D26,'Master Data'!A:F,5,FALSE) -> #N/A
A27: =VLOOKUP(D27,'Master Data'!A:F,2,FALSE) -> #N/A | B27: =VLOOKUP(D27,'Master Data'!A:F,3,FALSE) -> #N/A | C27: =VLOOKUP(D27,'Master Data'!A:F,6,FALSE) -> #N/A | F27: =VLOOKUP(D27,'Master Data'!A:F,4,FALSE) -> #N/A | G27: =VLOOKUP(D27,'Master Data'!A:F,5,FALSE) -> #N/A
A28: =VLOOKUP(D28,'Master Data'!A:F,2,FALSE) -> #N/A | B28: =VLOOKUP(D28,'Master Data'!A:F,3,FALSE) -> #N/A | C28: =VLOOKUP(D28,'Master Data'!A:F,6,FALSE) -> #N/A | F28: =VLOOKUP(D28,'Master Data'!A:F,4,FALSE) -> #N/A | G28: =VLOOKUP(D28,'Master Data'!A:F,5,FALSE) -> #N/A
A29: =VLOOKUP(D29,'Master Data'!A:F,2,FALSE) -> #N/A | B29: =VLOOKUP(D29,'Master Data'!A:F,3,FALSE) -> #N/A | C29: =VLOOKUP(D29,'Master Data'!A:F,6,FALSE) -> #N/A | F29: =VLOOKUP(D29,'Master Data'!A:F,4,FALSE) -> #N/A | G29: =VLOOKUP(D29,'Master Data'!A:F,5,FALSE) -> #N/A
A30: =VLOOKUP(D30,'Master Data'!A:F,2,FALSE) -> #N/A | B30: =VLOOKUP(D30,'Master Data'!A:F,3,FALSE) -> #N/A | C30: =VLOOKUP(D30,'Master Data'!A:F,6,FALSE) -> #N/A | F30: =VLOOKUP(D30,'Master Data'!A:F,4,FALSE) -> #N/A | G30: =VLOOKUP(D30,'Master Data'!A:F,5,FALSE) -> #N/A
A31: =VLOOKUP(D31,'Master Data'!A:F,2,FALSE) -> #N/A | B31: =VLOOKUP(D31,'Master Data'!A:F,3,FALSE) -> #N/A | C31: =VLOOKUP(D31,'Master Data'!A:F,6,FALSE) -> #N/A | F31: =VLOOKUP(D31,'Master Data'!A:F,4,FALSE) -> #N/A | G31: =VLOOKUP(D31,'Master Data'!A:F,5,FALSE) -> #N/A
A32: =VLOOKUP(D32,'Master Data'!A:F,2,FALSE) -> #N/A | B32: =VLOOKUP(D32,'Master Data'!A:F,3,FALSE) -> #N/A | C32: =VLOOKUP(D32,'Master Data'!A:F,5,FALSE) -> #N/A | F32: =VLOOKUP(D32,'Master Data'!A:F,4,FALSE) -> #N/A | G32: =VLOOKUP(D32,'Master Data'!A:F,5,FALSE) -> #N/A | H32: =SUM(H7:H31) -> 2410

Sheet Mo_Salsa Beginner Stufe 1
A1: Anmeldungen - Salsa Beginner Stufe 1
A3: Datum: | B3: 05.01.2026 - 02.03.2026 | D3: Kurstag: | E3: Montag | G3: Lehrer: | H3: John
A4: Zeit: | B4: 20:30 - 21:30 | D4: Ort: | E4: Elisabethenanlage 7 | G4: Preis: | H4: CHF 190.- / CHF 160.-
A6: Vorname | B6: Name | C6: E-Mail | D6: Mobile | E6: Bemerkungen | F6: m/w | G6: Tarif | H6: Betrag | I6: Anwesenheit
A7: =VLOOKUP(D7,'Master Data'!A:F,2,FALSE) -> Sina | B7: =VLOOKUP(D7,'Master Data'!A:F,3,FALSE) -> Maier | C7: =VLOOKUP(D7,'Master Data'!A:F,6,FALSE) -> maiers.sina@gmx.de | D7: 004915227742600 | F7: =VLOOKUP(D7,'Master Data'!A:F,4,FALSE) -> w | G7: =VLOOKUP(D7,'Master Data'!A:F,5,FALSE) -> Paar | H7: 160 | I7: X | J7: X | M7: X
A8: =VLOOKUP(D8,'Master Data'!A:F,2,FALSE) -> Julian | B8: =VLOOKUP(D8,'Master Data'!A:F,3,FALSE) -> Degener | C8: =VLOOKUP(D8,'Master Data'!A:F,6,FALSE) -> deg.jul98@gmail.com | D8: 0765778768 | F8: =VLOOKUP(D8,'Master Data'!A:F,4,FALSE) -> m | G8: =VLOOKUP(D8,'Master Data'!A:F,5,FALSE) -> Paar | H8: 160 | I8: X | J8: X | M8: X
A9: =VLOOKUP(D9,'Master Data'!A:F,2,FALSE) -> Tobias | B9: =VLOOKUP(D9,'Master Data'!A:F,3,FALSE) -> Hasler | C9: =VLOOKUP(D9,'Master Data'!A:F,6,FALSE) -> jacqueline.sprecher@vtxmail.ch | D9: 0798440216 | F9: =VLOOKUP(D9,'Master Data'!A:F,4,FALSE) -> m | G9: =VLOOKUP(D9,'Master Data'!A:F,5,FALSE) -> Normal | H9: 190 | I9: X | J9: X | M9: X
A10: =VLOOKUP(D10,'Master Data'!A:F,2,FALSE) -> Paul | B10: =VLOOKUP(D10,'Master Data'!A:F,3,FALSE) -> Böttcher | C10: =VLOOKUP(D10,'Master Data'!A:F,6,FALSE) -> paul.boe@web.de | D10: 004917682586623 | F10: =VLOOKUP(D10,'Master Data'!A:F,4,FALSE) -> m | G10: =VLOOKUP(D10,'Master Data'!A:F,5,FALSE) -> Normal | H10: 160 | I10: X | J10: X | M10: X
A11: =VLOOKUP(D11,'Master Data'!A:F,2,FALSE) -> Vlera | B11: =VLOOKUP(D11,'Master Data'!A:F,3,FALSE) -> Memisi | C11: =VLOOKUP(D11,'Master Data'!A:F,6,FALSE) -> memisi.vlera@gmail.com | D11: 0763316390 | F11: =VLOOKUP(D11,'Master Data'!A:F,4,FALSE) -> w | G11: =VLOOKUP(D11,'Master Data'!A:F,5,FALSE) -> Paar | H11: 135 | I11: X | J11: X | M11: X
A12: =VLOOKUP(D12,'Master Data'!A:F,2,FALSE) -> Dominik | B12: =VLOOKUP(D12,'Master Data'!A:F,3,FALSE) -> Schnoz | C12: =VLOOKUP(D12,'Master Data'!A:F,6,FALSE) -> dominik211942@gmail.com | D12: 0767718111 | F12: =VLOOKUP(D12,'Master Data'!A:F,4,FALSE) -> m | G12: =VLOOKUP(D12,'Master Data'!A:F,5,FALSE) -> Paar | H12: 135 | I12: X | J12: X | M12: X
A13: =VLOOKUP(D13,'Master Data'!A:F,2,FALSE) -> Irene | B13: =VLOOKUP(D13,'Master Data'!A:F,3,FALSE) -> Heinimann | C13: =VLOOKUP(D13,'Master Data'!A:F,6,FALSE) -> irene.heinimann@gmail.com | D13: 0787606064 | F13: =VLOOKUP(D13,'Master Data'!A:F,4,FALSE) -> w | G13: =VLOOKUP(D13,'Master Data'!A:F,5,FALSE) -> Normal | H13: 160 | I13: X | J13: X | M13: X
A14: =VLOOKUP(D14,'Master Data'!A:F,2,FALSE) -> Christoph | B14: =VLOOKUP(D14,'Master Data'!A:F,3,FALSE) -> Heinimann | C14: =VLOOKUP(D14,'Master Data'!A:F,6,FALSE) -> salsaflow.b7g3d0@chm.8shield.net | D14: 0788726686 | F14: =VLOOKUP(D14,'Master Data'!A:F,4,FALSE) -> m | G14: =VLOOKUP(D14,'Master Data'!A:F,5,FALSE) -> Normal | H14: 135 | I14: X | J14: X | M14: X
A15: =VLOOKUP(D15,'Master Data'!A:F,2,FALSE) -> Jacqueline | B15: =VLOOKUP(D15,'Master Data'!A:F,3,FALSE) -> Sprecher | C15: =VLOOKUP(D15,'Master Data'!A:F,6,FALSE) -> jacqueline.sprecher@vtxmail.ch | D15: 0792248588 | F15: =VLOOKUP(D15,'Master Data'!A:F,4,FALSE) -> w | G15: =VLOOKUP(D15,'Master Data'!A:F,5,FALSE) -> Paar | H15: 160 | I15: X | J15: X | M15: X
A16: =VLOOKUP(D16,'Master Data'!A:F,2,FALSE) -> JC | B16: =VLOOKUP(D16,'Master Data'!A:F,3,FALSE) -> Hasler | C16: =VLOOKUP(D16,'Master Data'!A:F,6,FALSE) -> jc-hasler@globalsystem.ch | D16: 0788788333 | F16: =VLOOKUP(D16,'Master Data'!A:F,4,FALSE) -> m | G16: =VLOOKUP(D16,'Master Data'!A:F,5,FALSE) -> Paar | H16: 160 | I16: X | J16: X | M16: X
A17: =VLOOKUP(D17,'Master Data'!A:F,2,FALSE) -> Bülent | B17: =VLOOKUP(D17,'Master Data'!A:F,3,FALSE) -> Ekinci | C17: =VLOOKUP(D17,'Master Data'!A:F,6,FALSE) -> buelentekinci24@gamil.com | D17: 00491637919721 | F17: =VLOOKUP(D17,'Master Data'!A:F,4,FALSE) -> m | G17: =VLOOKUP(D17,'Master Data'!A:F,5,FALSE) -> Normal | I17: X | J17: X | M17: X
A18: =VLOOKUP(D18,'Master Data'!A:F,2,FALSE) -> Yasin | B18: =VLOOKUP(D18,'Master Data'!A:F,3,FALSE) -> Aktas | C18: =VLOOKUP(D18,'Master Data'!A:F,6,FALSE) -> aleyna_yasin@outlook.com | D18: 0762881020 | E18: 20% - Erste Woche Freitag | F18: =VLOOKUP(D18,'Master Data'!A:F,4,FALSE) -> m | G18: =VLOOKUP(D18,'Master Data'!A:F,5,FALSE) -> Paar | H18: 127.5 | I18: - | J18: - | M18: X
A19: =VLOOKUP(D19,'Master Data'!A:F,2,FALSE) -> Aleyna | B19: =VLOOKUP(D19,'Master Data'!A:F,3,FALSE) -> Acar-Aktaş | C19: =VLOOKUP(D19,'Master Data'!A:F,6,FALSE) -> aleyna_yasin@outlook.com | D19: 0762881020-1 | E19: 20% - Erste Woche Freitag | F19: =VLOOKUP(D19,'Master Data'!A:F,4,FALSE) -> w | G19: =VLOOKUP(D19,'Master Data'!A:F,5,FALSE) -> Paar | H19: 127.5 | I19: - | J19: - | M19: X
A20: =VLOOKUP(D20,'Master Data'!A:F,2,FALSE) -> Lara | B20: =VLOOKUP(D20,'Master Data'!A:F,3,FALSE) -> Kuhfeldt | C20: =VLOOKUP(D20,'Master Data'!A:F,6,FALSE) -> larakuhfeldt@icloud.com | D20: 004917645718658 | E20: Vom Mittwoch gewechselt | F20: =VLOOKUP(D20,'Master Data'!A:F,4,FALSE) -> w | G20: =VLOOKUP(D20,'Master Data'!A:F,5,FALSE) -> Paar | H20: 160 | I20: - | J20: - | M20: X
A21: =VLOOKUP(D21,'Master Data'!A:F,2,FALSE) -> Fabian | B21: =VLOOKUP(D21,'Master Data'!A:F,3,FALSE) -> Karsch | C21: =VLOOKUP(D21,'Master Data'!A:F,6,FALSE) -> 0 | D21: 00491743461676 | E21: Vom Mittwoch gewechselt | F21: =VLOOKUP(D21,'Master Data'!A:F,4,FALSE) -> m | G21: =VLOOKUP(D21,'Master Data'!A:F,5,FALSE) -> Paar | H21: 160 | I21: - | J21: - | M21: X
A22: =VLOOKUP(D22,'Master Data'!A:F,2,FALSE) -> #N/A | B22: =VLOOKUP(D22,'Master Data'!A:F,3,FALSE) -> #N/A | C22: =VLOOKUP(D22,'Master Data'!A:F,6,FALSE) -> #N/A | F22: =VLOOKUP(D22,'Master Data'!A:F,4,FALSE) -> #N/A | G22: =VLOOKUP(D22,'Master Data'!A:F,5,FALSE) -> #N/A
A23: =VLOOKUP(D23,'Master Data'!A:F,2,FALSE) -> #N/A | B23: =VLOOKUP(D23,'Master Data'!A:F,3,FALSE) -> #N/A | C23: =VLOOKUP(D23,'Master Data'!A:F,6,FALSE) -> #N/A | F23: =VLOOKUP(D23,'Master Data'!A:F,4,FALSE) -> #N/A | G23: =VLOOKUP(D23,'Master Data'!A:F,5,FALSE) -> #N/A
A24: =VLOOKUP(D24,'Master Data'!A:F,2,FALSE) -> #N/A | B24: =VLOOKUP(D24,'Master Data'!A:F,3,FALSE) -> #N/A | C24: =VLOOKUP(D24,'Master Data'!A:F,6,FALSE) -> #N/A | F24: =VLOOKUP(D24,'Master Data'!A:F,4,FALSE) -> #N/A | G24: =VLOOKUP(D24,'Master Data'!A:F,5,FALSE) -> #N/A
A25: =VLOOKUP(D25,'Master Data'!A:F,2,FALSE) -> #N/A | B25: =VLOOKUP(D25,'Master Data'!A:F,3,FALSE) -> #N/A | C25: =VLOOKUP(D25,'Master Data'!A:F,6,FALSE) -> #N/A | F25: =VLOOKUP(D25,'Master Data'!A:F,4,FALSE) -> #N/A | G25: =VLOOKUP(D25,'Master Data'!A:F,5,FALSE) -> #N/A
A26: =VLOOKUP(D26,'Master Data'!A:F,2,FALSE) -> #N/A | B26: =VLOOKUP(D26,'Master Data'!A:F,3,FALSE) -> #N/A | C26: =VLOOKUP(D26,'Master Data'!A:F,6,FALSE) -> #N/A | F26: =VLOOKUP(D26,'Master Data'!A:F,4,FALSE) -> #N/A | G26: =VLOOKUP(D26,'Master Data'!A:F,5,FALSE) -> #N/A
A27: =VLOOKUP(D27,'Master Data'!A:F,2,FALSE) -> #N/A | B27: =VLOOKUP(D27,'Master Data'!A:F,3,FALSE) -> #N/A | C27: =VLOOKUP(D27,'Master Data'!A:F,6,FALSE) -> #N/A | F27: =VLOOKUP(D27,'Master Data'!A:F,4,FALSE) -> #N/A | G27: =VLOOKUP(D27,'Master Data'!A:F,5,FALSE) -> #N/A
A28: =VLOOKUP(D28,'Master Data'!A:F,2,FALSE) -> #N/A | B28: =VLOOKUP(D28,'Master Data'!A:F,3,FALSE) -> #N/A | C28: =VLOOKUP(D28,'Master Data'!A:F,6,FALSE) -> #N/A | F28: =VLOOKUP(D28,'Master Data'!A:F,4,FALSE) -> #N/A | G28: =VLOOKUP(D28,'Master Data'!A:F,5,FALSE) -> #N/A
A29: =VLOOKUP(D29,'Master Data'!A:F,2,FALSE) -> #N/A | B29: =VLOOKUP(D29,'Master Data'!A:F,3,FALSE) -> #N/A | C29: =VLOOKUP(D29,'Master Data'!A:F,6,FALSE) -> #N/A | F29: =VLOOKUP(D29,'Master Data'!A:F,4,FALSE) -> #N/A | G29: =VLOOKUP(D29,'Master Data'!A:F,5,FALSE) -> #N/A
A30: =VLOOKUP(D30,'Master Data'!A:F,2,FALSE) -> #N/A | B30: =VLOOKUP(D30,'Master Data'!A:F,3,FALSE) -> #N/A | C30: =VLOOKUP(D30,'Master Data'!A:F,6,FALSE) -> #N/A | F30: =VLOOKUP(D30,'Master Data'!A:F,4,FALSE) -> #N/A | G30: =VLOOKUP(D30,'Master Data'!A:F,5,FALSE) -> #N/A
A31: =VLOOKUP(D31,'Master Data'!A:F,2,FALSE) -> #N/A | B31: =VLOOKUP(D31,'Master Data'!A:F,3,FALSE) -> #N/A | C31: =VLOOKUP(D31,'Master Data'!A:F,6,FALSE) -> #N/A | F31: =VLOOKUP(D31,'Master Data'!A:F,4,FALSE) -> #N/A | G31: =VLOOKUP(D31,'Master Data'!A:F,5,FALSE) -> #N/A
A32: =VLOOKUP(D32,'Master Data'!A:F,2,FALSE) -> #N/A | B32: =VLOOKUP(D32,'Master Data'!A:F,3,FALSE) -> #N/A | C32: =VLOOKUP(D32,'Master Data'!A:F,5,FALSE) -> #N/A | F32: =VLOOKUP(D32,'Master Data'!A:F,4,FALSE) -> #N/A | G32: =VLOOKUP(D32,'Master Data'!A:F,5,FALSE) -> #N/A | H32: =SUM(H7:H31) -> 2130

Sheet Di_Salsa Beginner Stufe 2
A1: Anmeldungen - Salsa Beginner Stufe 2
A3: Datum: | B3: 06.01.2026 - 03.03.2026 | D3: Kurstag: | E3: Dienstag | G3: Lehrer: | H3: Jenny & Mihai
A4: Zeit: | B4: 18:30 - 19:30 | D4: Ort: | E4: Elisabethenanlage 7 | G4: Preis: | H4: CHF 190.- / CHF 160.-
A6: Vorname | B6: Name | C6: E-Mail | D6: Mobile | E6: Bemerkungen | F6: m/w | G6: Tarif | H6: Betrag | I6: Anwesenheit
A7: =VLOOKUP(D7,'Master Data'!A:F,2,FALSE) -> Sabrina | B7: =VLOOKUP(D7,'Master Data'!A:F,3,FALSE) -> Stehlin-Flück | C7: =VLOOKUP(D7,'Master Data'!A:F,6,FALSE) -> sabrina.stehlin@hispeed.ch | D7: 0792811108 | F7: =VLOOKUP(D7,'Master Data'!A:F,4,FALSE) -> w | G7: =VLOOKUP(D7,'Master Data'!A:F,5,FALSE) -> Normal | H7: 190 | I7: x | J7: x | K7: x | L7: x | M7: x | N7: x | P7: x | Q7: x
A8: =VLOOKUP(D8,'Master Data'!A:F,2,FALSE) -> Pasquale | B8: =VLOOKUP(D8,'Master Data'!A:F,3,FALSE) -> Cataldo | C8: =VLOOKUP(D8,'Master Data'!A:F,6,FALSE) -> pasquale.cataldo@web.de | D8: 0789840501 | F8: =VLOOKUP(D8,'Master Data'!A:F,4,FALSE) -> m | G8: =VLOOKUP(D8,'Master Data'!A:F,5,FALSE) -> Normal | H8: 190 | I8: x | J8: x | K8: x | L8: x | M8: x | N8: x | P8: x | Q8: x
A9: =VLOOKUP(D9,'Master Data'!A:F,2,FALSE) -> Lena | B9: =VLOOKUP(D9,'Master Data'!A:F,3,FALSE) -> Bremer | C9: =VLOOKUP(D9,'Master Data'!A:F,6,FALSE) -> lena_bremer96@web.de | D9: 0767361357 | F9: m | G9: =VLOOKUP(D9,'Master Data'!A:F,5,FALSE) -> Pushflow | I9: x | J9: x | K9: x | L9: x | M9: x | N9: x | P9: x | Q9: x
A10: =VLOOKUP(D10,'Master Data'!A:F,2,FALSE) -> Constantin | B10: =VLOOKUP(D10,'Master Data'!A:F,3,FALSE) -> Hof | C10: =VLOOKUP(D10,'Master Data'!A:F,6,FALSE) -> constantin.hof@gmx.net | D10: 004917688120457 | F10: =VLOOKUP(D10,'Master Data'!A:F,4,FALSE) -> m | G10: =VLOOKUP(D10,'Master Data'!A:F,5,FALSE) -> Normal | H10: 160 | I10: x | J10: x | K10: x | L10: - | M10: x | N10: x | P10: x | Q10: x
A11: =VLOOKUP(D11,'Master Data'!A:F,2,FALSE) -> Steve | B11: =VLOOKUP(D11,'Master Data'!A:F,3,FALSE) -> Adderson | C11: =VLOOKUP(D11,'Master Data'!A:F,6,FALSE) -> s.adderson@yahoo.com | D11: 0788595656 | F11: =VLOOKUP(D11,'Master Data'!A:F,4,FALSE) -> m | G11: =VLOOKUP(D11,'Master Data'!A:F,5,FALSE) -> Normal | H11: 190 | I11: x | J11: x | K11: x | L11: x | M11: x | N11: x | P11: x | Q11: x
A12: =VLOOKUP(D12,'Master Data'!A:F,2,FALSE) -> Patricia | B12: =VLOOKUP(D12,'Master Data'!A:F,3,FALSE) -> Von Planta | C12: =VLOOKUP(D12,'Master Data'!A:F,6,FALSE) -> patriciavonplanta@gmail.com | D12: 0788028099 | F12: =VLOOKUP(D12,'Master Data'!A:F,4,FALSE) -> w | G12: =VLOOKUP(D12,'Master Data'!A:F,5,FALSE) -> Normal | H12: 190 | I12: - | J12: x | K12: x | L12: x | M12: x | N12: x | P12: x | Q12: x
A13: =VLOOKUP(D13,'Master Data'!A:F,2,FALSE) -> Samuel | B13: =VLOOKUP(D13,'Master Data'!A:F,3,FALSE) -> Balula | C13: =VLOOKUP(D13,'Master Data'!A:F,6,FALSE) -> samuel.balula@gmail.com | D13: 00351926373955 | F13: =VLOOKUP(D13,'Master Data'!A:F,4,FALSE) -> m | G13: =VLOOKUP(D13,'Master Data'!A:F,5,FALSE) -> Normal | H13: 190 | I13: x | J13: x | K13: x | L13: x | M13: x | N13: x | P13: x | Q13: x
A14: =VLOOKUP(D14,'Master Data'!A:F,2,FALSE) -> Rahsan | B14: =VLOOKUP(D14,'Master Data'!A:F,3,FALSE) -> Toptas | C14: =VLOOKUP(D14,'Master Data'!A:F,6,FALSE) -> toptasrahsan@hotmail.ch | D14: 0763714799 | F14: =VLOOKUP(D14,'Master Data'!A:F,4,FALSE) -> w | G14: =VLOOKUP(D14,'Master Data'!A:F,5,FALSE) -> Normal | H14: 190 | I14: x | J14: x | K14: x | L14: x | M14: x | N14: x | P14: x | Q14: x
A15: =VLOOKUP(D15,'Master Data'!A:F,2,FALSE) -> Michael | B15: =VLOOKUP(D15,'Master Data'!A:F,3,FALSE) -> Thommen | C15: =VLOOKUP(D15,'Master Data'!A:F,6,FALSE) -> michi2@gmx.ch | D15: 0799630213 | F15: =VLOOKUP(D15,'Master Data'!A:F,4,FALSE) -> m | G15: =VLOOKUP(D15,'Master Data'!A:F,5,FALSE) -> Normal | H15: 190 | I15: - | J15: x | K15: x | L15: x | M15: x | N15: x | P15: x | Q15: x
A16: =VLOOKUP(D16,'Master Data'!A:F,2,FALSE) -> Heidi | B16: =VLOOKUP(D16,'Master Data'!A:F,3,FALSE) -> Bürgin-Kühne | C16: =VLOOKUP(D16,'Master Data'!A:F,6,FALSE) -> kuehneh@vtxmail.ch | D16: 0786615581 | E16: Fehlen 3 Mal | F16: =VLOOKUP(D16,'Master Data'!A:F,4,FALSE) -> w | G16: =VLOOKUP(D16,'Master Data'!A:F,5,FALSE) -> Paar | H16: 100 | I16: x | J16: - | K16: x | L16: - | M16: x | N16: x | P16: x | Q16: x
A17: =VLOOKUP(D17,'Master Data'!A:F,2,FALSE) -> Neil | B17: =VLOOKUP(D17,'Master Data'!A:F,3,FALSE) -> Bürgin | C17: =VLOOKUP(D17,'Master Data'!A:F,6,FALSE) -> neil.buergin@hotmail.com | D17: 0789766366 | E17: Fehlen 3 Mal | F17: =VLOOKUP(D17,'Master Data'!A:F,4,FALSE) -> m | G17: =VLOOKUP(D17,'Master Data'!A:F,5,FALSE) -> Paar | H17: 85 | I17: x | J17: - | K17: x | L17: - | M17: x | N17: x | P17: x | Q17: x
A18: =VLOOKUP(D18,'Master Data'!A:F,2,FALSE) -> Filipa | B18: =VLOOKUP(D18,'Master Data'!A:F,3,FALSE) -> Ribeiro | C18: =VLOOKUP(D18,'Master Data'!A:F,6,FALSE) -> anafilipafcribeiro@gmail.com | D18: 0779454345 | F18: =VLOOKUP(D18,'Master Data'!A:F,4,FALSE) -> w | G18: =VLOOKUP(D18,'Master Data'!A:F,5,FALSE) -> Normal | H18: 190 | I18: x | J18: x | K18: - | L18: x | M18: x | N18: x | P18: x | Q18: x
A19: =VLOOKUP(D19,'Master Data'!A:F,2,FALSE) -> Ben | B19: =VLOOKUP(D19,'Master Data'!A:F,3,FALSE) -> Böke | C19: =VLOOKUP(D19,'Master Data'!A:F,6,FALSE) -> ben25boeke@gmail.com | D19: 00491602122888 | E19: Salsaflow Pass | F19: =VLOOKUP(D19,'Master Data'!A:F,4,FALSE) -> m | G19: =VLOOKUP(D19,'Master Data'!A:F,5,FALSE) -> Normal | H19: 410 | I19: x | J19: x | K19: x | L19: x | M19: x | N19: x | P19: x | Q19: x
A20: =VLOOKUP(D20,'Master Data'!A:F,2,FALSE) -> Bülent | B20: =VLOOKUP(D20,'Master Data'!A:F,3,FALSE) -> Ekinci | C20: =VLOOKUP(D20,'Master Data'!A:F,6,FALSE) -> buelentekinci24@gamil.com | D20: 00491637919721 | E20: Salsaflow Pass | F20: =VLOOKUP(D20,'Master Data'!A:F,4,FALSE) -> m | G20: =VLOOKUP(D20,'Master Data'!A:F,5,FALSE) -> Normal | H20: 410 | I20: x | J20: x | K20: x | L20: x | M20: x | N20: x | P20: x | Q20: x
A21: =VLOOKUP(D21,'Master Data'!A:F,2,FALSE) -> #N/A | B21: =VLOOKUP(D21,'Master Data'!A:F,3,FALSE) -> #N/A | C21: =VLOOKUP(D21,'Master Data'!A:F,6,FALSE) -> #N/A | F21: =VLOOKUP(D21,'Master Data'!A:F,4,FALSE) -> #N/A | G21: =VLOOKUP(D21,'Master Data'!A:F,5,FALSE) -> #N/A
A22: =VLOOKUP(D22,'Master Data'!A:F,2,FALSE) -> #N/A | B22: =VLOOKUP(D22,'Master Data'!A:F,3,FALSE) -> #N/A | C22: =VLOOKUP(D22,'Master Data'!A:F,6,FALSE) -> #N/A | F22: =VLOOKUP(D22,'Master Data'!A:F,4,FALSE) -> #N/A | G22: =VLOOKUP(D22,'Master Data'!A:F,5,FALSE) -> #N/A
A23: =VLOOKUP(D23,'Master Data'!A:F,2,FALSE) -> #N/A | B23: =VLOOKUP(D23,'Master Data'!A:F,3,FALSE) -> #N/A | C23: =VLOOKUP(D23,'Master Data'!A:F,6,FALSE) -> #N/A | F23: =VLOOKUP(D23,'Master Data'!A:F,4,FALSE) -> #N/A | G23: =VLOOKUP(D23,'Master Data'!A:F,5,FALSE) -> #N/A
A24: =VLOOKUP(D24,'Master Data'!A:F,2,FALSE) -> #N/A | B24: =VLOOKUP(D24,'Master Data'!A:F,3,FALSE) -> #N/A | C24: =VLOOKUP(D24,'Master Data'!A:F,6,FALSE) -> #N/A | F24: =VLOOKUP(D24,'Master Data'!A:F,4,FALSE) -> #N/A | G24: =VLOOKUP(D24,'Master Data'!A:F,5,FALSE) -> #N/A
A25: =VLOOKUP(D25,'Master Data'!A:F,2,FALSE) -> #N/A | B25: =VLOOKUP(D25,'Master Data'!A:F,3,FALSE) -> #N/A | C25: =VLOOKUP(D25,'Master Data'!A:F,6,FALSE) -> #N/A | F25: =VLOOKUP(D25,'Master Data'!A:F,4,FALSE) -> #N/A | G25: =VLOOKUP(D25,'Master Data'!A:F,5,FALSE) -> #N/A
A26: =VLOOKUP(D26,'Master Data'!A:F,2,FALSE) -> #N/A | B26: =VLOOKUP(D26,'Master Data'!A:F,3,FALSE) -> #N/A | C26: =VLOOKUP(D26,'Master Data'!A:F,6,FALSE) -> #N/A | F26: =VLOOKUP(D26,'Master Data'!A:F,4,FALSE) -> #N/A | G26: =VLOOKUP(D26,'Master Data'!A:F,5,FALSE) -> #N/A
A27: =VLOOKUP(D27,'Master Data'!A:F,2,FALSE) -> #N/A | B27: =VLOOKUP(D27,'Master Data'!A:F,3,FALSE) -> #N/A | C27: =VLOOKUP(D27,'Master Data'!A:F,6,FALSE) -> #N/A | F27: =VLOOKUP(D27,'Master Data'!A:F,4,FALSE) -> #N/A | G27: =VLOOKUP(D27,'Master Data'!A:F,5,FALSE) -> #N/A
A28: =VLOOKUP(D28,'Master Data'!A:F,2,FALSE) -> #N/A | B28: =VLOOKUP(D28,'Master Data'!A:F,3,FALSE) -> #N/A | C28: =VLOOKUP(D28,'Master Data'!A:F,6,FALSE) -> #N/A | F28: =VLOOKUP(D28,'Master Data'!A:F,4,FALSE) -> #N/A | G28: =VLOOKUP(D28,'Master Data'!A:F,5,FALSE) -> #N/A
A29: =VLOOKUP(D29,'Master Data'!A:F,2,FALSE) -> #N/A | B29: =VLOOKUP(D29,'Master Data'!A:F,3,FALSE) -> #N/A | C29: =VLOOKUP(D29,'Master Data'!A:F,6,FALSE) -> #N/A | F29: =VLOOKUP(D29,'Master Data'!A:F,4,FALSE) -> #N/A | G29: =VLOOKUP(D29,'Master Data'!A:F,5,FALSE) -> #N/A
A30: =VLOOKUP(D30,'Master Data'!A:F,2,FALSE) -> #N/A | B30: =VLOOKUP(D30,'Master Data'!A:F,3,FALSE) -> #N/A | C30: =VLOOKUP(D30,'Master Data'!A:F,6,FALSE) -> #N/A | F30: =VLOOKUP(D30,'Master Data'!A:F,4,FALSE) -> #N/A | G30: =VLOOKUP(D30,'Master Data'!A:F,5,FALSE) -> #N/A
A31: =VLOOKUP(D31,'Master Data'!A:F,2,FALSE) -> #N/A | B31: =VLOOKUP(D31,'Master Data'!A:F,3,FALSE) -> #N/A | C31: =VLOOKUP(D31,'Master Data'!A:F,6,FALSE) -> #N/A | F31: =VLOOKUP(D31,'Master Data'!A:F,4,FALSE) -> #N/A | G31: =VLOOKUP(D31,'Master Data'!A:F,5,FALSE) -> #N/A
A32: =VLOOKUP(D32,'Master Data'!A:F,2,FALSE) -> #N/A | B32: =VLOOKUP(D32,'Master Data'!A:F,3,FALSE) -> #N/A | C32: =VLOOKUP(D32,'Master Data'!A:F,5,FALSE) -> #N/A | G32: Einnahmen | H32: =SUM(H7:H31) -> 2685

Sheet Di_Salsa Intermediate Stufe 9
A1: Anmeldungen - Salsa Intermediate Stufe 9
A3: Datum: | B3: 06.01.2026 - 03.03.2026 | D3: Kurstag: | E3: Dienstag | G3: Lehrer: | H3: Rena & Fabio
A4: Zeit: | B4: 18:30 - 19:30 | D4: Ort: | E4: Elisabethenanlage 7 | G4: Preis: | H4: CHF 190.- / CHF 160.-
A6: Vorname | B6: Name | C6: E-Mail | D6: Mobile | E6: Bemerkungen | F6: m/w | G6: Tarif | H6: Betrag | I6: Anwesenheit
A7: =VLOOKUP(D7,'Master Data'!A:F,2,FALSE) -> Jessica | B7: =VLOOKUP(D7,'Master Data'!A:F,3,FALSE) -> Bratz Solano | C7: =VLOOKUP(D7,'Master Data'!A:F,6,FALSE) -> jessica.bratzsolano@web.de | D7: 004915228110792 | F7: =VLOOKUP(D7,'Master Data'!A:F,4,FALSE) -> w | G7: =VLOOKUP(D7,'Master Data'!A:F,5,FALSE) -> Normal | H7: 240 | I7: x | J7: x | K7: x | L7: - | M7: x | N7: - | P7: x
A8: =VLOOKUP(D8,'Master Data'!A:F,2,FALSE) -> Natascha | B8: =VLOOKUP(D8,'Master Data'!A:F,3,FALSE) -> Natum | C8: =VLOOKUP(D8,'Master Data'!A:F,6,FALSE) -> naschizone@gmx.ch | D8: 0797961351 | F8: =VLOOKUP(D8,'Master Data'!A:F,4,FALSE) -> w | G8: =VLOOKUP(D8,'Master Data'!A:F,5,FALSE) -> Normal | H8: 190 | I8: x | J8: x | K8: x | L8: x | M8: x | N8: - | P8: x
A9: =VLOOKUP(D9,'Master Data'!A:F,2,FALSE) -> Laszlo | B9: =VLOOKUP(D9,'Master Data'!A:F,3,FALSE) -> Lukacs | C9: =VLOOKUP(D9,'Master Data'!A:F,6,FALSE) -> laci91128@gmail.com | D9: 0036703794124 | F9: =VLOOKUP(D9,'Master Data'!A:F,4,FALSE) -> m | G9: =VLOOKUP(D9,'Master Data'!A:F,5,FALSE) -> Normal | I9: - | J9: x | K9: x | L9: x | M9: x | N9: - | P9: x
A10: =VLOOKUP(D10,'Master Data'!A:F,2,FALSE) -> Larissa | B10: =VLOOKUP(D10,'Master Data'!A:F,3,FALSE) -> Probst | C10: =VLOOKUP(D10,'Master Data'!A:F,6,FALSE) -> larissa.probst@outlook.com | D10: 0783536391 | F10: =VLOOKUP(D10,'Master Data'!A:F,4,FALSE) -> w | G10: =VLOOKUP(D10,'Master Data'!A:F,5,FALSE) -> Normal | H10: 190 | I10: x | J10: - | K10: x | L10: x | M10: x | N10: x | P10: x
A11: =VLOOKUP(D11,'Master Data'!A:F,2,FALSE) -> Raul | B11: =VLOOKUP(D11,'Master Data'!A:F,3,FALSE) -> Penaguião | C11: =VLOOKUP(D11,'Master Data'!A:F,6,FALSE) -> 0 | D11: 00351918697557 | F11: =VLOOKUP(D11,'Master Data'!A:F,4,FALSE) -> m | G11: =VLOOKUP(D11,'Master Data'!A:F,5,FALSE) -> Normal | H11: 145 | I11: - | J11: - | K11: x | L11: x | M11: x | N11: x | P11: -
A12: =VLOOKUP(D12,'Master Data'!A:F,2,FALSE) -> Carolin | B12: =VLOOKUP(D12,'Master Data'!A:F,3,FALSE) -> Warnecke | C12: =VLOOKUP(D12,'Master Data'!A:F,6,FALSE) -> carolinwarnecke@yahoo.de | D12: 0767491286 | F12: =VLOOKUP(D12,'Master Data'!A:F,4,FALSE) -> w | G12: =VLOOKUP(D12,'Master Data'!A:F,5,FALSE) -> Normal | H12: 160 | I12: X | J12: x | K12: x | L12: x | M12: x | N12: x | P12: x
A13: =VLOOKUP(D13,'Master Data'!A:F,2,FALSE) -> Kamila | B13: =VLOOKUP(D13,'Master Data'!A:F,3,FALSE) -> Kowalska | C13: =VLOOKUP(D13,'Master Data'!A:F,6,FALSE) -> kamilazkowalska@gmail.com | D13: 0778148182 | F13: =VLOOKUP(D13,'Master Data'!A:F,4,FALSE) -> w | G13: =VLOOKUP(D13,'Master Data'!A:F,5,FALSE) -> Paar | H13: 160 | I13: x | J13: x | K13: x | L13: x | M13: x | N13: x | P13: x
A14: =VLOOKUP(D14,'Master Data'!A:F,2,FALSE) -> Krzysztof | B14: =VLOOKUP(D14,'Master Data'!A:F,3,FALSE) -> Lorens | C14: =VLOOKUP(D14,'Master Data'!A:F,6,FALSE) -> kristoflorens@gmail.com | D14: 0048505674703 | F14: =VLOOKUP(D14,'Master Data'!A:F,4,FALSE) -> m | G14: =VLOOKUP(D14,'Master Data'!A:F,5,FALSE) -> Paar | H14: 160 | I14: x | J14: x | K14: x | L14: x | M14: x | N14: x | P14: x
A15: =VLOOKUP(D15,'Master Data'!A:F,2,FALSE) -> Ines | B15: =VLOOKUP(D15,'Master Data'!A:F,3,FALSE) -> Zapater | C15: =VLOOKUP(D15,'Master Data'!A:F,6,FALSE) -> ines.zapater@posteo.net | D15: 0767240824 | E15: 2. Kurse | F15: =VLOOKUP(D15,'Master Data'!A:F,4,FALSE) -> w | G15: =VLOOKUP(D15,'Master Data'!A:F,5,FALSE) -> Normal | H15: 285 | I15: - | J15: x | K15: x | L15: x | M15: x | N15: x | P15: x
A16: =VLOOKUP(D16,'Master Data'!A:F,2,FALSE) -> Yael | B16: =VLOOKUP(D16,'Master Data'!A:F,3,FALSE) -> Spira | C16: =VLOOKUP(D16,'Master Data'!A:F,6,FALSE) -> yael.spira@hotmail.com | D16: 0793168634 | F16: =VLOOKUP(D16,'Master Data'!A:F,4,FALSE) -> w | G16: =VLOOKUP(D16,'Master Data'!A:F,5,FALSE) -> Normal | H16: 145 | I16: x | J16: x | K16: x | L16: x | M16: x | N16: x | O16: - | P16: x
A17: =VLOOKUP(D17,'Master Data'!A:F,2,FALSE) -> Bruno | B17: =VLOOKUP(D17,'Master Data'!A:F,3,FALSE) -> Branco | C17: =VLOOKUP(D17,'Master Data'!A:F,6,FALSE) -> bruno_branco_1993@hotmail.com | D17: 0764948929 | F17: =VLOOKUP(D17,'Master Data'!A:F,4,FALSE) -> m | G17: =VLOOKUP(D17,'Master Data'!A:F,5,FALSE) -> Familie | I17: x | J17: x | K17: x | L17: - | M17: x | N17: x | P17: x
A18: =VLOOKUP(D18,'Master Data'!A:F,2,FALSE) -> Messias | B18: =VLOOKUP(D18,'Master Data'!A:F,3,FALSE) -> Romano | C18: =VLOOKUP(D18,'Master Data'!A:F,6,FALSE) -> sandra.couteiro@sunrise.ch | D18: 0764971909 | F18: =VLOOKUP(D18,'Master Data'!A:F,4,FALSE) -> m | G18: =VLOOKUP(D18,'Master Data'!A:F,5,FALSE) -> Familie | I18: - | J18: x | K18: x | L18: x | M18: x | N18: x | P18: x
A19: =VLOOKUP(D19,'Master Data'!A:F,2,FALSE) -> Estelle | B19: =VLOOKUP(D19,'Master Data'!A:F,3,FALSE) -> Pierrot | C19: =VLOOKUP(D19,'Master Data'!A:F,6,FALSE) -> stella110@hotmail.fr | D19: 0765235926 | E19: Salsaflow Pass | F19: =VLOOKUP(D19,'Master Data'!A:F,4,FALSE) -> w | G19: =VLOOKUP(D19,'Master Data'!A:F,5,FALSE) -> Normal | I19: x | J19: x | K19: x | L19: x | M19: x | N19: - | P19: -
A20: =VLOOKUP(D20,'Master Data'!A:F,2,FALSE) -> Yvo | B20: =VLOOKUP(D20,'Master Data'!A:F,3,FALSE) -> Brügger | C20: =VLOOKUP(D20,'Master Data'!A:F,6,FALSE) -> yvo.bruegger@gmx.ch | D20: 0774667852 | F20: =VLOOKUP(D20,'Master Data'!A:F,4,FALSE) -> m | G20: =VLOOKUP(D20,'Master Data'!A:F,5,FALSE) -> Normal | H20: 190 | I20: x | J20: x | K20: - | L20: x | M20: x | N20: x | P20: x
A21: =VLOOKUP(D21,'Master Data'!A:F,2,FALSE) -> Kalin | B21: =VLOOKUP(D21,'Master Data'!A:F,3,FALSE) -> Marinov | C21: =VLOOKUP(D21,'Master Data'!A:F,6,FALSE) -> kalin.marinov977@gmail.com | D21: 0798122926 | E21: Salsaflow Pass | F21: =VLOOKUP(D21,'Master Data'!A:F,4,FALSE) -> m | G21: =VLOOKUP(D21,'Master Data'!A:F,5,FALSE) -> Normal | I21: - | J21: x | K21: x | L21: x | M21: x | N21: - | P21: -
A22: =VLOOKUP(D22,'Master Data'!A:F,2,FALSE) -> Ivan | B22: =VLOOKUP(D22,'Master Data'!A:F,3,FALSE) -> Glushenkov | C22: =VLOOKUP(D22,'Master Data'!A:F,6,FALSE) -> ivan.glushenkov.data@gmail.com | D22: 0762636496 | E22: Salsaflow Pass | F22: =VLOOKUP(D22,'Master Data'!A:F,4,FALSE) -> m | G22: =VLOOKUP(D22,'Master Data'!A:F,5,FALSE) -> Normal | I22: x | J22: x | K22: x | L22: x | M22: x | N22: x | P22: x
A23: =VLOOKUP(D23,'Master Data'!A:F,2,FALSE) -> David | B23: =VLOOKUP(D23,'Master Data'!A:F,3,FALSE) -> Rubio Hermosa | C23: =VLOOKUP(D23,'Master Data'!A:F,6,FALSE) -> david.rubiohermosa@gmail.com | D23: 0796673360 | F23: =VLOOKUP(D23,'Master Data'!A:F,4,FALSE) -> m | G23: =VLOOKUP(D23,'Master Data'!A:F,5,FALSE) -> Normal | H23: 170 | I23: - | J23: x | K23: x | L23: x | M23: - | N23: x | P23: -
A24: =VLOOKUP(D24,'Master Data'!A:F,2,FALSE) -> Björn | B24: =VLOOKUP(D24,'Master Data'!A:F,3,FALSE) -> Friebe | C24: =VLOOKUP(D24,'Master Data'!A:F,6,FALSE) -> 0 | D24: 0762141635 | F24: =VLOOKUP(D24,'Master Data'!A:F,4,FALSE) -> m | G24: =VLOOKUP(D24,'Master Data'!A:F,5,FALSE) -> Paar | I24: x | J24: x | K24: x | L24: x | M24: x | N24: x | P24: x
A25: =VLOOKUP(D25,'Master Data'!A:F,2,FALSE) -> Doinita | B25: =VLOOKUP(D25,'Master Data'!A:F,3,FALSE) -> Deliu | C25: =VLOOKUP(D25,'Master Data'!A:F,6,FALSE) -> d.doinita98@yahoo.com | D25: 0782266690 | F25: =VLOOKUP(D25,'Master Data'!A:F,4,FALSE) -> w | G25: =VLOOKUP(D25,'Master Data'!A:F,5,FALSE) -> Normal | H25: 190 | I25: x | J25: x | K25: - | L25: x | M25: x | N25: x | P25: x
A26: =VLOOKUP(D26,'Master Data'!A:F,2,FALSE) -> Magalie | B26: =VLOOKUP(D26,'Master Data'!A:F,3,FALSE) -> Müller | C26: =VLOOKUP(D26,'Master Data'!A:F,6,FALSE) -> Magalie.mueller@gmail.com | D26: 0762616678 | F26: =VLOOKUP(D26,'Master Data'!A:F,4,FALSE) -> w | G26: =VLOOKUP(D26,'Master Data'!A:F,5,FALSE) -> Normal | H26: 190 | I26: x | J26: x | K26: x | L26: - | M26: x | N26: - | P26: x
A27: =VLOOKUP(D27,'Master Data'!A:F,2,FALSE) -> #N/A | B27: =VLOOKUP(D27,'Master Data'!A:F,3,FALSE) -> #N/A | C27: =VLOOKUP(D27,'Master Data'!A:F,6,FALSE) -> #N/A | F27: =VLOOKUP(D27,'Master Data'!A:F,4,FALSE) -> #N/A | G27: =VLOOKUP(D27,'Master Data'!A:F,5,FALSE) -> #N/A
A28: =VLOOKUP(D28,'Master Data'!A:F,2,FALSE) -> #N/A | B28: =VLOOKUP(D28,'Master Data'!A:F,3,FALSE) -> #N/A | C28: =VLOOKUP(D28,'Master Data'!A:F,6,FALSE) -> #N/A | F28: =VLOOKUP(D28,'Master Data'!A:F,4,FALSE) -> #N/A | G28: =VLOOKUP(D28,'Master Data'!A:F,5,FALSE) -> #N/A
A29: =VLOOKUP(D29,'Master Data'!A:F,2,FALSE) -> #N/A | B29: =VLOOKUP(D29,'Master Data'!A:F,3,FALSE) -> #N/A | C29: =VLOOKUP(D29,'Master Data'!A:F,6,FALSE) -> #N/A | F29: =VLOOKUP(D29,'Master Data'!A:F,4,FALSE) -> #N/A | G29: =VLOOKUP(D29,'Master Data'!A:F,5,FALSE) -> #N/A
A30: =VLOOKUP(D30,'Master Data'!A:F,2,FALSE) -> #N/A | B30: =VLOOKUP(D30,'Master Data'!A:F,3,FALSE) -> #N/A | C30: =VLOOKUP(D30,'Master Data'!A:F,6,FALSE) -> #N/A | F30: =VLOOKUP(D30,'Master Data'!A:F,4,FALSE) -> #N/A | G30: =VLOOKUP(D30,'Master Data'!A:F,5,FALSE) -> #N/A
A31: =VLOOKUP(D31,'Master Data'!A:F,2,FALSE) -> #N/A | B31: =VLOOKUP(D31,'Master Data'!A:F,3,FALSE) -> #N/A | C31: =VLOOKUP(D31,'Master Data'!A:F,6,FALSE) -> #N/A | F31: =VLOOKUP(D31,'Master Data'!A:F,4,FALSE) -> #N/A | G31: =VLOOKUP(D31,'Master Data'!A:F,5,FALSE) -> #N/A
A32: =VLOOKUP(D32,'Master Data'!A:F,2,FALSE) -> #N/A | B32: =VLOOKUP(D32,'Master Data'!A:F,3,FALSE) -> #N/A | C32: =VLOOKUP(D32,'Master Data'!A:F,5,FALSE) -> #N/A | G32: Einnahmen | H32: =SUM(H7:H31) -> 2415

Sheet Di_Basics & Fundamentals
A1: Anmeldungen - Basics & Fundamentals
A3: Datum: | B3: 06.01.2026 - 03.03.2026 | D3: Kurstag: | E3: Dienstag | G3: Lehrer: | H3: Mihai
A4: Zeit: | B4: 19:30 - 20:30 | D4: Ort: | E4: Elisabethenanlage 7 | G4: Preis: | H4: CHF 190.- / CHF 160.-
A6: Vorname | B6: Name | C6: E-Mail | D6: Mobile | E6: Bemerkungen | F6: m/w | G6: Tarif | H6: Betrag | I6: Anwesenheit
A7: =VLOOKUP(D7,'Master Data'!A:F,2,FALSE) -> Estelle | B7: =VLOOKUP(D7,'Master Data'!A:F,3,FALSE) -> Pierrot | C7: =VLOOKUP(D7,'Master Data'!A:F,6,FALSE) -> stella110@hotmail.fr | D7: 0765235926 | F7: =VLOOKUP(D7,'Master Data'!A:F,4,FALSE) -> w | G7: =VLOOKUP(D7,'Master Data'!A:F,5,FALSE) -> Normal | I7: - | J7: x | K7: x | L7: x | M7: x | N7: x | P7: x
A8: =VLOOKUP(D8,'Master Data'!A:F,2,FALSE) -> Iryna | B8: =VLOOKUP(D8,'Master Data'!A:F,3,FALSE) -> Marrini | C8: =VLOOKUP(D8,'Master Data'!A:F,6,FALSE) -> iryna@marrini.com | D8: 0772655009 | E8: Salsaflow Pass | F8: =VLOOKUP(D8,'Master Data'!A:F,4,FALSE) -> w | G8: =VLOOKUP(D8,'Master Data'!A:F,5,FALSE) -> Normal | I8: x | J8: x | K8: x | L8: x | M8: x | N8: x | P8: x
A9: =VLOOKUP(D9,'Master Data'!A:F,2,FALSE) -> Kalin | B9: =VLOOKUP(D9,'Master Data'!A:F,3,FALSE) -> Marinov | C9: =VLOOKUP(D9,'Master Data'!A:F,6,FALSE) -> kalin.marinov977@gmail.com | D9: 0798122926 | E9: Salsaflow Pass | F9: =VLOOKUP(D9,'Master Data'!A:F,4,FALSE) -> m | G9: =VLOOKUP(D9,'Master Data'!A:F,5,FALSE) -> Normal | I9: - | J9: x | K9: x | L9: x | M9: x | N9: x | P9: x
A10: =VLOOKUP(D10,'Master Data'!A:F,2,FALSE) -> Burak | B10: =VLOOKUP(D10,'Master Data'!A:F,3,FALSE) -> Yildirim | C10: =VLOOKUP(D10,'Master Data'!A:F,6,FALSE) -> burak.yildirim@gmx.ch | D10: 0795584011 | F10: =VLOOKUP(D10,'Master Data'!A:F,4,FALSE) -> m | G10: =VLOOKUP(D10,'Master Data'!A:F,5,FALSE) -> Normal | I10: - | J10: x | K10: x | L10: x | M10: x | N10: x | P10: x
A11: =VLOOKUP(D11,'Master Data'!A:F,2,FALSE) -> Laszlo | B11: =VLOOKUP(D11,'Master Data'!A:F,3,FALSE) -> Lukacs | C11: =VLOOKUP(D11,'Master Data'!A:F,6,FALSE) -> laci91128@gmail.com | D11: 0036703794124 | F11: =VLOOKUP(D11,'Master Data'!A:F,4,FALSE) -> m | G11: =VLOOKUP(D11,'Master Data'!A:F,5,FALSE) -> Normal | I11: - | J11: x | K11: x | L11: x | M11: x | N11: x | P11: x
A12: =VLOOKUP(D12,'Master Data'!A:F,2,FALSE) -> Lena | B12: =VLOOKUP(D12,'Master Data'!A:F,3,FALSE) -> Bremer | C12: =VLOOKUP(D12,'Master Data'!A:F,6,FALSE) -> lena_bremer96@web.de | D12: 0767361357 | F12: =VLOOKUP(D12,'Master Data'!A:F,4,FALSE) -> w | G12: =VLOOKUP(D12,'Master Data'!A:F,5,FALSE) -> Pushflow | I12: x | J12: x | K12: x | L12: x | M12: x | N12: x | P12: x
A13: =VLOOKUP(D13,'Master Data'!A:F,2,FALSE) -> Javier | B13: =VLOOKUP(D13,'Master Data'!A:F,3,FALSE) -> Gonzalez | C13: =VLOOKUP(D13,'Master Data'!A:F,6,FALSE) -> j_gonzalez_80@hotmail.com | D13: 0764380975 | F13: =VLOOKUP(D13,'Master Data'!A:F,4,FALSE) -> m | G13: =VLOOKUP(D13,'Master Data'!A:F,5,FALSE) -> Normal | H13: 190 | I13: x | J13: x | K13: x | L13: x | M13: x | N13: x | P13: x
A14: =VLOOKUP(D14,'Master Data'!A:F,2,FALSE) -> Lea | B14: =VLOOKUP(D14,'Master Data'!A:F,3,FALSE) -> Kurmann | C14: =VLOOKUP(D14,'Master Data'!A:F,6,FALSE) -> lea.kurmann@bluewin.ch | D14: 0795982651 | F14: =VLOOKUP(D14,'Master Data'!A:F,4,FALSE) -> w | G14: =VLOOKUP(D14,'Master Data'!A:F,5,FALSE) -> Normal | H14: 190 | I14: x | J14: x | K14: x | L14: x | M14: x | N14: x | P14: x
A15: =VLOOKUP(D15,'Master Data'!A:F,2,FALSE) -> Bülent | B15: =VLOOKUP(D15,'Master Data'!A:F,3,FALSE) -> Ekinci | C15: =VLOOKUP(D15,'Master Data'!A:F,6,FALSE) -> buelentekinci24@gamil.com | D15: 00491637919721 | E15: Salsaflow Pass | F15: =VLOOKUP(D15,'Master Data'!A:F,4,FALSE) -> m | G15: =VLOOKUP(D15,'Master Data'!A:F,5,FALSE) -> Normal | I15: x | J15: x | K15: x | L15: x | M15: x | N15: x | P15: x
A16: =VLOOKUP(D16,'Master Data'!A:F,2,FALSE) -> Ivan | B16: =VLOOKUP(D16,'Master Data'!A:F,3,FALSE) -> Glushenkov | C16: =VLOOKUP(D16,'Master Data'!A:F,6,FALSE) -> ivan.glushenkov.data@gmail.com | D16: 0762636496 | F16: =VLOOKUP(D16,'Master Data'!A:F,4,FALSE) -> m | G16: =VLOOKUP(D16,'Master Data'!A:F,5,FALSE) -> Normal | I16: x | J16: x | K16: x | L16: x | M16: x | N16: x | P16: x
A17: =VLOOKUP(D17,'Master Data'!A:F,2,FALSE) -> Ben | B17: =VLOOKUP(D17,'Master Data'!A:F,3,FALSE) -> Böke | C17: =VLOOKUP(D17,'Master Data'!A:F,6,FALSE) -> ben25boeke@gmail.com | D17: 00491602122888 | E17: Salsaflow Pass | F17: =VLOOKUP(D17,'Master Data'!A:F,4,FALSE) -> m | G17: =VLOOKUP(D17,'Master Data'!A:F,5,FALSE) -> Normal | I17: x | J17: x | K17: x | L17: x | M17: x | N17: x | P17: x
A18: =VLOOKUP(D18,'Master Data'!A:F,2,FALSE) -> #N/A | B18: =VLOOKUP(D18,'Master Data'!A:F,3,FALSE) -> #N/A | C18: =VLOOKUP(D18,'Master Data'!A:F,6,FALSE) -> #N/A | F18: =VLOOKUP(D18,'Master Data'!A:F,4,FALSE) -> #N/A | G18: =VLOOKUP(D18,'Master Data'!A:F,5,FALSE) -> #N/A
A19: =VLOOKUP(D19,'Master Data'!A:F,2,FALSE) -> #N/A | B19: =VLOOKUP(D19,'Master Data'!A:F,3,FALSE) -> #N/A | C19: =VLOOKUP(D19,'Master Data'!A:F,6,FALSE) -> #N/A | F19: =VLOOKUP(D19,'Master Data'!A:F,4,FALSE) -> #N/A | G19: =VLOOKUP(D19,'Master Data'!A:F,5,FALSE) -> #N/A
A20: =VLOOKUP(D20,'Master Data'!A:F,2,FALSE) -> #N/A | B20: =VLOOKUP(D20,'Master Data'!A:F,3,FALSE) -> #N/A | C20: =VLOOKUP(D20,'Master Data'!A:F,6,FALSE) -> #N/A | F20: =VLOOKUP(D20,'Master Data'!A:F,4,FALSE) -> #N/A | G20: =VLOOKUP(D20,'Master Data'!A:F,5,FALSE) -> #N/A
A21: =VLOOKUP(D21,'Master Data'!A:F,2,FALSE) -> #N/A | B21: =VLOOKUP(D21,'Master Data'!A:F,3,FALSE) -> #N/A | C21: =VLOOKUP(D21,'Master Data'!A:F,6,FALSE) -> #N/A | F21: =VLOOKUP(D21,'Master Data'!A:F,4,FALSE) -> #N/A | G21: =VLOOKUP(D21,'Master Data'!A:F,5,FALSE) -> #N/A
A22: =VLOOKUP(D22,'Master Data'!A:F,2,FALSE) -> #N/A | B22: =VLOOKUP(D22,'Master Data'!A:F,3,FALSE) -> #N/A | C22: =VLOOKUP(D22,'Master Data'!A:F,6,FALSE) -> #N/A | F22: =VLOOKUP(D22,'Master Data'!A:F,4,FALSE) -> #N/A | G22: =VLOOKUP(D22,'Master Data'!A:F,5,FALSE) -> #N/A
A23: =VLOOKUP(D23,'Master Data'!A:F,2,FALSE) -> #N/A | B23: =VLOOKUP(D23,'Master Data'!A:F,3,FALSE) -> #N/A | C23: =VLOOKUP(D23,'Master Data'!A:F,6,FALSE) -> #N/A | F23: =VLOOKUP(D23,'Master Data'!A:F,4,FALSE) -> #N/A | G23: =VLOOKUP(D23,'Master Data'!A:F,5,FALSE) -> #N/A
A24: =VLOOKUP(D24,'Master Data'!A:F,2,FALSE) -> #N/A | B24: =VLOOKUP(D24,'Master Data'!A:F,3,FALSE) -> #N/A | C24: =VLOOKUP(D24,'Master Data'!A:F,6,FALSE) -> #N/A | F24: =VLOOKUP(D24,'Master Data'!A:F,4,FALSE) -> #N/A | G24: =VLOOKUP(D24,'Master Data'!A:F,5,FALSE) -> #N/A
A25: =VLOOKUP(D25,'Master Data'!A:F,2,FALSE) -> #N/A | B25: =VLOOKUP(D25,'Master Data'!A:F,3,FALSE) -> #N/A | C25: =VLOOKUP(D25,'Master Data'!A:F,6,FALSE) -> #N/A | F25: =VLOOKUP(D25,'Master Data'!A:F,4,FALSE) -> #N/A | G25: =VLOOKUP(D25,'Master Data'!A:F,5,FALSE) -> #N/A
A26: =VLOOKUP(D26,'Master Data'!A:F,2,FALSE) -> #N/A | B26: =VLOOKUP(D26,'Master Data'!A:F,3,FALSE) -> #N/A | C26: =VLOOKUP(D26,'Master Data'!A:F,6,FALSE) -> #N/A | F26: =VLOOKUP(D26,'Master Data'!A:F,4,FALSE) -> #N/A | G26: =VLOOKUP(D26,'Master Data'!A:F,5,FALSE) -> #N/A
A27: =VLOOKUP(D27,'Master Data'!A:F,2,FALSE) -> #N/A | B27: =VLOOKUP(D27,'Master Data'!A:F,3,FALSE) -> #N/A | C27: =VLOOKUP(D27,'Master Data'!A:F,6,FALSE) -> #N/A | F27: =VLOOKUP(D27,'Master Data'!A:F,4,FALSE) -> #N/A | G27: =VLOOKUP(D27,'Master Data'!A:F,5,FALSE) -> #N/A
A28: =VLOOKUP(D28,'Master Data'!A:F,2,FALSE) -> #N/A | B28: =VLOOKUP(D28,'Master Data'!A:F,3,FALSE) -> #N/A | C28: =VLOOKUP(D28,'Master Data'!A:F,6,FALSE) -> #N/A | F28: =VLOOKUP(D28,'Master Data'!A:F,4,FALSE) -> #N/A | G28: =VLOOKUP(D28,'Master Data'!A:F,5,FALSE) -> #N/A
A29: =VLOOKUP(D29,'Master Data'!A:F,2,FALSE) -> #N/A | B29: =VLOOKUP(D29,'Master Data'!A:F,3,FALSE) -> #N/A | C29: =VLOOKUP(D29,'Master Data'!A:F,6,FALSE) -> #N/A | F29: =VLOOKUP(D29,'Master Data'!A:F,4,FALSE) -> #N/A | G29: =VLOOKUP(D29,'Master Data'!A:F,5,FALSE) -> #N/A
... A31: =VLOOKUP(D31,'Master Data'!A:F,2,FALSE) -> #N/A | B31: =VLOOKUP(D31,'Master Data'!A:F,3,FALSE) -> #N/A | C31: =VLOOKUP(D31,'Master Data'!A:F,6,FALSE) -> #N/A | F31: =VLOOKUP(D31,'Master Data'!A:F,4,FALSE) -> #N/A | G31: =VLOOKUP(D31,'Master Data'!A:F,5,FALSE) -> #N/A
A32: =VLOOKUP(D32,'Master Data'!A:F,2,FALSE) -> #N/A | B32: =VLOOKUP(D32,'Master Data'!A:F,3,FALSE) -> #N/A | C32: =VLOOKUP(D32,'Master Data'!A:F,5,FALSE) -> #N/A | G32: Einnahmen | H32: =SUM(H7:H31) -> 380

Sheet Di_Salsa Advanced Stufe 16
A1: Anmeldungen - Salsa Advanced Stufe 16
A3: Datum: | B3: 06.01.2026 - 03.03.2026 | D3: Kurstag: | E3: Dienstag | G3: Lehrer: | H3: Rena & Fabio
A4: Zeit: | B4: 19:30 - 20:30 | D4: Ort: | E4: Elisabethenanlage 7 | G4: Preis: | H4: CHF 190.- / CHF 160.-
A6: Vorname | B6: Name | C6: E-Mail | D6: Mobile | E6: Bemerkungen | F6: m/w | G6: Tarif | H6: Betrag | I6: Anwesenheit
A7: =VLOOKUP(D7,'Master Data'!A:F,2,FALSE) -> Svitlana | B7: =VLOOKUP(D7,'Master Data'!A:F,3,FALSE) -> Logvinova | C7: =VLOOKUP(D7,'Master Data'!A:F,6,FALSE) -> sway@ua.fm | D7: 0795164912 | F7: =VLOOKUP(D7,'Master Data'!A:F,4,FALSE) -> w | G7: =VLOOKUP(D7,'Master Data'!A:F,5,FALSE) -> Normal | H7: 190 | I7: x | J7: x | K7: - | L7: x | M7: x | N7: - | P7: x
A8: =VLOOKUP(D8,'Master Data'!A:F,2,FALSE) -> Imanol | B8: =VLOOKUP(D8,'Master Data'!A:F,3,FALSE) -> Moreno Huerga | C8: =VLOOKUP(D8,'Master Data'!A:F,6,FALSE) -> i.moreno.huerga@gmail.com | D8: 0034634426790 | F8: =VLOOKUP(D8,'Master Data'!A:F,4,FALSE) -> m | G8: =VLOOKUP(D8,'Master Data'!A:F,5,FALSE) -> Normal | H8: 160 | I8: x | J8: x | K8: x | L8: x | M8: x | N8: x | P8: x
A9: =VLOOKUP(D9,'Master Data'!A:F,2,FALSE) -> Diana | B9: =VLOOKUP(D9,'Master Data'!A:F,3,FALSE) -> Albertos Torres | C9: =VLOOKUP(D9,'Master Data'!A:F,6,FALSE) -> didialbertos@hotmail.com | D9: 0034648156327 | F9: =VLOOKUP(D9,'Master Data'!A:F,4,FALSE) -> w | G9: =VLOOKUP(D9,'Master Data'!A:F,5,FALSE) -> Paar | H9: 160 | I9: x | J9: x | K9: x | L9: x | M9: x | N9: x | P9: x
A10: =VLOOKUP(D10,'Master Data'!A:F,2,FALSE) -> Tamara | B10: =VLOOKUP(D10,'Master Data'!A:F,3,FALSE) -> Rzehak | C10: =VLOOKUP(D10,'Master Data'!A:F,6,FALSE) -> tamara.rzehak@sunrise.ch | D10: 0765490154 | F10: =VLOOKUP(D10,'Master Data'!A:F,4,FALSE) -> w | G10: =VLOOKUP(D10,'Master Data'!A:F,5,FALSE) -> Normal | H10: 190 | I10: x | J10: x | K10: x | L10: x | M10: x | N10: x | P10: x
A11: =VLOOKUP(D11,'Master Data'!A:F,2,FALSE) -> Jacqueline | B11: =VLOOKUP(D11,'Master Data'!A:F,3,FALSE) -> Meier | C11: =VLOOKUP(D11,'Master Data'!A:F,6,FALSE) -> jacquelinemeier@msn.com | D11: 0793415374 | F11: =VLOOKUP(D11,'Master Data'!A:F,4,FALSE) -> w | G11: =VLOOKUP(D11,'Master Data'!A:F,5,FALSE) -> Normal | H11: 75 | I11: x | J11: x | K11: x | L11: - | M11: - | N11: - | O11: - | P11: -
A12: =VLOOKUP(D12,'Master Data'!A:F,2,FALSE) -> Corinne | B12: =VLOOKUP(D12,'Master Data'!A:F,3,FALSE) -> Leiser | C12: =VLOOKUP(D12,'Master Data'!A:F,6,FALSE) -> corinneleiser@bluewin.ch | D12: 0798696601 | F12: =VLOOKUP(D12,'Master Data'!A:F,4,FALSE) -> w | G12: =VLOOKUP(D12,'Master Data'!A:F,5,FALSE) -> Normal | H12: 190 | I12: x | J12: x | K12: x | L12: x | M12: x | N12: x | P12: x
A13: =VLOOKUP(D13,'Master Data'!A:F,2,FALSE) -> Ruben | B13: =VLOOKUP(D13,'Master Data'!A:F,3,FALSE) -> Castillo | C13: =VLOOKUP(D13,'Master Data'!A:F,6,FALSE) -> rubencastillo@hotmail.ch | D13: 0764326720 | F13: =VLOOKUP(D13,'Master Data'!A:F,4,FALSE) -> m | G13: =VLOOKUP(D13,'Master Data'!A:F,5,FALSE) -> Pushflow | I13: x | J13: x | K13: x | L13: x | M13: x | N13: x | P13: x
A14: =VLOOKUP(D14,'Master Data'!A:F,2,FALSE) -> Torben | B14: =VLOOKUP(D14,'Master Data'!A:F,3,FALSE) -> Lietzke | C14: =VLOOKUP(D14,'Master Data'!A:F,6,FALSE) -> t.lietzke@gmx.ch | D14: 0796006308 | F14: =VLOOKUP(D14,'Master Data'!A:F,4,FALSE) -> m | G14: =VLOOKUP(D14,'Master Data'!A:F,5,FALSE) -> Normal | H14: 160 | I14: x | J14: x | K14: x | L14: x | M14: x | N14: x | P14: x
A15: =VLOOKUP(D15,'Master Data'!A:F,2,FALSE) -> Eva | B15: =VLOOKUP(D15,'Master Data'!A:F,3,FALSE) -> Hammel | C15: =VLOOKUP(D15,'Master Data'!A:F,6,FALSE) -> eva.hammel@protonmail.ch | D15: 0789356222 | F15: =VLOOKUP(D15,'Master Data'!A:F,4,FALSE) -> w | G15: =VLOOKUP(D15,'Master Data'!A:F,5,FALSE) -> Normal | H15: 190 | I15: x | J15: x | K15: x | L15: x | M15: x | N15: - | P15: -
A16: =VLOOKUP(D16,'Master Data'!A:F,2,FALSE) -> Rayan | B16: =VLOOKUP(D16,'Master Data'!A:F,3,FALSE) -> Kieffer | C16: =VLOOKUP(D16,'Master Data'!A:F,6,FALSE) -> rayan.kieffer@gmail.com | D16: 0774619836 | E16: 2. Kurse | F16: =VLOOKUP(D16,'Master Data'!A:F,4,FALSE) -> m | G16: =VLOOKUP(D16,'Master Data'!A:F,5,FALSE) -> Normal | I16: x | J16: x | K16: x | L16: x | M16: - | N16: x | P16: x
A17: =VLOOKUP(D17,'Master Data'!A:F,2,FALSE) -> Regula | B17: =VLOOKUP(D17,'Master Data'!A:F,3,FALSE) -> Rudolf von Rohr | C17: =VLOOKUP(D17,'Master Data'!A:F,6,FALSE) -> regula.rvr@hotmail.com | D17: 0795836107 | E17: Salsaflow Pass | F17: =VLOOKUP(D17,'Master Data'!A:F,4,FALSE) -> w | G17: =VLOOKUP(D17,'Master Data'!A:F,5,FALSE) -> Normal | H17: 410 | I17: x | J17: x | K17: - | L17: x | M17: x | N17: x | P17: -
A18: =VLOOKUP(D18,'Master Data'!A:F,2,FALSE) -> Janina | B18: =VLOOKUP(D18,'Master Data'!A:F,3,FALSE) -> Aufrichtig | C18: =VLOOKUP(D18,'Master Data'!A:F,6,FALSE) -> j.aufrichtig@gmx.ch | D18: 0789136792 | E18: 2. Kurse | F18: =VLOOKUP(D18,'Master Data'!A:F,4,FALSE) -> w | G18: =VLOOKUP(D18,'Master Data'!A:F,5,FALSE) -> Normal | H18: 285 | I18: x | J18: x | K18: - | L18: x | M18: x | N18: x | P18: x
A19: =VLOOKUP(D19,'Master Data'!A:F,2,FALSE) -> Naida | B19: =VLOOKUP(D19,'Master Data'!A:F,3,FALSE) -> Lulic | C19: =VLOOKUP(D19,'Master Data'!A:F,6,FALSE) -> naida.lulic@gmail.com | D19: 0793124523 | F19: =VLOOKUP(D19,'Master Data'!A:F,4,FALSE) -> w | G19: =VLOOKUP(D19,'Master Data'!A:F,5,FALSE) -> Normal | H19: 190 | I19: x | J19: x | K19: x | L19: x | M19: x | N19: x | P19: x
A20: =VLOOKUP(D20,'Master Data'!A:F,2,FALSE) -> Myriam | B20: =VLOOKUP(D20,'Master Data'!A:F,3,FALSE) -> Aouadi | C20: =VLOOKUP(D20,'Master Data'!A:F,6,FALSE) -> aouadme@gmail.com | D20: 0795404172 | E20: Salsaflow | F20: =VLOOKUP(D20,'Master Data'!A:F,4,FALSE) -> w | G20: =VLOOKUP(D20,'Master Data'!A:F,5,FALSE) -> Normal | I20: x | J20: x | K20: - | L20: x | M20: x | N20: x | P20: x
A21: =VLOOKUP(D21,'Master Data'!A:F,2,FALSE) -> #N/A | B21: =VLOOKUP(D21,'Master Data'!A:F,3,FALSE) -> #N/A | C21: =VLOOKUP(D21,'Master Data'!A:F,6,FALSE) -> #N/A | F21: =VLOOKUP(D21,'Master Data'!A:F,4,FALSE) -> #N/A | G21: =VLOOKUP(D21,'Master Data'!A:F,5,FALSE) -> #N/A
A22: =VLOOKUP(D22,'Master Data'!A:F,2,FALSE) -> #N/A | B22: =VLOOKUP(D22,'Master Data'!A:F,3,FALSE) -> #N/A | C22: =VLOOKUP(D22,'Master Data'!A:F,6,FALSE) -> #N/A | F22: =VLOOKUP(D22,'Master Data'!A:F,4,FALSE) -> #N/A | G22: =VLOOKUP(D22,'Master Data'!A:F,5,FALSE) -> #N/A
A23: =VLOOKUP(D23,'Master Data'!A:F,2,FALSE) -> #N/A | B23: =VLOOKUP(D23,'Master Data'!A:F,3,FALSE) -> #N/A | C23: =VLOOKUP(D23,'Master Data'!A:F,6,FALSE) -> #N/A | F23: =VLOOKUP(D23,'Master Data'!A:F,4,FALSE) -> #N/A | G23: =VLOOKUP(D23,'Master Data'!A:F,5,FALSE) -> #N/A
A24: =VLOOKUP(D24,'Master Data'!A:F,2,FALSE) -> #N/A | B24: =VLOOKUP(D24,'Master Data'!A:F,3,FALSE) -> #N/A | C24: =VLOOKUP(D24,'Master Data'!A:F,6,FALSE) -> #N/A | F24: =VLOOKUP(D24,'Master Data'!A:F,4,FALSE) -> #N/A | G24: =VLOOKUP(D24,'Master Data'!A:F,5,FALSE) -> #N/A
A25: =VLOOKUP(D25,'Master Data'!A:F,2,FALSE) -> #N/A | B25: =VLOOKUP(D25,'Master Data'!A:F,3,FALSE) -> #N/A | C25: =VLOOKUP(D25,'Master Data'!A:F,6,FALSE) -> #N/A | F25: =VLOOKUP(D25,'Master Data'!A:F,4,FALSE) -> #N/A | G25: =VLOOKUP(D25,'Master Data'!A:F,5,FALSE) -> #N/A
A26: =VLOOKUP(D26,'Master Data'!A:F,2,FALSE) -> #N/A | B26: =VLOOKUP(D26,'Master Data'!A:F,3,FALSE) -> #N/A | C26: =VLOOKUP(D26,'Master Data'!A:F,6,FALSE) -> #N/A | F26: =VLOOKUP(D26,'Master Data'!A:F,4,FALSE) -> #N/A | G26: =VLOOKUP(D26,'Master Data'!A:F,5,FALSE) -> #N/A
A27: =VLOOKUP(D27,'Master Data'!A:F,2,FALSE) -> #N/A | B27: =VLOOKUP(D27,'Master Data'!A:F,3,FALSE) -> #N/A | C27: =VLOOKUP(D27,'Master Data'!A:F,6,FALSE) -> #N/A | F27: =VLOOKUP(D27,'Master Data'!A:F,4,FALSE) -> #N/A | G27: =VLOOKUP(D27,'Master Data'!A:F,5,FALSE) -> #N/A
A28: =VLOOKUP(D28,'Master Data'!A:F,2,FALSE) -> #N/A | B28: =VLOOKUP(D28,'Master Data'!A:F,3,FALSE) -> #N/A | C28: =VLOOKUP(D28,'Master Data'!A:F,6,FALSE) -> #N/A | F28: =VLOOKUP(D28,'Master Data'!A:F,4,FALSE) -> #N/A | G28: =VLOOKUP(D28,'Master Data'!A:F,5,FALSE) -> #N/A
A29: =VLOOKUP(D29,'Master Data'!A:F,2,FALSE) -> #N/A | B29: =VLOOKUP(D29,'Master Data'!A:F,3,FALSE) -> #N/A | C29: =VLOOKUP(D29,'Master Data'!A:F,6,FALSE) -> #N/A | F29: =VLOOKUP(D29,'Master Data'!A:F,4,FALSE) -> #N/A | G29: =VLOOKUP(D29,'Master Data'!A:F,5,FALSE) -> #N/A
A30: =VLOOKUP(D30,'Master Data'!A:F,2,FALSE) -> #N/A | B30: =VLOOKUP(D30,'Master Data'!A:F,3,FALSE) -> #N/A | C30: =VLOOKUP(D30,'Master Data'!A:F,6,FALSE) -> #N/A | F30: =VLOOKUP(D30,'Master Data'!A:F,4,FALSE) -> #N/A | G30: =VLOOKUP(D30,'Master Data'!A:F,5,FALSE) -> #N/A
A31: =VLOOKUP(D31,'Master Data'!A:F,2,FALSE) -> #N/A | B31: =VLOOKUP(D31,'Master Data'!A:F,3,FALSE) -> #N/A | C31: =VLOOKUP(D31,'Master Data'!A:F,6,FALSE) -> #N/A | F31: =VLOOKUP(D31,'Master Data'!A:F,4,FALSE) -> #N/A | G31: =VLOOKUP(D31,'Master Data'!A:F,5,FALSE) -> #N/A
A32: =VLOOKUP(D32,'Master Data'!A:F,2,FALSE) -> #N/A | B32: =VLOOKUP(D32,'Master Data'!A:F,3,FALSE) -> #N/A | C32: =VLOOKUP(D32,'Master Data'!A:F,5,FALSE) -> #N/A | G32: Einnahmen | H32: =SUM(H7:H31) -> 2200

Sheet Di_Salsa Beginner Stufe 3
A1: Anmeldungen - Salsa Beginner Stufe 3
A3: Datum: | B3: 06.01.2026 - 03.03.2026 | D3: Kurstag: | E3: Dienstag | G3: Lehrer: | H3: Jelena & Yannick
A4: Zeit: | B4: 19:30 - 20:30 | D4: Ort: | E4: Elisabethenanlage 7 | G4: Preis: | H4: CHF 190.- / CHF 160.-
A6: Vorname | B6: Name | C6: E-Mail | D6: Mobile | E6: Bemerkungen | F6: m/w | G6: Tarif | H6: Betrag | I6: Anwesenheit
A7: =VLOOKUP(D7,'Master Data'!A:F,2,FALSE) -> Pavel | B7: =VLOOKUP(D7,'Master Data'!A:F,3,FALSE) -> Kos | C7: =VLOOKUP(D7,'Master Data'!A:F,6,FALSE) -> pavel.kos.personal@gmail.com | D7: 0766504322 | F7: =VLOOKUP(D7,'Master Data'!A:F,4,FALSE) -> m | G7: =VLOOKUP(D7,'Master Data'!A:F,5,FALSE) -> Normal | H7: 190 | I7: x | J7: x | K7: x | L7: x | M7: x | N7: x | P7: x
A8: =VLOOKUP(D8,'Master Data'!A:F,2,FALSE) -> Katharina | B8: =VLOOKUP(D8,'Master Data'!A:F,3,FALSE) -> Haaf | C8: =VLOOKUP(D8,'Master Data'!A:F,6,FALSE) -> katharinahaaf@web.de | D8: 0762681107 | F8: =VLOOKUP(D8,'Master Data'!A:F,4,FALSE) -> w | G8: =VLOOKUP(D8,'Master Data'!A:F,5,FALSE) -> Normal | H8: 190 | I8: x | J8: x | K8: x | L8: x | M8: - | N8: x | P8: x
A9: =VLOOKUP(D9,'Master Data'!A:F,2,FALSE) -> Ivan | B9: =VLOOKUP(D9,'Master Data'!A:F,3,FALSE) -> Glushenkov | C9: =VLOOKUP(D9,'Master Data'!A:F,6,FALSE) -> ivan.glushenkov.data@gmail.com | D9: 0762636496 | E9: Salsaflow Pass | F9: =VLOOKUP(D9,'Master Data'!A:F,4,FALSE) -> m | G9: =VLOOKUP(D9,'Master Data'!A:F,5,FALSE) -> Normal | I9: x | J9: x | K9: x | L9: x | M9: x | N9: x | P9: x
A10: =VLOOKUP(D10,'Master Data'!A:F,2,FALSE) -> Ben | B10: =VLOOKUP(D10,'Master Data'!A:F,3,FALSE) -> Böke | C10: =VLOOKUP(D10,'Master Data'!A:F,6,FALSE) -> ben25boeke@gmail.com | D10: 00491602122888 | E10: Salsaflow Pass | F10: =VLOOKUP(D10,'Master Data'!A:F,4,FALSE) -> m | G10: =VLOOKUP(D10,'Master Data'!A:F,5,FALSE) -> Normal | I10: x | J10: x | K10: x | L10: x | M10: x | N10: x | P10: x
A11: =VLOOKUP(D11,'Master Data'!A:F,2,FALSE) -> Simão Pedro | B11: =VLOOKUP(D11,'Master Data'!A:F,3,FALSE) -> Oliveira | C11: =VLOOKUP(D11,'Master Data'!A:F,6,FALSE) -> spedro.oliveira@gmail.com | D11: 0033681301330 | F11: =VLOOKUP(D11,'Master Data'!A:F,4,FALSE) -> m | G11: =VLOOKUP(D11,'Master Data'!A:F,5,FALSE) -> Normal | H11: 285 | I11: x | J11: x | K11: x | L11: x | M11: x | N11: x | P11: x
A12: =VLOOKUP(D12,'Master Data'!A:F,2,FALSE) -> Dino | B12: =VLOOKUP(D12,'Master Data'!A:F,3,FALSE) -> Nienhold | C12: =VLOOKUP(D12,'Master Data'!A:F,6,FALSE) -> dino.nienhold@gmail.com | D12: 0788787879 | F12: =VLOOKUP(D12,'Master Data'!A:F,4,FALSE) -> m | G12: =VLOOKUP(D12,'Master Data'!A:F,5,FALSE) -> Normal | H12: 190 | I12: x | J12: x | K12: x | L12: x | M12: - | N12: x | O12: - | P12: -
A13: =VLOOKUP(D13,'Master Data'!A:F,2,FALSE) -> Philipp | B13: =VLOOKUP(D13,'Master Data'!A:F,3,FALSE) -> Schaub | C13: =VLOOKUP(D13,'Master Data'!A:F,6,FALSE) -> philipp.schaub@magnet.ch | D13: 0797964450 | F13: =VLOOKUP(D13,'Master Data'!A:F,4,FALSE) -> m | G13: =VLOOKUP(D13,'Master Data'!A:F,5,FALSE) -> Normal | H13: 190 | I13: x | J13: x | K13: x | L13: x | M13: x | N13: x | P13: x
A14: =VLOOKUP(D14,'Master Data'!A:F,2,FALSE) -> Evgenij | B14: =VLOOKUP(D14,'Master Data'!A:F,3,FALSE) -> Komarov | C14: =VLOOKUP(D14,'Master Data'!A:F,6,FALSE) -> k_ewe@hotmail.de | D14: 0792465093 | F14: =VLOOKUP(D14,'Master Data'!A:F,4,FALSE) -> m | G14: =VLOOKUP(D14,'Master Data'!A:F,5,FALSE) -> Normal | H14: 190 | I14: x | J14: x | K14: x | L14: x | M14: - | N14: x | P14: x
A15: =VLOOKUP(D15,'Master Data'!A:F,2,FALSE) -> Imân | B15: =VLOOKUP(D15,'Master Data'!A:F,3,FALSE) -> Hofer | C15: =VLOOKUP(D15,'Master Data'!A:F,6,FALSE) -> i.hofer@hotmail.com | D15: 0763215082 | F15: =VLOOKUP(D15,'Master Data'!A:F,4,FALSE) -> w | G15: =VLOOKUP(D15,'Master Data'!A:F,5,FALSE) -> Normal | H15: 145 | I15: x | J15: - | K15: - | L15: x | M15: x | N15: x | P15: x
A16: =VLOOKUP(D16,'Master Data'!A:F,2,FALSE) -> Linda | B16: =VLOOKUP(D16,'Master Data'!A:F,3,FALSE) -> Pedrazzoli | C16: =VLOOKUP(D16,'Master Data'!A:F,6,FALSE) -> linda.pedrazzoli@bluewin.ch | D16: 0797270838 | F16: =VLOOKUP(D16,'Master Data'!A:F,4,FALSE) -> w | G16: =VLOOKUP(D16,'Master Data'!A:F,5,FALSE) -> Paar | H16: 160 | I16: - | J16: x | K16: x | L16: x | M16: - | N16: x | P16: x
A17: =VLOOKUP(D17,'Master Data'!A:F,2,FALSE) -> Claudio | B17: =VLOOKUP(D17,'Master Data'!A:F,3,FALSE) -> Laely | C17: =VLOOKUP(D17,'Master Data'!A:F,6,FALSE) -> claudiolaely@bluewin.ch | D17: 0796752628 | F17: =VLOOKUP(D17,'Master Data'!A:F,4,FALSE) -> m | G17: =VLOOKUP(D17,'Master Data'!A:F,5,FALSE) -> Paar | H17: 160 | I17: - | J17: x | K17: x | L17: x | M17: - | N17: x | P17: -
A18: =VLOOKUP(D18,'Master Data'!A:F,2,FALSE) -> #N/A | B18: =VLOOKUP(D18,'Master Data'!A:F,3,FALSE) -> #N/A | C18: =VLOOKUP(D18,'Master Data'!A:F,6,FALSE) -> #N/A | F18: =VLOOKUP(D18,'Master Data'!A:F,4,FALSE) -> #N/A | G18: =VLOOKUP(D18,'Master Data'!A:F,5,FALSE) -> #N/A
A19: =VLOOKUP(D19,'Master Data'!A:F,2,FALSE) -> #N/A | B19: =VLOOKUP(D19,'Master Data'!A:F,3,FALSE) -> #N/A | C19: =VLOOKUP(D19,'Master Data'!A:F,6,FALSE) -> #N/A | F19: =VLOOKUP(D19,'Master Data'!A:F,4,FALSE) -> #N/A | G19: =VLOOKUP(D19,'Master Data'!A:F,5,FALSE) -> #N/A
A20: =VLOOKUP(D20,'Master Data'!A:F,2,FALSE) -> #N/A | B20: =VLOOKUP(D20,'Master Data'!A:F,3,FALSE) -> #N/A | C20: =VLOOKUP(D20,'Master Data'!A:F,6,FALSE) -> #N/A | F20: =VLOOKUP(D20,'Master Data'!A:F,4,FALSE) -> #N/A | G20: =VLOOKUP(D20,'Master Data'!A:F,5,FALSE) -> #N/A
A21: =VLOOKUP(D21,'Master Data'!A:F,2,FALSE) -> #N/A | B21: =VLOOKUP(D21,'Master Data'!A:F,3,FALSE) -> #N/A | C21: =VLOOKUP(D21,'Master Data'!A:F,6,FALSE) -> #N/A | G21: =VLOOKUP(D21,'Master Data'!A:F,5,FALSE) -> #N/A
A22: =VLOOKUP(D22,'Master Data'!A:F,2,FALSE) -> #N/A | B22: =VLOOKUP(D22,'Master Data'!A:F,3,FALSE) -> #N/A | C22: =VLOOKUP(D22,'Master Data'!A:F,6,FALSE) -> #N/A | G22: =VLOOKUP(D22,'Master Data'!A:F,5,FALSE) -> #N/A
A23: =VLOOKUP(D23,'Master Data'!A:F,2,FALSE) -> #N/A | B23: =VLOOKUP(D23,'Master Data'!A:F,3,FALSE) -> #N/A | C23: =VLOOKUP(D23,'Master Data'!A:F,6,FALSE) -> #N/A | G23: =VLOOKUP(D23,'Master Data'!A:F,5,FALSE) -> #N/A
A24: =VLOOKUP(D24,'Master Data'!A:F,2,FALSE) -> #N/A | B24: =VLOOKUP(D24,'Master Data'!A:F,3,FALSE) -> #N/A | C24: =VLOOKUP(D24,'Master Data'!A:F,6,FALSE) -> #N/A | F24: =VLOOKUP(D24,'Master Data'!A:F,4,FALSE) -> #N/A | G24: =VLOOKUP(D24,'Master Data'!A:F,5,FALSE) -> #N/A
A25: =VLOOKUP(D25,'Master Data'!A:F,2,FALSE) -> #N/A | B25: =VLOOKUP(D25,'Master Data'!A:F,3,FALSE) -> #N/A | C25: =VLOOKUP(D25,'Master Data'!A:F,6,FALSE) -> #N/A | F25: =VLOOKUP(D25,'Master Data'!A:F,4,FALSE) -> #N/A | G25: =VLOOKUP(D25,'Master Data'!A:F,5,FALSE) -> #N/A
A26: =VLOOKUP(D26,'Master Data'!A:F,2,FALSE) -> #N/A | B26: =VLOOKUP(D26,'Master Data'!A:F,3,FALSE) -> #N/A | C26: =VLOOKUP(D26,'Master Data'!A:F,6,FALSE) -> #N/A | F26: =VLOOKUP(D26,'Master Data'!A:F,4,FALSE) -> #N/A | G26: =VLOOKUP(D26,'Master Data'!A:F,5,FALSE) -> #N/A
A27: =VLOOKUP(D27,'Master Data'!A:F,2,FALSE) -> #N/A | B27: =VLOOKUP(D27,'Master Data'!A:F,3,FALSE) -> #N/A | C27: =VLOOKUP(D27,'Master Data'!A:F,6,FALSE) -> #N/A | F27: =VLOOKUP(D27,'Master Data'!A:F,4,FALSE) -> #N/A | G27: =VLOOKUP(D27,'Master Data'!A:F,5,FALSE) -> #N/A
A28: =VLOOKUP(D28,'Master Data'!A:F,2,FALSE) -> #N/A | B28: =VLOOKUP(D28,'Master Data'!A:F,3,FALSE) -> #N/A | C28: =VLOOKUP(D28,'Master Data'!A:F,6,FALSE) -> #N/A | F28: =VLOOKUP(D28,'Master Data'!A:F,4,FALSE) -> #N/A | G28: =VLOOKUP(D28,'Master Data'!A:F,5,FALSE) -> #N/A
A29: =VLOOKUP(D29,'Master Data'!A:F,2,FALSE) -> #N/A | B29: =VLOOKUP(D29,'Master Data'!A:F,3,FALSE) -> #N/A | C29: =VLOOKUP(D29,'Master Data'!A:F,6,FALSE) -> #N/A | F29: =VLOOKUP(D29,'Master Data'!A:F,4,FALSE) -> #N/A | G29: =VLOOKUP(D29,'Master Data'!A:F,5,FALSE) -> #N/A
A30: =VLOOKUP(D30,'Master Data'!A:F,2,FALSE) -> #N/A | B30: =VLOOKUP(D30,'Master Data'!A:F,3,FALSE) -> #N/A | C30: =VLOOKUP(D30,'Master Data'!A:F,6,FALSE) -> #N/A | F30: =VLOOKUP(D30,'Master Data'!A:F,4,FALSE) -> #N/A | G30: =VLOOKUP(D30,'Master Data'!A:F,5,FALSE) -> #N/A
A31: =VLOOKUP(D31,'Master Data'!A:F,2,FALSE) -> #N/A | B31: =VLOOKUP(D31,'Master Data'!A:F,3,FALSE) -> #N/A | C31: =VLOOKUP(D31,'Master Data'!A:F,6,FALSE) -> #N/A | F31: =VLOOKUP(D31,'Master Data'!A:F,4,FALSE) -> #N/A | G31: =VLOOKUP(D31,'Master Data'!A:F,5,FALSE) -> #N/A
A32: =VLOOKUP(D32,'Master Data'!A:F,2,FALSE) -> #N/A | B32: =VLOOKUP(D32,'Master Data'!A:F,3,FALSE) -> #N/A | C32: =VLOOKUP(D32,'Master Data'!A:F,5,FALSE) -> #N/A | G32: Einnahmen | H32: =SUM(H7:H31) -> 1700

Sheet Di_Cha cha cha
A1: Anmeldungen - Cha cha cha
A3: Datum: | B3: 06.01.2026 - 03.03.2026 | D3: Kurstag: | E3: Dienstag | G3: Lehrer: | H3: Mihai
A4: Zeit: | B4: 20:30 - 21:30 | D4: Ort: | E4: Elisabethenanlage 7 | G4: Preis: | H4: CHF 190.- / CHF 160.-
A6: Vorname | B6: Name | C6: E-Mail | D6: Mobile | E6: Bemerkungen | F6: m/w | G6: Tarif | H6: Betrag | I6: Anwesenheit
A7: =VLOOKUP(D7,'Master Data'!A:F,2,FALSE) -> Kalin | B7: =VLOOKUP(D7,'Master Data'!A:F,3,FALSE) -> Marinov | C7: =VLOOKUP(D7,'Master Data'!A:F,6,FALSE) -> kalin.marinov977@gmail.com | D7: 0798122926 | E7: Salsaflow Pass | F7: =VLOOKUP(D7,'Master Data'!A:F,4,FALSE) -> m | G7: =VLOOKUP(D7,'Master Data'!A:F,5,FALSE) -> Normal | I7: - | J7: x | K7: x | L7: x | M7: x | N7: x | P7: x
A8: =VLOOKUP(D8,'Master Data'!A:F,2,FALSE) -> Lena | B8: =VLOOKUP(D8,'Master Data'!A:F,3,FALSE) -> Bremer | C8: =VLOOKUP(D8,'Master Data'!A:F,6,FALSE) -> lena_bremer96@web.de | D8: 0767361357 | F8: =VLOOKUP(D8,'Master Data'!A:F,4,FALSE) -> w | G8: =VLOOKUP(D8,'Master Data'!A:F,5,FALSE) -> Pushflow | I8: x | J8: x | K8: x | L8: x | M8: x | N8: x | P8: x
A9: =VLOOKUP(D9,'Master Data'!A:F,2,FALSE) -> Burak | B9: =VLOOKUP(D9,'Master Data'!A:F,3,FALSE) -> Yildirim | C9: =VLOOKUP(D9,'Master Data'!A:F,6,FALSE) -> burak.yildirim@gmx.ch | D9: 0795584011 | F9: =VLOOKUP(D9,'Master Data'!A:F,4,FALSE) -> m | G9: =VLOOKUP(D9,'Master Data'!A:F,5,FALSE) -> Normal | H9: 410 | I9: - | J9: x | K9: x | L9: x | M9: x | N9: x | P9: x
A10: =VLOOKUP(D10,'Master Data'!A:F,2,FALSE) -> Estelle | B10: =VLOOKUP(D10,'Master Data'!A:F,3,FALSE) -> Pierrot | C10: =VLOOKUP(D10,'Master Data'!A:F,6,FALSE) -> stella110@hotmail.fr | D10: 0765235926 | F10: =VLOOKUP(D10,'Master Data'!A:F,4,FALSE) -> w | G10: =VLOOKUP(D10,'Master Data'!A:F,5,FALSE) -> Normal | I10: - | J10: x | K10: x | L10: x | M10: x | N10: x | P10: x
A11: =VLOOKUP(D11,'Master Data'!A:F,2,FALSE) -> Regula | B11: =VLOOKUP(D11,'Master Data'!A:F,3,FALSE) -> Rudolf von Rohr | C11: =VLOOKUP(D11,'Master Data'!A:F,6,FALSE) -> regula.rvr@hotmail.com | D11: 0795836107 | E11: Salsaflow Pass | F11: =VLOOKUP(D11,'Master Data'!A:F,4,FALSE) -> w | G11: =VLOOKUP(D11,'Master Data'!A:F,5,FALSE) -> Normal | I11: x | J11: x | K11: x | L11: x | M11: x | N11: x | P11: x
A12: =VLOOKUP(D12,'Master Data'!A:F,2,FALSE) -> Iryna | B12: =VLOOKUP(D12,'Master Data'!A:F,3,FALSE) -> Marrini | C12: =VLOOKUP(D12,'Master Data'!A:F,6,FALSE) -> iryna@marrini.com | D12: 0772655009 | E12: Salsaflow Pass | F12: =VLOOKUP(D12,'Master Data'!A:F,4,FALSE) -> w | G12: =VLOOKUP(D12,'Master Data'!A:F,5,FALSE) -> Normal | I12: x | J12: x | K12: x | L12: x | M12: x | N12: x | P12: x
A13: =VLOOKUP(D13,'Master Data'!A:F,2,FALSE) -> Ben | B13: =VLOOKUP(D13,'Master Data'!A:F,3,FALSE) -> Böke | C13: =VLOOKUP(D13,'Master Data'!A:F,6,FALSE) -> ben25boeke@gmail.com | D13: 00491602122888 | E13: Salsaflow Pass | F13: =VLOOKUP(D13,'Master Data'!A:F,4,FALSE) -> m | G13: =VLOOKUP(D13,'Master Data'!A:F,5,FALSE) -> Normal | I13: x | J13: x | K13: x | L13: x | M13: x | N13: x | P13: x
A14: =VLOOKUP(D14,'Master Data'!A:F,2,FALSE) -> Ivan | B14: =VLOOKUP(D14,'Master Data'!A:F,3,FALSE) -> Glushenkov | C14: =VLOOKUP(D14,'Master Data'!A:F,6,FALSE) -> ivan.glushenkov.data@gmail.com | D14: 0762636496 | E14: Salsaflow Pass | F14: =VLOOKUP(D14,'Master Data'!A:F,4,FALSE) -> m | G14: =VLOOKUP(D14,'Master Data'!A:F,5,FALSE) -> Normal | I14: x | J14: x | K14: x | L14: x | M14: x | N14: x | P14: x
A15: =VLOOKUP(D15,'Master Data'!A:F,2,FALSE) -> Bülent | B15: =VLOOKUP(D15,'Master Data'!A:F,3,FALSE) -> Ekinci | C15: =VLOOKUP(D15,'Master Data'!A:F,6,FALSE) -> buelentekinci24@gamil.com | D15: 00491637919721 | E15: Salsaflow Pass | F15: =VLOOKUP(D15,'Master Data'!A:F,4,FALSE) -> m | G15: =VLOOKUP(D15,'Master Data'!A:F,5,FALSE) -> Normal | I15: x | J15: x | K15: x | L15: x | M15: x | N15: x | P15: x
A16: =VLOOKUP(D16,'Master Data'!A:F,2,FALSE) -> Stephanie | B16: =VLOOKUP(D16,'Master Data'!A:F,3,FALSE) -> Csendes | C16: =VLOOKUP(D16,'Master Data'!A:F,6,FALSE) -> stephanie.csendes@gmail.com | D16: 0764177421 | E16: Pushflow | F16: =VLOOKUP(D16,'Master Data'!A:F,4,FALSE) -> w | G16: =VLOOKUP(D16,'Master Data'!A:F,5,FALSE) -> Normal | I16: x | J16: x | K16: x | L16: - | M16: - | N16: x | P16: x
A17: =VLOOKUP(D17,'Master Data'!A:F,2,FALSE) -> Laszlo | B17: =VLOOKUP(D17,'Master Data'!A:F,3,FALSE) -> Lukacs | C17: =VLOOKUP(D17,'Master Data'!A:F,6,FALSE) -> laci91128@gmail.com | D17: 0036703794124 | F17: =VLOOKUP(D17,'Master Data'!A:F,4,FALSE) -> m | G17: =VLOOKUP(D17,'Master Data'!A:F,5,FALSE) -> Normal | I17: - | J17: x | K17: x | L17: x | M17: x | N17: - | P17: x
A18: =VLOOKUP(D18,'Master Data'!A:F,2,FALSE) -> Ali | B18: =VLOOKUP(D18,'Master Data'!A:F,3,FALSE) -> Üstündag | C18: =VLOOKUP(D18,'Master Data'!A:F,6,FALSE) -> ali.uestuendag@gmail.com | D18: 0786262771 | F18: =VLOOKUP(D18,'Master Data'!A:F,4,FALSE) -> m | G18: =VLOOKUP(D18,'Master Data'!A:F,5,FALSE) -> Pushflow | I18: x | J18: - | K18: x | L18: x | M18: x | N18: x | P18: x
A19: =VLOOKUP(D19,'Master Data'!A:F,2,FALSE) -> #N/A | B19: =VLOOKUP(D19,'Master Data'!A:F,3,FALSE) -> #N/A | C19: =VLOOKUP(D19,'Master Data'!A:F,6,FALSE) -> #N/A | F19: =VLOOKUP(D19,'Master Data'!A:F,4,FALSE) -> #N/A | G19: =VLOOKUP(D19,'Master Data'!A:F,5,FALSE) -> #N/A
A20: =VLOOKUP(D20,'Master Data'!A:F,2,FALSE) -> #N/A | B20: =VLOOKUP(D20,'Master Data'!A:F,3,FALSE) -> #N/A | C20: =VLOOKUP(D20,'Master Data'!A:F,6,FALSE) -> #N/A | F20: =VLOOKUP(D20,'Master Data'!A:F,4,FALSE) -> #N/A | G20: =VLOOKUP(D20,'Master Data'!A:F,5,FALSE) -> #N/A
A21: =VLOOKUP(D21,'Master Data'!A:F,2,FALSE) -> #N/A | B21: =VLOOKUP(D21,'Master Data'!A:F,3,FALSE) -> #N/A | C21: =VLOOKUP(D21,'Master Data'!A:F,6,FALSE) -> #N/A | F21: =VLOOKUP(D21,'Master Data'!A:F,4,FALSE) -> #N/A | G21: =VLOOKUP(D21,'Master Data'!A:F,5,FALSE) -> #N/A
A22: =VLOOKUP(D22,'Master Data'!A:F,2,FALSE) -> #N/A | B22: =VLOOKUP(D22,'Master Data'!A:F,3,FALSE) -> #N/A | C22: =VLOOKUP(D22,'Master Data'!A:F,6,FALSE) -> #N/A | F22: =VLOOKUP(D22,'Master Data'!A:F,4,FALSE) -> #N/A | G22: =VLOOKUP(D22,'Master Data'!A:F,5,FALSE) -> #N/A
A23: =VLOOKUP(D23,'Master Data'!A:F,2,FALSE) -> #N/A | B23: =VLOOKUP(D23,'Master Data'!A:F,3,FALSE) -> #N/A | C23: =VLOOKUP(D23,'Master Data'!A:F,6,FALSE) -> #N/A | F23: =VLOOKUP(D23,'Master Data'!A:F,4,FALSE) -> #N/A | G23: =VLOOKUP(D23,'Master Data'!A:F,5,FALSE) -> #N/A
A24: =VLOOKUP(D24,'Master Data'!A:F,2,FALSE) -> #N/A | B24: =VLOOKUP(D24,'Master Data'!A:F,3,FALSE) -> #N/A | C24: =VLOOKUP(D24,'Master Data'!A:F,6,FALSE) -> #N/A | F24: =VLOOKUP(D24,'Master Data'!A:F,4,FALSE) -> #N/A | G24: =VLOOKUP(D24,'Master Data'!A:F,5,FALSE) -> #N/A
A25: =VLOOKUP(D25,'Master Data'!A:F,2,FALSE) -> #N/A | B25: =VLOOKUP(D25,'Master Data'!A:F,3,FALSE) -> #N/A | C25: =VLOOKUP(D25,'Master Data'!A:F,6,FALSE) -> #N/A | F25: =VLOOKUP(D25,'Master Data'!A:F,4,FALSE) -> #N/A | G25: =VLOOKUP(D25,'Master Data'!A:F,5,FALSE) -> #N/A
A26: =VLOOKUP(D26,'Master Data'!A:F,2,FALSE) -> #N/A | B26: =VLOOKUP(D26,'Master Data'!A:F,3,FALSE) -> #N/A | C26: =VLOOKUP(D26,'Master Data'!A:F,6,FALSE) -> #N/A | F26: =VLOOKUP(D26,'Master Data'!A:F,4,FALSE) -> #N/A | G26: =VLOOKUP(D26,'Master Data'!A:F,5,FALSE) -> #N/A
A27: =VLOOKUP(D27,'Master Data'!A:F,2,FALSE) -> #N/A | B27: =VLOOKUP(D27,'Master Data'!A:F,3,FALSE) -> #N/A | C27: =VLOOKUP(D27,'Master Data'!A:F,6,FALSE) -> #N/A | F27: =VLOOKUP(D27,'Master Data'!A:F,4,FALSE) -> #N/A | G27: =VLOOKUP(D27,'Master Data'!A:F,5,FALSE) -> #N/A
A28: =VLOOKUP(D28,'Master Data'!A:F,2,FALSE) -> #N/A | B28: =VLOOKUP(D28,'Master Data'!A:F,3,FALSE) -> #N/A | C28: =VLOOKUP(D28,'Master Data'!A:F,6,FALSE) -> #N/A | F28: =VLOOKUP(D28,'Master Data'!A:F,4,FALSE) -> #N/A | G28: =VLOOKUP(D28,'Master Data'!A:F,5,FALSE) -> #N/A
A29: =VLOOKUP(D29,'Master Data'!A:F,2,FALSE) -> #N/A | B29: =VLOOKUP(D29,'Master Data'!A:F,3,FALSE) -> #N/A | C29: =VLOOKUP(D29,'Master Data'!A:F,6,FALSE) -> #N/A | F29: =VLOOKUP(D29,'Master Data'!A:F,4,FALSE) -> #N/A | G29: =VLOOKUP(D29,'Master Data'!A:F,5,FALSE) -> #N/A
A30: =VLOOKUP(D30,'Master Data'!A:F,2,FALSE) -> #N/A | B30: =VLOOKUP(D30,'Master Data'!A:F,3,FALSE) -> #N/A | C30: =VLOOKUP(D30,'Master Data'!A:F,6,FALSE) -> #N/A | F30: =VLOOKUP(D30,'Master Data'!A:F,4,FALSE) -> #N/A | G30: =VLOOKUP(D30,'Master Data'!A:F,5,FALSE) -> #N/A
A31: =VLOOKUP(D31,'Master Data'!A:F,2,FALSE) -> #N/A | B31: =VLOOKUP(D31,'Master Data'!A:F,3,FALSE) -> #N/A | C31: =VLOOKUP(D31,'Master Data'!A:F,6,FALSE) -> #N/A | F31: =VLOOKUP(D31,'Master Data'!A:F,4,FALSE) -> #N/A | G31: =VLOOKUP(D31,'Master Data'!A:F,5,FALSE) -> #N/A
A32: =VLOOKUP(D32,'Master Data'!A:F,2,FALSE) -> #N/A | B32: =VLOOKUP(D32,'Master Data'!A:F,3,FALSE) -> #N/A | C32: =VLOOKUP(D32,'Master Data'!A:F,5,FALSE) -> #N/A | G32: Einnahmen | H32: =SUM(H7:H31) -> 410

Sheet Di_Salsa Advanced Stufe 13
A1: Anmeldungen - Salsa Advanced Stufe 13
A3: Datum: | B3: 06.01.2026 - 03.03.2026 | D3: Kurstag: | E3: Dienstag | G3: Lehrer: | H3: Rena & Fabio
A4: Zeit: | B4: 20:30 - 21:30 | D4: Ort: | E4: Elisabethenanlage 7 | G4: Preis: | H4: CHF 190.- / CHF 160.-
A6: Vorname | B6: Name | C6: E-Mail | D6: Mobile | E6: Bemerkungen | F6: m/w | G6: Tarif | H6: Betrag | I6: Anwesenheit
A7: =VLOOKUP(D7,'Master Data'!A:F,2,FALSE) -> Helmut | B7: =VLOOKUP(D7,'Master Data'!A:F,3,FALSE) -> Trippel | C7: =VLOOKUP(D7,'Master Data'!A:F,6,FALSE) -> helmuttrippel@web.de | D7: 004917632111012 | F7: =VLOOKUP(D7,'Master Data'!A:F,4,FALSE) -> m | G7: =VLOOKUP(D7,'Master Data'!A:F,5,FALSE) -> Normal | H7: 190 | I7: x | J7: x | K7: x | L7: x | M7: x | N7: x | P7: x
A8: =VLOOKUP(D8,'Master Data'!A:F,2,FALSE) -> Susanna | B8: =VLOOKUP(D8,'Master Data'!A:F,3,FALSE) -> Zamolo | C8: =VLOOKUP(D8,'Master Data'!A:F,6,FALSE) -> joellezamolo@gmail.com | D8: 0763929994 | F8: =VLOOKUP(D8,'Master Data'!A:F,4,FALSE) -> w | G8: =VLOOKUP(D8,'Master Data'!A:F,5,FALSE) -> Normal | H8: 190 | I8: x | J8: x | K8: x | L8: x | M8: x | N8: x | P8: x
A9: =VLOOKUP(D9,'Master Data'!A:F,2,FALSE) -> Solange | B9: =VLOOKUP(D9,'Master Data'!A:F,3,FALSE) -> Burmeister | C9: =VLOOKUP(D9,'Master Data'!A:F,6,FALSE) -> burmesol27@gmail.com | D9: 0765852702 | E9: 2. Kurse | F9: =VLOOKUP(D9,'Master Data'!A:F,4,FALSE) -> w | G9: =VLOOKUP(D9,'Master Data'!A:F,5,FALSE) -> Normal | H9: 285 | I9: x | J9: x | K9: x | L9: x | M9: x | N9: x | P9: x
A10: =VLOOKUP(D10,'Master Data'!A:F,2,FALSE) -> Linda | B10: =VLOOKUP(D10,'Master Data'!A:F,3,FALSE) -> Baumgartl | C10: =VLOOKUP(D10,'Master Data'!A:F,6,FALSE) -> baumgartl_linda@yahoo.de | D10: 0765610894 | F10: =VLOOKUP(D10,'Master Data'!A:F,4,FALSE) -> w | G10: =VLOOKUP(D10,'Master Data'!A:F,5,FALSE) -> Normal | H10: 190 | I10: x | J10: - | K10: x | L10: x | M10: - | N10: - | P10: x
A11: =VLOOKUP(D11,'Master Data'!A:F,2,FALSE) -> Daniel | B11: =VLOOKUP(D11,'Master Data'!A:F,3,FALSE) -> Gmür | C11: =VLOOKUP(D11,'Master Data'!A:F,6,FALSE) -> danielgmuer5@hotmail.com | D11: 0789352049 | F11: =VLOOKUP(D11,'Master Data'!A:F,4,FALSE) -> m | G11: =VLOOKUP(D11,'Master Data'!A:F,5,FALSE) -> Normal | H11: 160 | I11: x | J11: x | K11: x | L11: x | M11: x | N11: x | P11: x
A12: =VLOOKUP(D12,'Master Data'!A:F,2,FALSE) -> Pia Maria | B12: =VLOOKUP(D12,'Master Data'!A:F,3,FALSE) -> Köppen | C12: =VLOOKUP(D12,'Master Data'!A:F,6,FALSE) -> pia_maria.k@hotmail.com | D12: 0794531696 | F12: =VLOOKUP(D12,'Master Data'!A:F,4,FALSE) -> w | G12: =VLOOKUP(D12,'Master Data'!A:F,5,FALSE) -> Normal | H12: 160 | I12: x | J12: x | K12: x | L12: x | M12: x | N12: x | P12: x
A13: =VLOOKUP(D13,'Master Data'!A:F,2,FALSE) -> Katarzyna | B13: =VLOOKUP(D13,'Master Data'!A:F,3,FALSE) -> Werczynska | C13: =VLOOKUP(D13,'Master Data'!A:F,6,FALSE) -> kwerczynska@op.pl | D13: 0048600945360 | F13: =VLOOKUP(D13,'Master Data'!A:F,4,FALSE) -> w | G13: =VLOOKUP(D13,'Master Data'!A:F,5,FALSE) -> Normal | H13: 190 | I13: x | J13: x | K13: x | L13: x | M13: - | N13: x | P13: x
A14: =VLOOKUP(D14,'Master Data'!A:F,2,FALSE) -> Lukas | B14: =VLOOKUP(D14,'Master Data'!A:F,3,FALSE) -> Erni | C14: =VLOOKUP(D14,'Master Data'!A:F,6,FALSE) -> ernilweber@icloud.com | D14: 0792141383 | F14: =VLOOKUP(D14,'Master Data'!A:F,4,FALSE) -> m | G14: =VLOOKUP(D14,'Master Data'!A:F,5,FALSE) -> Normal | H14: 285 | I14: - | J14: x | K14: x | L14: x | M14: x | N14: x | P14: x
A15: =VLOOKUP(D15,'Master Data'!A:F,2,FALSE) -> Markus | B15: =VLOOKUP(D15,'Master Data'!A:F,3,FALSE) -> Schürch | C15: =VLOOKUP(D15,'Master Data'!A:F,6,FALSE) -> 0 | D15: 0792837450 | F15: =VLOOKUP(D15,'Master Data'!A:F,4,FALSE) -> m | G15: =VLOOKUP(D15,'Master Data'!A:F,5,FALSE) -> Normal | H15: 160 | I15: x | J15: x | K15: x | L15: x | M15: x | N15: - | P15: x
A16: =VLOOKUP(D16,'Master Data'!A:F,2,FALSE) -> Sabina | B16: =VLOOKUP(D16,'Master Data'!A:F,3,FALSE) -> Ziberi | C16: =VLOOKUP(D16,'Master Data'!A:F,6,FALSE) -> s_ziberi@hotmail.ch | D16: 0763434134 | F16: =VLOOKUP(D16,'Master Data'!A:F,4,FALSE) -> w | G16: =VLOOKUP(D16,'Master Data'!A:F,5,FALSE) -> Normal | H16: 160 | I16: x | J16: x | K16: x | L16: x | M16: x | N16: x | P16: x
A17: =VLOOKUP(D17,'Master Data'!A:F,2,FALSE) -> Michelle | B17: =VLOOKUP(D17,'Master Data'!A:F,3,FALSE) -> Roggo | C17: =VLOOKUP(D17,'Master Data'!A:F,6,FALSE) -> michelle222@hotmail.ch | D17: 0793627756 | F17: =VLOOKUP(D17,'Master Data'!A:F,4,FALSE) -> w | G17: =VLOOKUP(D17,'Master Data'!A:F,5,FALSE) -> Normal | H17: 190 | I17: x | J17: x | K17: - | L17: x | M17: x | N17: - | P17: x
A18: =VLOOKUP(D18,'Master Data'!A:F,2,FALSE) -> Arina | B18: =VLOOKUP(D18,'Master Data'!A:F,3,FALSE) -> Kadanik | C18: =VLOOKUP(D18,'Master Data'!A:F,6,FALSE) -> arina.ber@bluewin.ch | D18: 0763493544 | F18: =VLOOKUP(D18,'Master Data'!A:F,4,FALSE) -> w | G18: =VLOOKUP(D18,'Master Data'!A:F,5,FALSE) -> Normal | H18: 190 | I18: x | J18: x | K18: x | L18: x | M18: - | N18: - | P18: x
A19: =VLOOKUP(D19,'Master Data'!A:F,2,FALSE) -> #N/A | B19: =VLOOKUP(D19,'Master Data'!A:F,3,FALSE) -> #N/A | C19: =VLOOKUP(D19,'Master Data'!A:F,6,FALSE) -> #N/A | F19: =VLOOKUP(D19,'Master Data'!A:F,4,FALSE) -> #N/A | G19: =VLOOKUP(D19,'Master Data'!A:F,5,FALSE) -> #N/A
A20: =VLOOKUP(D20,'Master Data'!A:F,2,FALSE) -> #N/A | B20: =VLOOKUP(D20,'Master Data'!A:F,3,FALSE) -> #N/A | C20: =VLOOKUP(D20,'Master Data'!A:F,6,FALSE) -> #N/A | F20: =VLOOKUP(D20,'Master Data'!A:F,4,FALSE) -> #N/A | G20: =VLOOKUP(D20,'Master Data'!A:F,5,FALSE) -> #N/A
A21: =VLOOKUP(D21,'Master Data'!A:F,2,FALSE) -> #N/A | B21: =VLOOKUP(D21,'Master Data'!A:F,3,FALSE) -> #N/A | C21: =VLOOKUP(D21,'Master Data'!A:F,6,FALSE) -> #N/A | F21: =VLOOKUP(D21,'Master Data'!A:F,4,FALSE) -> #N/A | G21: =VLOOKUP(D21,'Master Data'!A:F,5,FALSE) -> #N/A
A22: =VLOOKUP(D22,'Master Data'!A:F,2,FALSE) -> #N/A | B22: =VLOOKUP(D22,'Master Data'!A:F,3,FALSE) -> #N/A | C22: =VLOOKUP(D22,'Master Data'!A:F,6,FALSE) -> #N/A | F22: =VLOOKUP(D22,'Master Data'!A:F,4,FALSE) -> #N/A | G22: =VLOOKUP(D22,'Master Data'!A:F,5,FALSE) -> #N/A
A23: =VLOOKUP(D23,'Master Data'!A:F,2,FALSE) -> #N/A | B23: =VLOOKUP(D23,'Master Data'!A:F,3,FALSE) -> #N/A | C23: =VLOOKUP(D23,'Master Data'!A:F,6,FALSE) -> #N/A | F23: =VLOOKUP(D23,'Master Data'!A:F,4,FALSE) -> #N/A | G23: =VLOOKUP(D23,'Master Data'!A:F,5,FALSE) -> #N/A
A24: =VLOOKUP(D24,'Master Data'!A:F,2,FALSE) -> #N/A | B24: =VLOOKUP(D24,'Master Data'!A:F,3,FALSE) -> #N/A | C24: =VLOOKUP(D24,'Master Data'!A:F,6,FALSE) -> #N/A | F24: =VLOOKUP(D24,'Master Data'!A:F,4,FALSE) -> #N/A | G24: =VLOOKUP(D24,'Master Data'!A:F,5,FALSE) -> #N/A
A25: =VLOOKUP(D25,'Master Data'!A:F,2,FALSE) -> #N/A | B25: =VLOOKUP(D25,'Master Data'!A:F,3,FALSE) -> #N/A | C25: =VLOOKUP(D25,'Master Data'!A:F,6,FALSE) -> #N/A | F25: =VLOOKUP(D25,'Master Data'!A:F,4,FALSE) -> #N/A | G25: =VLOOKUP(D25,'Master Data'!A:F,5,FALSE) -> #N/A
A26: =VLOOKUP(D26,'Master Data'!A:F,2,FALSE) -> #N/A | B26: =VLOOKUP(D26,'Master Data'!A:F,3,FALSE) -> #N/A | C26: =VLOOKUP(D26,'Master Data'!A:F,6,FALSE) -> #N/A | F26: =VLOOKUP(D26,'Master Data'!A:F,4,FALSE) -> #N/A | G26: =VLOOKUP(D26,'Master Data'!A:F,5,FALSE) -> #N/A
A27: =VLOOKUP(D27,'Master Data'!A:F,2,FALSE) -> #N/A | B27: =VLOOKUP(D27,'Master Data'!A:F,3,FALSE) -> #N/A | C27: =VLOOKUP(D27,'Master Data'!A:F,6,FALSE) -> #N/A | F27: =VLOOKUP(D27,'Master Data'!A:F,4,FALSE) -> #N/A | G27: =VLOOKUP(D27,'Master Data'!A:F,5,FALSE) -> #N/A
A28: =VLOOKUP(D28,'Master Data'!A:F,2,FALSE) -> #N/A | B28: =VLOOKUP(D28,'Master Data'!A:F,3,FALSE) -> #N/A | C28: =VLOOKUP(D28,'Master Data'!A:F,6,FALSE) -> #N/A | F28: =VLOOKUP(D28,'Master Data'!A:F,4,FALSE) -> #N/A | G28: =VLOOKUP(D28,'Master Data'!A:F,5,FALSE) -> #N/A
A29: =VLOOKUP(D29,'Master Data'!A:F,2,FALSE) -> #N/A | B29: =VLOOKUP(D29,'Master Data'!A:F,3,FALSE) -> #N/A | C29: =VLOOKUP(D29,'Master Data'!A:F,6,FALSE) -> #N/A | F29: =VLOOKUP(D29,'Master Data'!A:F,4,FALSE) -> #N/A | G29: =VLOOKUP(D29,'Master Data'!A:F,5,FALSE) -> #N/A
A30: =VLOOKUP(D30,'Master Data'!A:F,2,FALSE) -> #N/A | B30: =VLOOKUP(D30,'Master Data'!A:F,3,FALSE) -> #N/A | C30: =VLOOKUP(D30,'Master Data'!A:F,6,FALSE) -> #N/A | F30: =VLOOKUP(D30,'Master Data'!A:F,4,FALSE) -> #N/A | G30: =VLOOKUP(D30,'Master Data'!A:F,5,FALSE) -> #N/A
A31: =VLOOKUP(D31,'Master Data'!A:F,2,FALSE) -> #N/A | B31: =VLOOKUP(D31,'Master Data'!A:F,3,FALSE) -> #N/A | C31: =VLOOKUP(D31,'Master Data'!A:F,6,FALSE) -> #N/A | F31: =VLOOKUP(D31,'Master Data'!A:F,4,FALSE) -> #N/A | G31: =VLOOKUP(D31,'Master Data'!A:F,5,FALSE) -> #N/A
A32: =VLOOKUP(D32,'Master Data'!A:F,2,FALSE) -> #N/A | B32: =VLOOKUP(D32,'Master Data'!A:F,3,FALSE) -> #N/A | C32: =VLOOKUP(D32,'Master Data'!A:F,5,FALSE) -> #N/A | G32: Einnahmen | H32: =SUM(H7:H31) -> 2350

Sheet Di_Salsa Beginner Stufe 1
A1: Anmeldungen - Salsa Beginner Stufe 1
A3: Datum: | B3: 06.01.2026 - 03.03.2026 | D3: Kurstag: | E3: Dienstag | G3: Lehrer: | H3: Jelena & Yannick
A4: Zeit: | B4: 20:30 - 21:30 | D4: Ort: | E4: Elisabethenanlage 7 | G4: Preis: | H4: CHF 190.- / CHF 160.-
A6: Vorname | B6: Name | C6: E-Mail | D6: Mobile | E6: Bemerkungen | F6: m/w | G6: Tarif | H6: Betrag | I6: Anwesenheit
A7: =VLOOKUP(D7,'Master Data'!A:F,2,FALSE) -> #N/A | B7: =VLOOKUP(D7,'Master Data'!A:F,3,FALSE) -> #N/A | C7: =VLOOKUP(D7,'Master Data'!A:F,6,FALSE) -> #N/A | F7: =VLOOKUP(D7,'Master Data'!A:F,4,FALSE) -> #N/A | G7: =VLOOKUP(D7,'Master Data'!A:F,5,FALSE) -> #N/A
A8: =VLOOKUP(D8,'Master Data'!A:F,2,FALSE) -> #N/A | B8: =VLOOKUP(D8,'Master Data'!A:F,3,FALSE) -> #N/A | C8: =VLOOKUP(D8,'Master Data'!A:F,6,FALSE) -> #N/A | F8: =VLOOKUP(D8,'Master Data'!A:F,4,FALSE) -> #N/A | G8: =VLOOKUP(D8,'Master Data'!A:F,5,FALSE) -> #N/A
A9: =VLOOKUP(D9,'Master Data'!A:F,2,FALSE) -> #N/A | B9: =VLOOKUP(D9,'Master Data'!A:F,3,FALSE) -> #N/A | C9: =VLOOKUP(D9,'Master Data'!A:F,6,FALSE) -> #N/A | F9: =VLOOKUP(D9,'Master Data'!A:F,4,FALSE) -> #N/A | G9: =VLOOKUP(D9,'Master Data'!A:F,5,FALSE) -> #N/A | I9: - | O9: -
A10: =VLOOKUP(D10,'Master Data'!A:F,2,FALSE) -> #N/A | B10: =VLOOKUP(D10,'Master Data'!A:F,3,FALSE) -> #N/A | C10: =VLOOKUP(D10,'Master Data'!A:F,6,FALSE) -> #N/A | F10: =VLOOKUP(D10,'Master Data'!A:F,4,FALSE) -> #N/A | G10: =VLOOKUP(D10,'Master Data'!A:F,5,FALSE) -> #N/A | I10: - | O10: -
A11: =VLOOKUP(D11,'Master Data'!A:F,2,FALSE) -> #N/A | B11: =VLOOKUP(D11,'Master Data'!A:F,3,FALSE) -> #N/A | C11: =VLOOKUP(D11,'Master Data'!A:F,6,FALSE) -> #N/A | F11: =VLOOKUP(D11,'Master Data'!A:F,4,FALSE) -> #N/A | G11: =VLOOKUP(D11,'Master Data'!A:F,5,FALSE) -> #N/A
A12: =VLOOKUP(D12,'Master Data'!A:F,2,FALSE) -> #N/A | B12: =VLOOKUP(D12,'Master Data'!A:F,3,FALSE) -> #N/A | C12: =VLOOKUP(D12,'Master Data'!A:F,6,FALSE) -> #N/A | F12: =VLOOKUP(D12,'Master Data'!A:F,4,FALSE) -> #N/A | G12: =VLOOKUP(D12,'Master Data'!A:F,5,FALSE) -> #N/A
A13: =VLOOKUP(D13,'Master Data'!A:F,2,FALSE) -> #N/A | B13: =VLOOKUP(D13,'Master Data'!A:F,3,FALSE) -> #N/A | C13: =VLOOKUP(D13,'Master Data'!A:F,6,FALSE) -> #N/A | F13: =VLOOKUP(D13,'Master Data'!A:F,4,FALSE) -> #N/A | G13: =VLOOKUP(D13,'Master Data'!A:F,5,FALSE) -> #N/A
A14: =VLOOKUP(D14,'Master Data'!A:F,2,FALSE) -> #N/A | B14: =VLOOKUP(D14,'Master Data'!A:F,3,FALSE) -> #N/A | C14: =VLOOKUP(D14,'Master Data'!A:F,6,FALSE) -> #N/A | F14: =VLOOKUP(D14,'Master Data'!A:F,4,FALSE) -> #N/A | G14: =VLOOKUP(D14,'Master Data'!A:F,5,FALSE) -> #N/A
A15: =VLOOKUP(D15,'Master Data'!A:F,2,FALSE) -> #N/A | B15: =VLOOKUP(D15,'Master Data'!A:F,3,FALSE) -> #N/A | C15: =VLOOKUP(D15,'Master Data'!A:F,6,FALSE) -> #N/A | F15: =VLOOKUP(D15,'Master Data'!A:F,4,FALSE) -> #N/A | G15: =VLOOKUP(D15,'Master Data'!A:F,5,FALSE) -> #N/A
A16: =VLOOKUP(D16,'Master Data'!A:F,2,FALSE) -> #N/A | B16: =VLOOKUP(D16,'Master Data'!A:F,3,FALSE) -> #N/A | C16: =VLOOKUP(D16,'Master Data'!A:F,6,FALSE) -> #N/A | F16: =VLOOKUP(D16,'Master Data'!A:F,4,FALSE) -> #N/A | G16: =VLOOKUP(D16,'Master Data'!A:F,5,FALSE) -> #N/A
A17: =VLOOKUP(D17,'Master Data'!A:F,2,FALSE) -> #N/A | B17: =VLOOKUP(D17,'Master Data'!A:F,3,FALSE) -> #N/A | C17: =VLOOKUP(D17,'Master Data'!A:F,6,FALSE) -> #N/A | F17: =VLOOKUP(D17,'Master Data'!A:F,4,FALSE) -> #N/A | G17: =VLOOKUP(D17,'Master Data'!A:F,5,FALSE) -> #N/A
A18: =VLOOKUP(D18,'Master Data'!A:F,2,FALSE) -> #N/A | B18: =VLOOKUP(D18,'Master Data'!A:F,3,FALSE) -> #N/A | C18: =VLOOKUP(D18,'Master Data'!A:F,6,FALSE) -> #N/A | F18: =VLOOKUP(D18,'Master Data'!A:F,4,FALSE) -> #N/A | G18: =VLOOKUP(D18,'Master Data'!A:F,5,FALSE) -> #N/A
A19: =VLOOKUP(D19,'Master Data'!A:F,2,FALSE) -> #N/A | B19: =VLOOKUP(D19,'Master Data'!A:F,3,FALSE) -> #N/A | C19: =VLOOKUP(D19,'Master Data'!A:F,6,FALSE) -> #N/A | F19: =VLOOKUP(D19,'Master Data'!A:F,4,FALSE) -> #N/A | G19: =VLOOKUP(D19,'Master Data'!A:F,5,FALSE) -> #N/A
A20: =VLOOKUP(D20,'Master Data'!A:F,2,FALSE) -> #N/A | B20: =VLOOKUP(D20,'Master Data'!A:F,3,FALSE) -> #N/A | C20: =VLOOKUP(D20,'Master Data'!A:F,6,FALSE) -> #N/A | F20: =VLOOKUP(D20,'Master Data'!A:F,4,FALSE) -> #N/A | G20: =VLOOKUP(D20,'Master Data'!A:F,5,FALSE) -> #N/A
A21: =VLOOKUP(D21,'Master Data'!A:F,2,FALSE) -> #N/A | B21: =VLOOKUP(D21,'Master Data'!A:F,3,FALSE) -> #N/A | C21: =VLOOKUP(D21,'Master Data'!A:F,6,FALSE) -> #N/A | F21: =VLOOKUP(D21,'Master Data'!A:F,4,FALSE) -> #N/A | G21: =VLOOKUP(D21,'Master Data'!A:F,5,FALSE) -> #N/A
A22: =VLOOKUP(D22,'Master Data'!A:F,2,FALSE) -> #N/A | B22: =VLOOKUP(D22,'Master Data'!A:F,3,FALSE) -> #N/A | C22: =VLOOKUP(D22,'Master Data'!A:F,6,FALSE) -> #N/A | F22: =VLOOKUP(D22,'Master Data'!A:F,4,FALSE) -> #N/A | G22: =VLOOKUP(D22,'Master Data'!A:F,5,FALSE) -> #N/A
... A29: =VLOOKUP(D29,'Master Data'!A:F,2,FALSE) -> #N/A | B29: =VLOOKUP(D29,'Master Data'!A:F,3,FALSE) -> #N/A | C29: =VLOOKUP(D29,'Master Data'!A:F,6,FALSE) -> #N/A | F29: =VLOOKUP(D29,'Master Data'!A:F,4,FALSE) -> #N/A | G29: =VLOOKUP(D29,'Master Data'!A:F,5,FALSE) -> #N/A
A30: =VLOOKUP(D30,'Master Data'!A:F,2,FALSE) -> #N/A | B30: =VLOOKUP(D30,'Master Data'!A:F,3,FALSE) -> #N/A | C30: =VLOOKUP(D30,'Master Data'!A:F,5,FALSE) -> #N/A | F30: =VLOOKUP(D30,'Master Data'!A:F,4,FALSE) -> #N/A | G30: =VLOOKUP(D30,'Master Data'!A:F,5,FALSE) -> #N/A
A31: =VLOOKUP(D31,'Master Data'!A:F,2,FALSE) -> #N/A | B31: =VLOOKUP(D31,'Master Data'!A:F,3,FALSE) -> #N/A | C31: =VLOOKUP(D31,'Master Data'!A:F,5,FALSE) -> #N/A | F31: =VLOOKUP(D31,'Master Data'!A:F,4,FALSE) -> #N/A | G31: =VLOOKUP(D31,'Master Data'!A:F,5,FALSE) -> #N/A
G32: Einnahmen | H32: =SUM(H7:H31) -> 0

Sheet Mi_Salsa Beginner Stufe 1
A1: Anmeldungen - Salsa Beginner Stufe 1
A3: Datum: | B3: 07.01.2026 - 04.03.2026 | D3: Kurstag: | E3: Mittwoch | G3: Lehrer: | H3: Jenny & Sebastian
A4: Zeit: | B4: 18:30 - 19:30 | D4: Ort: | E4: Elisabethenanlage 7 | G4: Preis: | H4: CHF 190.- / CHF 160.-
A6: Vorname | B6: Name | C6: E-Mail | D6: Mobile | E6: Bemerkungen | F6: m/w | G6: Tarif | H6: Betrag | I6: Anwesenheit
A7: =VLOOKUP(D7,'Master Data'!A:F,2,FALSE) -> Valentin | B7: =VLOOKUP(D7,'Master Data'!A:F,3,FALSE) -> Alvarellos | C7: =VLOOKUP(D7,'Master Data'!A:F,6,FALSE) -> valentinbetesh97@gmail.com | D7: 0033621375222 | F7: =VLOOKUP(D7,'Master Data'!A:F,4,FALSE) -> m | G7: =VLOOKUP(D7,'Master Data'!A:F,5,FALSE) -> Normal | H7: 150 | I7: x | J7: x | K7: X | M7: X
A8: =VLOOKUP(D8,'Master Data'!A:F,2,FALSE) -> Meral | B8: =VLOOKUP(D8,'Master Data'!A:F,3,FALSE) -> Korkmaz | C8: =VLOOKUP(D8,'Master Data'!A:F,6,FALSE) -> meral_kz@hotmail.com | D8: 0797914500 | F8: =VLOOKUP(D8,'Master Data'!A:F,4,FALSE) -> w | G8: =VLOOKUP(D8,'Master Data'!A:F,5,FALSE) -> Normal | H8: 190 | I8: x | J8: x | K8: X | M8: X
A9: =VLOOKUP(D9,'Master Data'!A:F,2,FALSE) -> Ràel | B9: =VLOOKUP(D9,'Master Data'!A:F,3,FALSE) -> Probst | C9: =VLOOKUP(D9,'Master Data'!A:F,6,FALSE) -> p.rael@hotmail.com | D9: 0782171086 | F9: =VLOOKUP(D9,'Master Data'!A:F,4,FALSE) -> w | G9: =VLOOKUP(D9,'Master Data'!A:F,5,FALSE) -> Paar | H9: 160 | I9: x | J9: x | K9: X | M9: X
A10: =VLOOKUP(D10,'Master Data'!A:F,2,FALSE) -> Pascal | B10: =VLOOKUP(D10,'Master Data'!A:F,3,FALSE) -> Aeschi | C10: =VLOOKUP(D10,'Master Data'!A:F,6,FALSE) -> aeschi.p@gmx.ch | D10: 0788436655 | F10: =VLOOKUP(D10,'Master Data'!A:F,4,FALSE) -> m | G10: =VLOOKUP(D10,'Master Data'!A:F,5,FALSE) -> Paar | H10: 160 | I10: x | J10: x | K10: X | M10: X
A11: =VLOOKUP(D11,'Master Data'!A:F,2,FALSE) -> Marvin | B11: =VLOOKUP(D11,'Master Data'!A:F,3,FALSE) -> Hankel | C11: =VLOOKUP(D11,'Master Data'!A:F,6,FALSE) -> marv.hankel@gmail.com | D11: 004915129053132 | E11: 2. Kurse | F11: =VLOOKUP(D11,'Master Data'!A:F,4,FALSE) -> m | G11: =VLOOKUP(D11,'Master Data'!A:F,5,FALSE) -> Normal | H11: 285 | I11: x | J11: x | K11: - | M11: X
A12: =VLOOKUP(D12,'Master Data'!A:F,2,FALSE) -> Corey | B12: =VLOOKUP(D12,'Master Data'!A:F,3,FALSE) -> Rigley | C12: =VLOOKUP(D12,'Master Data'!A:F,6,FALSE) -> coreyrigley@gmail.com | D12: 00353863495138 | F12: =VLOOKUP(D12,'Master Data'!A:F,4,FALSE) -> m | G12: =VLOOKUP(D12,'Master Data'!A:F,5,FALSE) -> Normal | H12: 190 | I12: x | J12: x | K12: X | M12: X
A13: =VLOOKUP(D13,'Master Data'!A:F,2,FALSE) -> Martina | B13: =VLOOKUP(D13,'Master Data'!A:F,3,FALSE) -> Veider Hochfilzer | C13: =VLOOKUP(D13,'Master Data'!A:F,6,FALSE) -> veider@veider.com | D13: 004369910476550 | F13: =VLOOKUP(D13,'Master Data'!A:F,4,FALSE) -> w | G13: =VLOOKUP(D13,'Master Data'!A:F,5,FALSE) -> Normal | H13: 190 | I13: x | J13: x | K13: X | M13: X | O13: -
A14: =VLOOKUP(D14,'Master Data'!A:F,2,FALSE) -> Thomas | B14: =VLOOKUP(D14,'Master Data'!A:F,3,FALSE) -> Studer | C14: =VLOOKUP(D14,'Master Data'!A:F,6,FALSE) -> th.studer@gmail.com | D14: 0797942980 | F14: =VLOOKUP(D14,'Master Data'!A:F,4,FALSE) -> m | G14: =VLOOKUP(D14,'Master Data'!A:F,5,FALSE) -> Normal | H14: 190 | I14: x | J14: - | K14: X | M14: X
A15: =VLOOKUP(D15,'Master Data'!A:F,2,FALSE) -> Doris | B15: =VLOOKUP(D15,'Master Data'!A:F,3,FALSE) -> Aznar | C15: =VLOOKUP(D15,'Master Data'!A:F,6,FALSE) -> doris_aznar@hotmail.com | D15: 0765719154 | E15: Leader | F15: m | G15: =VLOOKUP(D15,'Master Data'!A:F,5,FALSE) -> Normal | I15: x | J15: x | K15: X | M15: X
A16: =VLOOKUP(D16,'Master Data'!A:F,2,FALSE) -> Cristian | B16: =VLOOKUP(D16,'Master Data'!A:F,3,FALSE) -> Aznar | C16: =VLOOKUP(D16,'Master Data'!A:F,6,FALSE) -> krisy84@hotmail.com | D16: 0765811015 | F16: =VLOOKUP(D16,'Master Data'!A:F,4,FALSE) -> m | G16: =VLOOKUP(D16,'Master Data'!A:F,5,FALSE) -> Normal | H16: 190 | I16: x | J16: x | K16: X | M16: X
A17: =VLOOKUP(D17,'Master Data'!A:F,2,FALSE) -> Bülent | B17: =VLOOKUP(D17,'Master Data'!A:F,3,FALSE) -> Ekinci | C17: =VLOOKUP(D17,'Master Data'!A:F,6,FALSE) -> buelentekinci24@gamil.com | D17: 00491637919721 | E17: Salsaflow Pass | F17: =VLOOKUP(D17,'Master Data'!A:F,4,FALSE) -> m | G17: =VLOOKUP(D17,'Master Data'!A:F,5,FALSE) -> Normal | I17: x | J17: x | K17: X | M17: X
A18: =VLOOKUP(D18,'Master Data'!A:F,2,FALSE) -> Anastasia | B18: =VLOOKUP(D18,'Master Data'!A:F,3,FALSE) -> Zeugin | C18: =VLOOKUP(D18,'Master Data'!A:F,6,FALSE) -> a.zeugin@gmx.ch | D18: 0791768471 | F18: =VLOOKUP(D18,'Master Data'!A:F,4,FALSE) -> w | G18: =VLOOKUP(D18,'Master Data'!A:F,5,FALSE) -> Paar | H18: 160 | I18: x | J18: x | K18: X | M18: X
A19: =VLOOKUP(D19,'Master Data'!A:F,2,FALSE) -> Sassoundine | B19: =VLOOKUP(D19,'Master Data'!A:F,3,FALSE) -> Sibabi | C19: =VLOOKUP(D19,'Master Data'!A:F,6,FALSE) -> 0 | D19: 0791768471-1 | F19: =VLOOKUP(D19,'Master Data'!A:F,4,FALSE) -> m | G19: =VLOOKUP(D19,'Master Data'!A:F,5,FALSE) -> Paar | H19: 160 | I19: x | J19: x | K19: X | M19: X | O19: - | P19: -
A20: =VLOOKUP(D20,'Master Data'!A:F,2,FALSE) -> Madlen | B20: =VLOOKUP(D20,'Master Data'!A:F,3,FALSE) -> Holzer | C20: =VLOOKUP(D20,'Master Data'!A:F,6,FALSE) -> madlen_holzer@hotmail.com | D20: 0796482119 | E20: Schnuppern 2. Kurstag | F20: =VLOOKUP(D20,'Master Data'!A:F,4,FALSE) -> w | G20: =VLOOKUP(D20,'Master Data'!A:F,5,FALSE) -> Normal | H20: 160 | I20: - | J20: x | K20: - | M20: X
A21: =VLOOKUP(D21,'Master Data'!A:F,2,FALSE) -> Bianca | B21: =VLOOKUP(D21,'Master Data'!A:F,3,FALSE) -> Heidersdorf | C21: =VLOOKUP(D21,'Master Data'!A:F,6,FALSE) -> biancah._@web.de | D21: 00491751678302 | F21: =VLOOKUP(D21,'Master Data'!A:F,4,FALSE) -> w | G21: =VLOOKUP(D21,'Master Data'!A:F,5,FALSE) -> Paar | H21: 160 | I21: x | J21: x | K21: X | M21: X | O21: -
A22: =VLOOKUP(D22,'Master Data'!A:F,2,FALSE) -> Adrian | B22: =VLOOKUP(D22,'Master Data'!A:F,3,FALSE) -> Brumann | C22: =VLOOKUP(D22,'Master Data'!A:F,6,FALSE) -> brumanski@hotmail.com | D22: 0787534979 | F22: =VLOOKUP(D22,'Master Data'!A:F,4,FALSE) -> m | G22: =VLOOKUP(D22,'Master Data'!A:F,5,FALSE) -> Paar | H22: 160 | I22: x | J22: x | K22: X | M22: X | O22: -
A23: =VLOOKUP(D23,'Master Data'!A:F,2,FALSE) -> Salome | B23: =VLOOKUP(D23,'Master Data'!A:F,3,FALSE) -> Amstutz | C23: =VLOOKUP(D23,'Master Data'!A:F,6,FALSE) -> salome.amstutz@gmail.com | D23: 0764317333 | F23: =VLOOKUP(D23,'Master Data'!A:F,4,FALSE) -> w | G23: =VLOOKUP(D23,'Master Data'!A:F,5,FALSE) -> Paar | H23: 110 | I23: x | J23: x | K23: X | L23: - | M23: - | N23: - | O23: -
A24: =VLOOKUP(D24,'Master Data'!A:F,2,FALSE) -> Cédric | B24: =VLOOKUP(D24,'Master Data'!A:F,3,FALSE) -> Sidler | C24: =VLOOKUP(D24,'Master Data'!A:F,6,FALSE) -> c.sidler@hotmail.com | D24: 0764317333-1 | F24: =VLOOKUP(D24,'Master Data'!A:F,4,FALSE) -> m | G24: =VLOOKUP(D24,'Master Data'!A:F,5,FALSE) -> Paar | H24: 110 | I24: x | J24: x | K24: X | L24: - | M24: - | N24: - | O24: -
A25: =VLOOKUP(D25,'Master Data'!A:F,2,FALSE) -> Ana | B25: =VLOOKUP(D25,'Master Data'!A:F,3,FALSE) -> Cruz | C25: =VLOOKUP(D25,'Master Data'!A:F,6,FALSE) -> ag-more@live.com.pt | D25: 0762259899 | F25: =VLOOKUP(D25,'Master Data'!A:F,4,FALSE) -> w | G25: =VLOOKUP(D25,'Master Data'!A:F,5,FALSE) -> Normal | H25: 190 | J25: x | K25: X | M25: X
A26: =VLOOKUP(D26,'Master Data'!A:F,2,FALSE) -> Silvan | B26: =VLOOKUP(D26,'Master Data'!A:F,3,FALSE) -> Irniger | C26: =VLOOKUP(D26,'Master Data'!A:F,6,FALSE) -> silvanirniger@gmail.com | D26: 0768170076 | F26: =VLOOKUP(D26,'Master Data'!A:F,4,FALSE) -> m | G26: =VLOOKUP(D26,'Master Data'!A:F,5,FALSE) -> Paar | H26: 100 | I26: - | J26: - | K26: X | M26: X
A27: =VLOOKUP(D27,'Master Data'!A:F,2,FALSE) -> Nadzeya | B27: =VLOOKUP(D27,'Master Data'!A:F,3,FALSE) -> Kurzava | C27: =VLOOKUP(D27,'Master Data'!A:F,6,FALSE) -> nadzeya.kurzava@gmail.com | D27: 0774296686 | F27: =VLOOKUP(D27,'Master Data'!A:F,4,FALSE) -> w | G27: =VLOOKUP(D27,'Master Data'!A:F,5,FALSE) -> Paar | H27: 100 | I27: - | J27: - | K27: X | M27: X
A28: =VLOOKUP(D28,'Master Data'!A:F,2,FALSE) -> Isabel | B28: =VLOOKUP(D28,'Master Data'!A:F,3,FALSE) -> Garcia | C28: =VLOOKUP(D28,'Master Data'!A:F,6,FALSE) -> 0 | D28: 0793407579 | F28: m | G28: =VLOOKUP(D28,'Master Data'!A:F,5,FALSE) -> Pushflow | O28: - | P28: -
A29: =VLOOKUP(D29,'Master Data'!A:F,2,FALSE) -> #N/A | B29: =VLOOKUP(D29,'Master Data'!A:F,3,FALSE) -> #N/A | C29: =VLOOKUP(D29,'Master Data'!A:F,6,FALSE) -> #N/A | G29: =VLOOKUP(D29,'Master Data'!A:F,5,FALSE) -> #N/A
A30: =VLOOKUP(D30,'Master Data'!A:F,2,FALSE) -> #N/A | B30: =VLOOKUP(D30,'Master Data'!A:F,3,FALSE) -> #N/A | C30: =VLOOKUP(D30,'Master Data'!A:F,6,FALSE) -> #N/A | F30: =VLOOKUP(D30,'Master Data'!A:F,4,FALSE) -> #N/A | G30: =VLOOKUP(D30,'Master Data'!A:F,5,FALSE) -> #N/A
A31: =VLOOKUP(D31,'Master Data'!A:F,2,FALSE) -> #N/A | B31: =VLOOKUP(D31,'Master Data'!A:F,3,FALSE) -> #N/A | C31: =VLOOKUP(D31,'Master Data'!A:F,6,FALSE) -> #N/A | F31: =VLOOKUP(D31,'Master Data'!A:F,4,FALSE) -> #N/A | G31: =VLOOKUP(D31,'Master Data'!A:F,5,FALSE) -> #N/A
A32: =VLOOKUP(D32,'Master Data'!A:F,2,FALSE) -> #N/A | B32: =VLOOKUP(D32,'Master Data'!A:F,3,FALSE) -> #N/A | C32: =VLOOKUP(D32,'Master Data'!A:F,6,FALSE) -> #N/A | F32: =VLOOKUP(D32,'Master Data'!A:F,4,FALSE) -> #N/A | G32: =VLOOKUP(D32,'Master Data'!A:F,5,FALSE) -> #N/A
A33: =VLOOKUP(D33,'Master Data'!A:F,2,FALSE) -> #N/A | B33: =VLOOKUP(D33,'Master Data'!A:F,3,FALSE) -> #N/A | C33: =VLOOKUP(D33,'Master Data'!A:F,5,FALSE) -> #N/A | G33: Einnahmen | H33: =SUM(H7:H32) -> 3115

Sheet Mi_Bodymovement & Ladystyle
A1: Anmeldungen - Bodymovement & Ladystyle
A3: Datum: | B3: 07.01.2026 - 04.03.2026 | D3: Kurstag: | E3: Mittwoch | G3: Lehrer: | H3: Claudia
A4: Zeit: | B4: 18:30 - 19:30 | D4: Ort: | E4: Elisabethenanlage 7 | G4: Preis: | H4: CHF 190.- / CHF 160.-
A6: Vorname | B6: Name | C6: E-Mail | D6: Mobile | E6: Bemerkungen | F6: m/w | G6: Tarif | H6: Betrag | I6: Anwesenheit
A7: =VLOOKUP(D7,'Master Data'!A:F,2,FALSE) -> Julia | B7: =VLOOKUP(D7,'Master Data'!A:F,3,FALSE) -> Ritter | C7: =VLOOKUP(D7,'Master Data'!A:F,6,FALSE) -> julia_schlachter@gmx.ch | D7: 0793974160 | F7: =VLOOKUP(D7,'Master Data'!A:F,4,FALSE) -> w | G7: =VLOOKUP(D7,'Master Data'!A:F,5,FALSE) -> Normal | H7: 30 | I7: x | M7: -
A8: =VLOOKUP(D8,'Master Data'!A:F,2,FALSE) -> Iryna | B8: =VLOOKUP(D8,'Master Data'!A:F,3,FALSE) -> Marrini | C8: =VLOOKUP(D8,'Master Data'!A:F,6,FALSE) -> iryna@marrini.com | D8: 0772655009 | E8: Salsaflow Pass | F8: =VLOOKUP(D8,'Master Data'!A:F,4,FALSE) -> w | G8: =VLOOKUP(D8,'Master Data'!A:F,5,FALSE) -> Normal | M8: x
A9: =VLOOKUP(D9,'Master Data'!A:F,2,FALSE) -> Alexandra | B9: =VLOOKUP(D9,'Master Data'!A:F,3,FALSE) -> Meier | C9: =VLOOKUP(D9,'Master Data'!A:F,6,FALSE) -> alexandra.meier@unibas.ch | D9: 0764306119 | E9: Pushflow | F9: =VLOOKUP(D9,'Master Data'!A:F,4,FALSE) -> w | G9: =VLOOKUP(D9,'Master Data'!A:F,5,FALSE) -> Paar | I9: x | M9: -
A10: =VLOOKUP(D10,'Master Data'!A:F,2,FALSE) -> Jo | B10: =VLOOKUP(D10,'Master Data'!A:F,3,FALSE) -> Storrar | C10: =VLOOKUP(D10,'Master Data'!A:F,6,FALSE) -> joanne_storrar@hotmail.com | D10: 00447723012843 | F10: =VLOOKUP(D10,'Master Data'!A:F,4,FALSE) -> w | G10: =VLOOKUP(D10,'Master Data'!A:F,5,FALSE) -> Pushflow | I10: x | M10: -
A11: =VLOOKUP(D11,'Master Data'!A:F,2,FALSE) -> Rita | B11: =VLOOKUP(D11,'Master Data'!A:F,3,FALSE) -> Gonzalez | C11: =VLOOKUP(D11,'Master Data'!A:F,6,FALSE) -> ritamaria.gd@gmail.com | D11: 0034605261891 | F11: =VLOOKUP(D11,'Master Data'!A:F,4,FALSE) -> w | G11: =VLOOKUP(D11,'Master Data'!A:F,5,FALSE) -> Pushflow | I11: x | M11: -
A12: =VLOOKUP(D12,'Master Data'!A:F,2,FALSE) -> Ali | B12: =VLOOKUP(D12,'Master Data'!A:F,3,FALSE) -> Üstündag | C12: =VLOOKUP(D12,'Master Data'!A:F,6,FALSE) -> ali.uestuendag@gmail.com | D12: 0786262771 | F12: =VLOOKUP(D12,'Master Data'!A:F,4,FALSE) -> m | G12: =VLOOKUP(D12,'Master Data'!A:F,5,FALSE) -> Pushflow | I12: x | M12: -
A13: =VLOOKUP(D13,'Master Data'!A:F,2,FALSE) -> Jenny | B13: =VLOOKUP(D13,'Master Data'!A:F,3,FALSE) -> Castro | C13: =VLOOKUP(D13,'Master Data'!A:F,6,FALSE) -> castro.jenny@hotmail.ch | D13: 0794500626 | F13: =VLOOKUP(D13,'Master Data'!A:F,4,FALSE) -> w | G13: =VLOOKUP(D13,'Master Data'!A:F,5,FALSE) -> Pushflow | I13: x | M13: -
A14: =VLOOKUP(D14,'Master Data'!A:F,2,FALSE) -> Maarten | B14: =VLOOKUP(D14,'Master Data'!A:F,3,FALSE) -> De Laat | C14: =VLOOKUP(D14,'Master Data'!A:F,6,FALSE) -> smaaardy@gmail.com | D14: 0791928289 | F14: =VLOOKUP(D14,'Master Data'!A:F,4,FALSE) -> m | G14: =VLOOKUP(D14,'Master Data'!A:F,5,FALSE) -> Pushflow | I14: x | M14: -
A15: =VLOOKUP(D15,'Master Data'!A:F,2,FALSE) -> Rabea | B15: =VLOOKUP(D15,'Master Data'!A:F,3,FALSE) -> Widmer | C15: =VLOOKUP(D15,'Master Data'!A:F,6,FALSE) -> widmerrabea@gmail.com | D15: 0797127581 | F15: =VLOOKUP(D15,'Master Data'!A:F,4,FALSE) -> w | G15: =VLOOKUP(D15,'Master Data'!A:F,5,FALSE) -> Pushflow | I15: x | M15: -
A16: =VLOOKUP(D16,'Master Data'!A:F,2,FALSE) -> Lena | B16: =VLOOKUP(D16,'Master Data'!A:F,3,FALSE) -> Bremer | C16: =VLOOKUP(D16,'Master Data'!A:F,6,FALSE) -> lena_bremer96@web.de | D16: 0767361357 | F16: =VLOOKUP(D16,'Master Data'!A:F,4,FALSE) -> w | G16: =VLOOKUP(D16,'Master Data'!A:F,5,FALSE) -> Pushflow | I16: x | M16: -
A17: =VLOOKUP(D17,'Master Data'!A:F,2,FALSE) -> Sarah | B17: =VLOOKUP(D17,'Master Data'!A:F,3,FALSE) -> Lindenmayer | C17: =VLOOKUP(D17,'Master Data'!A:F,6,FALSE) -> slindenmayer@outlook.de | D17: 00491778442461 | F17: =VLOOKUP(D17,'Master Data'!A:F,4,FALSE) -> w | G17: =VLOOKUP(D17,'Master Data'!A:F,5,FALSE) -> Normal | H17: 240 | I17: x | M17: x
A18: =VLOOKUP(D18,'Master Data'!A:F,2,FALSE) -> #N/A | B18: =VLOOKUP(D18,'Master Data'!A:F,3,FALSE) -> #N/A | C18: =VLOOKUP(D18,'Master Data'!A:F,6,FALSE) -> #N/A | F18: =VLOOKUP(D18,'Master Data'!A:F,4,FALSE) -> #N/A | G18: =VLOOKUP(D18,'Master Data'!A:F,5,FALSE) -> #N/A
A19: =VLOOKUP(D19,'Master Data'!A:F,2,FALSE) -> #N/A | B19: =VLOOKUP(D19,'Master Data'!A:F,3,FALSE) -> #N/A | C19: =VLOOKUP(D19,'Master Data'!A:F,6,FALSE) -> #N/A | F19: =VLOOKUP(D19,'Master Data'!A:F,4,FALSE) -> #N/A | G19: =VLOOKUP(D19,'Master Data'!A:F,5,FALSE) -> #N/A
A20: =VLOOKUP(D20,'Master Data'!A:F,2,FALSE) -> #N/A | B20: =VLOOKUP(D20,'Master Data'!A:F,3,FALSE) -> #N/A | C20: =VLOOKUP(D20,'Master Data'!A:F,6,FALSE) -> #N/A | F20: =VLOOKUP(D20,'Master Data'!A:F,4,FALSE) -> #N/A | G20: =VLOOKUP(D20,'Master Data'!A:F,5,FALSE) -> #N/A
A21: =VLOOKUP(D21,'Master Data'!A:F,2,FALSE) -> #N/A | B21: =VLOOKUP(D21,'Master Data'!A:F,3,FALSE) -> #N/A | C21: =VLOOKUP(D21,'Master Data'!A:F,6,FALSE) -> #N/A | F21: =VLOOKUP(D21,'Master Data'!A:F,4,FALSE) -> #N/A | G21: =VLOOKUP(D21,'Master Data'!A:F,5,FALSE) -> #N/A
A22: =VLOOKUP(D22,'Master Data'!A:F,2,FALSE) -> #N/A | B22: =VLOOKUP(D22,'Master Data'!A:F,3,FALSE) -> #N/A | C22: =VLOOKUP(D22,'Master Data'!A:F,6,FALSE) -> #N/A | F22: =VLOOKUP(D22,'Master Data'!A:F,4,FALSE) -> #N/A | G22: =VLOOKUP(D22,'Master Data'!A:F,5,FALSE) -> #N/A
A23: =VLOOKUP(D23,'Master Data'!A:F,2,FALSE) -> #N/A | B23: =VLOOKUP(D23,'Master Data'!A:F,3,FALSE) -> #N/A | C23: =VLOOKUP(D23,'Master Data'!A:F,6,FALSE) -> #N/A | F23: =VLOOKUP(D23,'Master Data'!A:F,4,FALSE) -> #N/A | G23: =VLOOKUP(D23,'Master Data'!A:F,5,FALSE) -> #N/A
A24: =VLOOKUP(D24,'Master Data'!A:F,2,FALSE) -> #N/A | B24: =VLOOKUP(D24,'Master Data'!A:F,3,FALSE) -> #N/A | C24: =VLOOKUP(D24,'Master Data'!A:F,6,FALSE) -> #N/A | F24: =VLOOKUP(D24,'Master Data'!A:F,4,FALSE) -> #N/A | G24: =VLOOKUP(D24,'Master Data'!A:F,5,FALSE) -> #N/A
A25: =VLOOKUP(D25,'Master Data'!A:F,2,FALSE) -> #N/A | B25: =VLOOKUP(D25,'Master Data'!A:F,3,FALSE) -> #N/A | C25: =VLOOKUP(D25,'Master Data'!A:F,6,FALSE) -> #N/A | F25: =VLOOKUP(D25,'Master Data'!A:F,4,FALSE) -> #N/A | G25: =VLOOKUP(D25,'Master Data'!A:F,5,FALSE) -> #N/A
A26: =VLOOKUP(D26,'Master Data'!A:F,2,FALSE) -> #N/A | B26: =VLOOKUP(D26,'Master Data'!A:F,3,FALSE) -> #N/A | C26: =VLOOKUP(D26,'Master Data'!A:F,6,FALSE) -> #N/A | F26: =VLOOKUP(D26,'Master Data'!A:F,4,FALSE) -> #N/A | G26: =VLOOKUP(D26,'Master Data'!A:F,5,FALSE) -> #N/A
A27: =VLOOKUP(D27,'Master Data'!A:F,2,FALSE) -> #N/A | B27: =VLOOKUP(D27,'Master Data'!A:F,3,FALSE) -> #N/A | C27: =VLOOKUP(D27,'Master Data'!A:F,5,FALSE) -> #N/A | F27: =VLOOKUP(D27,'Master Data'!A:F,4,FALSE) -> #N/A | G27: =VLOOKUP(D27,'Master Data'!A:F,5,FALSE) -> #N/A
A28: =VLOOKUP(D28,'Master Data'!A:F,2,FALSE) -> #N/A | B28: =VLOOKUP(D28,'Master Data'!A:F,3,FALSE) -> #N/A | C28: =VLOOKUP(D28,'Master Data'!A:F,5,FALSE) -> #N/A | F28: =VLOOKUP(D28,'Master Data'!A:F,4,FALSE) -> #N/A | G28: =VLOOKUP(D28,'Master Data'!A:F,5,FALSE) -> #N/A
A29: =VLOOKUP(D29,'Master Data'!A:F,2,FALSE) -> #N/A | B29: =VLOOKUP(D29,'Master Data'!A:F,3,FALSE) -> #N/A | C29: =VLOOKUP(D29,'Master Data'!A:F,5,FALSE) -> #N/A | F29: =VLOOKUP(D29,'Master Data'!A:F,4,FALSE) -> #N/A | G29: =VLOOKUP(D29,'Master Data'!A:F,5,FALSE) -> #N/A
A30: =VLOOKUP(D30,'Master Data'!A:F,2,FALSE) -> #N/A | B30: =VLOOKUP(D30,'Master Data'!A:F,3,FALSE) -> #N/A | C30: =VLOOKUP(D30,'Master Data'!A:F,5,FALSE) -> #N/A | F30: =VLOOKUP(D30,'Master Data'!A:F,4,FALSE) -> #N/A | G30: =VLOOKUP(D30,'Master Data'!A:F,5,FALSE) -> #N/A
A31: =VLOOKUP(D31,'Master Data'!A:F,2,FALSE) -> #N/A | B31: =VLOOKUP(D31,'Master Data'!A:F,3,FALSE) -> #N/A | C31: =VLOOKUP(D31,'Master Data'!A:F,5,FALSE) -> #N/A | F31: =VLOOKUP(D31,'Master Data'!A:F,4,FALSE) -> #N/A | G31: =VLOOKUP(D31,'Master Data'!A:F,5,FALSE) -> #N/A
G32: Einnahmen | H32: =SUM(H7:H31) -> 270

Sheet Mi_Bachata Beginner Stufe 4
A1: Anmeldungen - Bachata Beginner Stufe 4
A2: 4
A3: Datum: | B3: 07.01.2026 - 04.03.2026 | D3: Kurstag: | E3: Mittwoch | G3: Lehrer: | H3: Rena & Dan
A4: Zeit: | B4: 18:30 - 19:30 | D4: Ort: | E4: Elisabethenanlage 7 | G4: Preis: | H4: CHF 190.- / CHF 160.-
A6: Vorname | B6: Name | C6: E-Mail | D6: Mobile | E6: Bemerkungen | F6: m/w | G6: Tarif | H6: Betrag | I6: Anwesenheit
A7: =VLOOKUP(D7,'Master Data'!A:F,2,FALSE) -> Eleanor | B7: =VLOOKUP(D7,'Master Data'!A:F,3,FALSE) -> Low | C7: =VLOOKUP(D7,'Master Data'!A:F,6,FALSE) -> elebasel@gmail.com | D7: 0763802363 | E7: 2. Kurse | F7: =VLOOKUP(D7,'Master Data'!A:F,4,FALSE) -> w | G7: =VLOOKUP(D7,'Master Data'!A:F,5,FALSE) -> Normal | H7: 285 | I7: x | M7: x | N7: -
A8: =VLOOKUP(D8,'Master Data'!A:F,2,FALSE) -> Daniela | B8: =VLOOKUP(D8,'Master Data'!A:F,3,FALSE) -> Azzolin | C8: =VLOOKUP(D8,'Master Data'!A:F,6,FALSE) -> ddschoepf@gmx.ch | D8: 0763464285 | E8: fehlt 3 Mal | F8: =VLOOKUP(D8,'Master Data'!A:F,4,FALSE) -> w | G8: =VLOOKUP(D8,'Master Data'!A:F,5,FALSE) -> Paar | H8: 100 | I8: x | J8: - | K8: - | M8: - | N8: -
A9: =VLOOKUP(D9,'Master Data'!A:F,2,FALSE) -> Enrique | B9: =VLOOKUP(D9,'Master Data'!A:F,3,FALSE) -> Munoz | C9: =VLOOKUP(D9,'Master Data'!A:F,6,FALSE) -> enrique.munoz@gmx.ch | D9: 0797704890 | E9: fehlt 3 Mal | F9: =VLOOKUP(D9,'Master Data'!A:F,4,FALSE) -> m | G9: =VLOOKUP(D9,'Master Data'!A:F,5,FALSE) -> Normal | H9: 100 | I9: x | J9: - | K9: - | M9: - | N9: -
A10: =VLOOKUP(D10,'Master Data'!A:F,2,FALSE) -> Melina | B10: =VLOOKUP(D10,'Master Data'!A:F,3,FALSE) -> Götschi | C10: =VLOOKUP(D10,'Master Data'!A:F,6,FALSE) -> melinagoetschi@outlook.com | D10: 0795371219 | E10: 2. Kurse | F10: =VLOOKUP(D10,'Master Data'!A:F,4,FALSE) -> w | G10: =VLOOKUP(D10,'Master Data'!A:F,5,FALSE) -> Normal | H10: 285 | I10: - | M10: - | O10: -
A11: =VLOOKUP(D11,'Master Data'!A:F,2,FALSE) -> Julie | B11: =VLOOKUP(D11,'Master Data'!A:F,3,FALSE) -> Pfenninger | C11: =VLOOKUP(D11,'Master Data'!A:F,6,FALSE) -> j.pfenninger@hotmail.com | D11: 0786277824 | F11: =VLOOKUP(D11,'Master Data'!A:F,4,FALSE) -> w | G11: =VLOOKUP(D11,'Master Data'!A:F,5,FALSE) -> Normal | I11: x | M11: x | O11: -
A12: =VLOOKUP(D12,'Master Data'!A:F,2,FALSE) -> Inigo | B12: =VLOOKUP(D12,'Master Data'!A:F,3,FALSE) -> de la Maza | C12: =VLOOKUP(D12,'Master Data'!A:F,6,FALSE) -> i.delamaza.prieto@gmail.com | D12: 0795541328 | F12: =VLOOKUP(D12,'Master Data'!A:F,4,FALSE) -> m | G12: =VLOOKUP(D12,'Master Data'!A:F,5,FALSE) -> Normal | I12: x | M12: x
A13: =VLOOKUP(D13,'Master Data'!A:F,2,FALSE) -> Raphael | B13: =VLOOKUP(D13,'Master Data'!A:F,3,FALSE) -> Hubler | C13: =VLOOKUP(D13,'Master Data'!A:F,6,FALSE) -> raphaelhubler@gmail.com | D13: 0763358497 | F13: =VLOOKUP(D13,'Master Data'!A:F,4,FALSE) -> m | G13: =VLOOKUP(D13,'Master Data'!A:F,5,FALSE) -> Pushflow | I13: x | M13: x
A14: =VLOOKUP(D14,'Master Data'!A:F,2,FALSE) -> Irma | B14: =VLOOKUP(D14,'Master Data'!A:F,3,FALSE) -> Waltisberg | C14: =VLOOKUP(D14,'Master Data'!A:F,6,FALSE) -> walirma@bluewin.ch | D14: 0764122399 | F14: =VLOOKUP(D14,'Master Data'!A:F,4,FALSE) -> w | G14: =VLOOKUP(D14,'Master Data'!A:F,5,FALSE) -> Normal | H14: 190 | I14: - | M14: - | P14: -
A15: =VLOOKUP(D15,'Master Data'!A:F,2,FALSE) -> Franziska | B15: =VLOOKUP(D15,'Master Data'!A:F,3,FALSE) -> Krenmayr | C15: =VLOOKUP(D15,'Master Data'!A:F,6,FALSE) -> franzi.krenmayr@bluewin.ch | D15: 0797746466 | F15: =VLOOKUP(D15,'Master Data'!A:F,4,FALSE) -> w | G15: =VLOOKUP(D15,'Master Data'!A:F,5,FALSE) -> Normal | H15: 285 | I15: x | M15: x | P15: -
A16: =VLOOKUP(D16,'Master Data'!A:F,2,FALSE) -> Mathias | B16: =VLOOKUP(D16,'Master Data'!A:F,3,FALSE) -> Landsrath | C16: =VLOOKUP(D16,'Master Data'!A:F,6,FALSE) -> matila@gmx.de | D16: 0766413136 | F16: =VLOOKUP(D16,'Master Data'!A:F,4,FALSE) -> m | G16: =VLOOKUP(D16,'Master Data'!A:F,5,FALSE) -> Normal | H16: 410 | I16: x | M16: x
A17: =VLOOKUP(D17,'Master Data'!A:F,2,FALSE) -> #N/A | B17: =VLOOKUP(D17,'Master Data'!A:F,3,FALSE) -> #N/A | C17: =VLOOKUP(D17,'Master Data'!A:F,6,FALSE) -> #N/A | F17: =VLOOKUP(D17,'Master Data'!A:F,4,FALSE) -> #N/A | G17: =VLOOKUP(D17,'Master Data'!A:F,5,FALSE) -> #N/A
A18: =VLOOKUP(D18,'Master Data'!A:F,2,FALSE) -> #N/A | B18: =VLOOKUP(D18,'Master Data'!A:F,3,FALSE) -> #N/A | C18: =VLOOKUP(D18,'Master Data'!A:F,6,FALSE) -> #N/A | F18: =VLOOKUP(D18,'Master Data'!A:F,4,FALSE) -> #N/A | G18: =VLOOKUP(D18,'Master Data'!A:F,5,FALSE) -> #N/A
A19: =VLOOKUP(D19,'Master Data'!A:F,2,FALSE) -> #N/A | B19: =VLOOKUP(D19,'Master Data'!A:F,3,FALSE) -> #N/A | C19: =VLOOKUP(D19,'Master Data'!A:F,6,FALSE) -> #N/A | F19: =VLOOKUP(D19,'Master Data'!A:F,4,FALSE) -> #N/A | G19: =VLOOKUP(D19,'Master Data'!A:F,5,FALSE) -> #N/A
A20: =VLOOKUP(D20,'Master Data'!A:F,2,FALSE) -> #N/A | B20: =VLOOKUP(D20,'Master Data'!A:F,3,FALSE) -> #N/A | C20: =VLOOKUP(D20,'Master Data'!A:F,6,FALSE) -> #N/A | F20: =VLOOKUP(D20,'Master Data'!A:F,4,FALSE) -> #N/A | G20: =VLOOKUP(D20,'Master Data'!A:F,5,FALSE) -> #N/A
A21: =VLOOKUP(D21,'Master Data'!A:F,2,FALSE) -> #N/A | B21: =VLOOKUP(D21,'Master Data'!A:F,3,FALSE) -> #N/A | C21: =VLOOKUP(D21,'Master Data'!A:F,6,FALSE) -> #N/A | F21: =VLOOKUP(D21,'Master Data'!A:F,4,FALSE) -> #N/A | G21: =VLOOKUP(D21,'Master Data'!A:F,5,FALSE) -> #N/A
A22: =VLOOKUP(D22,'Master Data'!A:F,2,FALSE) -> #N/A | B22: =VLOOKUP(D22,'Master Data'!A:F,3,FALSE) -> #N/A | C22: =VLOOKUP(D22,'Master Data'!A:F,6,FALSE) -> #N/A | F22: =VLOOKUP(D22,'Master Data'!A:F,4,FALSE) -> #N/A | G22: =VLOOKUP(D22,'Master Data'!A:F,5,FALSE) -> #N/A
A23: =VLOOKUP(D23,'Master Data'!A:F,2,FALSE) -> #N/A | B23: =VLOOKUP(D23,'Master Data'!A:F,3,FALSE) -> #N/A | C23: =VLOOKUP(D23,'Master Data'!A:F,6,FALSE) -> #N/A | F23: =VLOOKUP(D23,'Master Data'!A:F,4,FALSE) -> #N/A | G23: =VLOOKUP(D23,'Master Data'!A:F,5,FALSE) -> #N/A
A24: =VLOOKUP(D24,'Master Data'!A:F,2,FALSE) -> #N/A | B24: =VLOOKUP(D24,'Master Data'!A:F,3,FALSE) -> #N/A | C24: =VLOOKUP(D24,'Master Data'!A:F,6,FALSE) -> #N/A | F24: =VLOOKUP(D24,'Master Data'!A:F,4,FALSE) -> #N/A | G24: =VLOOKUP(D24,'Master Data'!A:F,5,FALSE) -> #N/A
A25: =VLOOKUP(D25,'Master Data'!A:F,2,FALSE) -> #N/A | B25: =VLOOKUP(D25,'Master Data'!A:F,3,FALSE) -> #N/A | C25: =VLOOKUP(D25,'Master Data'!A:F,6,FALSE) -> #N/A | F25: =VLOOKUP(D25,'Master Data'!A:F,4,FALSE) -> #N/A | G25: =VLOOKUP(D25,'Master Data'!A:F,5,FALSE) -> #N/A
A26: =VLOOKUP(D26,'Master Data'!A:F,2,FALSE) -> #N/A | B26: =VLOOKUP(D26,'Master Data'!A:F,3,FALSE) -> #N/A | C26: =VLOOKUP(D26,'Master Data'!A:F,6,FALSE) -> #N/A | F26: =VLOOKUP(D26,'Master Data'!A:F,4,FALSE) -> #N/A | G26: =VLOOKUP(D26,'Master Data'!A:F,5,FALSE) -> #N/A
A27: =VLOOKUP(D27,'Master Data'!A:F,2,FALSE) -> #N/A | B27: =VLOOKUP(D27,'Master Data'!A:F,3,FALSE) -> #N/A | C27: =VLOOKUP(D27,'Master Data'!A:F,6,FALSE) -> #N/A | F27: =VLOOKUP(D27,'Master Data'!A:F,4,FALSE) -> #N/A | G27: =VLOOKUP(D27,'Master Data'!A:F,5,FALSE) -> #N/A
A28: =VLOOKUP(D28,'Master Data'!A:F,2,FALSE) -> #N/A | B28: =VLOOKUP(D28,'Master Data'!A:F,3,FALSE) -> #N/A | C28: =VLOOKUP(D28,'Master Data'!A:F,6,FALSE) -> #N/A | F28: =VLOOKUP(D28,'Master Data'!A:F,4,FALSE) -> #N/A | G28: =VLOOKUP(D28,'Master Data'!A:F,5,FALSE) -> #N/A
... A31: =VLOOKUP(D31,'Master Data'!A:F,2,FALSE) -> #N/A | B31: =VLOOKUP(D31,'Master Data'!A:F,3,FALSE) -> #N/A | C31: =VLOOKUP(D31,'Master Data'!A:F,6,FALSE) -> #N/A | F31: =VLOOKUP(D31,'Master Data'!A:F,4,FALSE) -> #N/A | G31: =VLOOKUP(D31,'Master Data'!A:F,5,FALSE) -> #N/A
A32: =VLOOKUP(D32,'Master Data'!A:F,2,FALSE) -> #N/A | B32: =VLOOKUP(D32,'Master Data'!A:F,3,FALSE) -> #N/A | C32: =VLOOKUP(D32,'Master Data'!A:F,5,FALSE) -> #N/A | G32: Einnahmen | H32: =SUM(H7:H31) -> 1655

Sheet Mi_Salsa Advanced On2 Flow
A1: Anmeldungen - Salsa Advanced On2 Flow
A3: Datum: | B3: 07.01.2026 - 04.03.2026 | D3: Kurstag: | E3: Mittwoch | G3: Lehrer: | H3: Vanessa & Sebastian
A4: Zeit: | B4: 19:30 - 20:30 | D4: Ort: | E4: Elisabethenanlage 7 | G4: Preis: | H4: CHF 190.- / CHF 160.-
A6: Vorname | B6: Name | C6: E-Mail | D6: Mobile | E6: Bemerkungen | F6: m/w | G6: Tarif | H6: Betrag | I6: Anwesenheit
A7: =VLOOKUP(D7,'Master Data'!A:F,2,FALSE) -> Raphael | B7: =VLOOKUP(D7,'Master Data'!A:F,3,FALSE) -> Hubler | C7: =VLOOKUP(D7,'Master Data'!A:F,6,FALSE) -> raphaelhubler@gmail.com | D7: 0763358497 | F7: =VLOOKUP(D7,'Master Data'!A:F,4,FALSE) -> m | G7: =VLOOKUP(D7,'Master Data'!A:F,5,FALSE) -> Pushflow | I7: x | J7: x | K7: X | M7: X
A8: =VLOOKUP(D8,'Master Data'!A:F,2,FALSE) -> Isabel | B8: =VLOOKUP(D8,'Master Data'!A:F,3,FALSE) -> Garcia | C8: =VLOOKUP(D8,'Master Data'!A:F,6,FALSE) -> 0 | D8: 0793407579 | F8: =VLOOKUP(D8,'Master Data'!A:F,4,FALSE) -> w | G8: =VLOOKUP(D8,'Master Data'!A:F,5,FALSE) -> Pushflow | I8: x | J8: x | K8: X | M8: X | O8: - | P8: -
A9: =VLOOKUP(D9,'Master Data'!A:F,2,FALSE) -> Jo | B9: =VLOOKUP(D9,'Master Data'!A:F,3,FALSE) -> Storrar | C9: =VLOOKUP(D9,'Master Data'!A:F,6,FALSE) -> joanne_storrar@hotmail.com | D9: 00447723012843 | F9: =VLOOKUP(D9,'Master Data'!A:F,4,FALSE) -> w | G9: =VLOOKUP(D9,'Master Data'!A:F,5,FALSE) -> Pushflow | I9: x | J9: x | K9: - | L9: - | M9: - | N9: - | O9: - | P9: -
A10: =VLOOKUP(D10,'Master Data'!A:F,2,FALSE) -> Franziska | B10: =VLOOKUP(D10,'Master Data'!A:F,3,FALSE) -> Krenmayr | C10: =VLOOKUP(D10,'Master Data'!A:F,6,FALSE) -> franzi.krenmayr@bluewin.ch | D10: 0797746466 | F10: =VLOOKUP(D10,'Master Data'!A:F,4,FALSE) -> w | G10: =VLOOKUP(D10,'Master Data'!A:F,5,FALSE) -> Normal | I10: x | J10: x | K10: - | M10: X | P10: -
A11: =VLOOKUP(D11,'Master Data'!A:F,2,FALSE) -> Tamas | B11: =VLOOKUP(D11,'Master Data'!A:F,3,FALSE) -> Faludi | C11: =VLOOKUP(D11,'Master Data'!A:F,6,FALSE) -> tamasfld@gmail.com | D11: 0799605394 | F11: =VLOOKUP(D11,'Master Data'!A:F,4,FALSE) -> m | G11: =VLOOKUP(D11,'Master Data'!A:F,5,FALSE) -> Normal | I11: x | J11: - | K11: X | M11: -
A12: =VLOOKUP(D12,'Master Data'!A:F,2,FALSE) -> Ali | B12: =VLOOKUP(D12,'Master Data'!A:F,3,FALSE) -> Üstündag | C12: =VLOOKUP(D12,'Master Data'!A:F,6,FALSE) -> ali.uestuendag@gmail.com | D12: 0786262771 | F12: =VLOOKUP(D12,'Master Data'!A:F,4,FALSE) -> m | G12: =VLOOKUP(D12,'Master Data'!A:F,5,FALSE) -> Pushflow | I12: x | J12: x | K12: X | M12: - | P12: -
A13: =VLOOKUP(D13,'Master Data'!A:F,2,FALSE) -> Jenny | B13: =VLOOKUP(D13,'Master Data'!A:F,3,FALSE) -> Castro | C13: =VLOOKUP(D13,'Master Data'!A:F,6,FALSE) -> castro.jenny@hotmail.ch | D13: 0794500626 | F13: =VLOOKUP(D13,'Master Data'!A:F,4,FALSE) -> w | G13: =VLOOKUP(D13,'Master Data'!A:F,5,FALSE) -> Pushflow | I13: x | J13: x | K13: X | M13: X
A14: =VLOOKUP(D14,'Master Data'!A:F,2,FALSE) -> Ilaria | B14: =VLOOKUP(D14,'Master Data'!A:F,3,FALSE) -> Seminatore | C14: =VLOOKUP(D14,'Master Data'!A:F,6,FALSE) -> ilaria.seminatore@gmail.com | D14: 0765892200 | F14: =VLOOKUP(D14,'Master Data'!A:F,4,FALSE) -> w | G14: =VLOOKUP(D14,'Master Data'!A:F,5,FALSE) -> Pushflow | I14: x | J14: x | K14: X | M14: X | P14: -
A15: =VLOOKUP(D15,'Master Data'!A:F,2,FALSE) -> Marco | B15: =VLOOKUP(D15,'Master Data'!A:F,3,FALSE) -> Krummenacher | C15: =VLOOKUP(D15,'Master Data'!A:F,6,FALSE) -> marco.krummenacher@unibas.ch | D15: 0793625124 | F15: =VLOOKUP(D15,'Master Data'!A:F,4,FALSE) -> m | G15: =VLOOKUP(D15,'Master Data'!A:F,5,FALSE) -> Pushflow | I15: x | J15: x | K15: X | M15: X | P15: -
A16: =VLOOKUP(D16,'Master Data'!A:F,2,FALSE) -> Doris | B16: =VLOOKUP(D16,'Master Data'!A:F,3,FALSE) -> Aznar | C16: =VLOOKUP(D16,'Master Data'!A:F,6,FALSE) -> doris_aznar@hotmail.com | D16: 0765719154 | F16: =VLOOKUP(D16,'Master Data'!A:F,4,FALSE) -> w | G16: =VLOOKUP(D16,'Master Data'!A:F,5,FALSE) -> Normal | H16: 410 | I16: x | J16: x | K16: X | M16: X
A17: =VLOOKUP(D17,'Master Data'!A:F,2,FALSE) -> Ivan | B17: =VLOOKUP(D17,'Master Data'!A:F,3,FALSE) -> Glushenkov | C17: =VLOOKUP(D17,'Master Data'!A:F,6,FALSE) -> ivan.glushenkov.data@gmail.com | D17: 0762636496 | E17: Salsaflow Pass | F17: =VLOOKUP(D17,'Master Data'!A:F,4,FALSE) -> m | G17: =VLOOKUP(D17,'Master Data'!A:F,5,FALSE) -> Normal | I17: x | J17: x | K17: - | M17: X
A18: =VLOOKUP(D18,'Master Data'!A:F,2,FALSE) -> #N/A | B18: =VLOOKUP(D18,'Master Data'!A:F,3,FALSE) -> #N/A | C18: =VLOOKUP(D18,'Master Data'!A:F,6,FALSE) -> #N/A | F18: =VLOOKUP(D18,'Master Data'!A:F,4,FALSE) -> #N/A | G18: =VLOOKUP(D18,'Master Data'!A:F,5,FALSE) -> #N/A
A19: =VLOOKUP(D19,'Master Data'!A:F,2,FALSE) -> #N/A | B19: =VLOOKUP(D19,'Master Data'!A:F,3,FALSE) -> #N/A | C19: =VLOOKUP(D19,'Master Data'!A:F,6,FALSE) -> #N/A | F19: =VLOOKUP(D19,'Master Data'!A:F,4,FALSE) -> #N/A | G19: =VLOOKUP(D19,'Master Data'!A:F,5,FALSE) -> #N/A
A20: =VLOOKUP(D20,'Master Data'!A:F,2,FALSE) -> #N/A | B20: =VLOOKUP(D20,'Master Data'!A:F,3,FALSE) -> #N/A | C20: =VLOOKUP(D20,'Master Data'!A:F,6,FALSE) -> #N/A | F20: =VLOOKUP(D20,'Master Data'!A:F,4,FALSE) -> #N/A | G20: =VLOOKUP(D20,'Master Data'!A:F,5,FALSE) -> #N/A
A21: =VLOOKUP(D21,'Master Data'!A:F,2,FALSE) -> #N/A | B21: =VLOOKUP(D21,'Master Data'!A:F,3,FALSE) -> #N/A | C21: =VLOOKUP(D21,'Master Data'!A:F,6,FALSE) -> #N/A | F21: =VLOOKUP(D21,'Master Data'!A:F,4,FALSE) -> #N/A | G21: =VLOOKUP(D21,'Master Data'!A:F,5,FALSE) -> #N/A
A22: =VLOOKUP(D22,'Master Data'!A:F,2,FALSE) -> #N/A | B22: =VLOOKUP(D22,'Master Data'!A:F,3,FALSE) -> #N/A | C22: =VLOOKUP(D22,'Master Data'!A:F,6,FALSE) -> #N/A | F22: =VLOOKUP(D22,'Master Data'!A:F,4,FALSE) -> #N/A | G22: =VLOOKUP(D22,'Master Data'!A:F,5,FALSE) -> #N/A
A23: =VLOOKUP(D23,'Master Data'!A:F,2,FALSE) -> #N/A | B23: =VLOOKUP(D23,'Master Data'!A:F,3,FALSE) -> #N/A | C23: =VLOOKUP(D23,'Master Data'!A:F,6,FALSE) -> #N/A | F23: =VLOOKUP(D23,'Master Data'!A:F,4,FALSE) -> #N/A | G23: =VLOOKUP(D23,'Master Data'!A:F,5,FALSE) -> #N/A
A24: =VLOOKUP(D24,'Master Data'!A:F,2,FALSE) -> #N/A | B24: =VLOOKUP(D24,'Master Data'!A:F,3,FALSE) -> #N/A | C24: =VLOOKUP(D24,'Master Data'!A:F,6,FALSE) -> #N/A | F24: =VLOOKUP(D24,'Master Data'!A:F,4,FALSE) -> #N/A | G24: =VLOOKUP(D24,'Master Data'!A:F,5,FALSE) -> #N/A
A25: =VLOOKUP(D25,'Master Data'!A:F,2,FALSE) -> #N/A | B25: =VLOOKUP(D25,'Master Data'!A:F,3,FALSE) -> #N/A | C25: =VLOOKUP(D25,'Master Data'!A:F,6,FALSE) -> #N/A | F25: =VLOOKUP(D25,'Master Data'!A:F,4,FALSE) -> #N/A | G25: =VLOOKUP(D25,'Master Data'!A:F,5,FALSE) -> #N/A
A26: =VLOOKUP(D26,'Master Data'!A:F,2,FALSE) -> #N/A | B26: =VLOOKUP(D26,'Master Data'!A:F,3,FALSE) -> #N/A | C26: =VLOOKUP(D26,'Master Data'!A:F,6,FALSE) -> #N/A | F26: =VLOOKUP(D26,'Master Data'!A:F,4,FALSE) -> #N/A | G26: =VLOOKUP(D26,'Master Data'!A:F,5,FALSE) -> #N/A
A27: =VLOOKUP(D27,'Master Data'!A:F,2,FALSE) -> #N/A | B27: =VLOOKUP(D27,'Master Data'!A:F,3,FALSE) -> #N/A | C27: =VLOOKUP(D27,'Master Data'!A:F,6,FALSE) -> #N/A | F27: =VLOOKUP(D27,'Master Data'!A:F,4,FALSE) -> #N/A | G27: =VLOOKUP(D27,'Master Data'!A:F,5,FALSE) -> #N/A
A28: =VLOOKUP(D28,'Master Data'!A:F,2,FALSE) -> #N/A | B28: =VLOOKUP(D28,'Master Data'!A:F,3,FALSE) -> #N/A | C28: =VLOOKUP(D28,'Master Data'!A:F,6,FALSE) -> #N/A | F28: =VLOOKUP(D28,'Master Data'!A:F,4,FALSE) -> #N/A | G28: =VLOOKUP(D28,'Master Data'!A:F,5,FALSE) -> #N/A
A29: =VLOOKUP(D29,'Master Data'!A:F,2,FALSE) -> #N/A | B29: =VLOOKUP(D29,'Master Data'!A:F,3,FALSE) -> #N/A | C29: =VLOOKUP(D29,'Master Data'!A:F,6,FALSE) -> #N/A | F29: =VLOOKUP(D29,'Master Data'!A:F,4,FALSE) -> #N/A | G29: =VLOOKUP(D29,'Master Data'!A:F,5,FALSE) -> #N/A
... A31: =VLOOKUP(D31,'Master Data'!A:F,2,FALSE) -> #N/A | B31: =VLOOKUP(D31,'Master Data'!A:F,3,FALSE) -> #N/A | C31: =VLOOKUP(D31,'Master Data'!A:F,6,FALSE) -> #N/A | F31: =VLOOKUP(D31,'Master Data'!A:F,4,FALSE) -> #N/A | G31: =VLOOKUP(D31,'Master Data'!A:F,5,FALSE) -> #N/A
A32: =VLOOKUP(D32,'Master Data'!A:F,2,FALSE) -> #N/A | B32: =VLOOKUP(D32,'Master Data'!A:F,3,FALSE) -> #N/A | C32: =VLOOKUP(D32,'Master Data'!A:F,5,FALSE) -> #N/A | G32: Einnahmen | H32: =SUM(H7:H31) -> 410

Sheet Mi_Bachata Beginner Stufe 1
A1: Anmeldungen - Bachata Beginner Stufe 1
A3: Datum: | B3: 07.01.2026 - 04.03.2026 | D3: Kurstag: | E3: Mittwoch | G3: Lehrer: | H3: Rena & Dan
A4: Zeit: | B4: 19:30 - 20:30 | D4: Ort: | E4: Elisabethenanlage 7 | G4: Preis: | H4: CHF 190.- / CHF 160.-
A6: Vorname | B6: Name | C6: E-Mail | D6: Mobile | E6: Bemerkungen | F6: m/w | G6: Tarif | H6: Betrag | I6: Anwesenheit
A7: =VLOOKUP(D7,'Master Data'!A:F,2,FALSE) -> Lena | B7: =VLOOKUP(D7,'Master Data'!A:F,3,FALSE) -> Strnad | C7: =VLOOKUP(D7,'Master Data'!A:F,6,FALSE) -> lena.strnad@gmail.com | D7: 0797632549 | F7: =VLOOKUP(D7,'Master Data'!A:F,4,FALSE) -> w | G7: =VLOOKUP(D7,'Master Data'!A:F,5,FALSE) -> Paar | H7: 160 | I7: x | J7: x | M7: x
A8: =VLOOKUP(D8,'Master Data'!A:F,2,FALSE) -> Titus Conradin | B8: =VLOOKUP(D8,'Master Data'!A:F,3,FALSE) -> Hell | C8: =VLOOKUP(D8,'Master Data'!A:F,6,FALSE) -> titus.hell@hotmail.com | D8: 0765874494 | F8: =VLOOKUP(D8,'Master Data'!A:F,4,FALSE) -> m | G8: =VLOOKUP(D8,'Master Data'!A:F,5,FALSE) -> Paar | H8: 160 | I8: x | J8: x | M8: x
A9: =VLOOKUP(D9,'Master Data'!A:F,2,FALSE) -> Felix | B9: =VLOOKUP(D9,'Master Data'!A:F,3,FALSE) -> Zimmermann | C9: =VLOOKUP(D9,'Master Data'!A:F,6,FALSE) -> Zimmermannfe@gmail.com | D9: 0775037116 | E9: 0.2 | F9: =VLOOKUP(D9,'Master Data'!A:F,4,FALSE) -> m | G9: =VLOOKUP(D9,'Master Data'!A:F,5,FALSE) -> Paar | H9: 127.5 | I9: x | J9: x | M9: - | N9: -
A10: =VLOOKUP(D10,'Master Data'!A:F,2,FALSE) -> Wioleta | B10: =VLOOKUP(D10,'Master Data'!A:F,3,FALSE) -> Chmielewicz | C10: =VLOOKUP(D10,'Master Data'!A:F,6,FALSE) -> wioleta.c@gmx.de | D10: 0585950464 | E10: 0.2 | F10: =VLOOKUP(D10,'Master Data'!A:F,4,FALSE) -> w | G10: =VLOOKUP(D10,'Master Data'!A:F,5,FALSE) -> Paar | H10: 127.5 | I10: x | J10: x | M10: -
A11: =VLOOKUP(D11,'Master Data'!A:F,2,FALSE) -> Marvin | B11: =VLOOKUP(D11,'Master Data'!A:F,3,FALSE) -> Hankel | C11: =VLOOKUP(D11,'Master Data'!A:F,6,FALSE) -> marv.hankel@gmail.com | D11: 004915129053132 | E11: 2. Kurse | F11: =VLOOKUP(D11,'Master Data'!A:F,4,FALSE) -> m | G11: =VLOOKUP(D11,'Master Data'!A:F,5,FALSE) -> Normal | I11: x | J11: x | M11: x
A12: =VLOOKUP(D12,'Master Data'!A:F,2,FALSE) -> Göknur | B12: =VLOOKUP(D12,'Master Data'!A:F,3,FALSE) -> Bektas | C12: =VLOOKUP(D12,'Master Data'!A:F,6,FALSE) -> gb@goebek.ch | D12: 0774167783 | E12: Schnuppern | F12: =VLOOKUP(D12,'Master Data'!A:F,4,FALSE) -> m | G12: =VLOOKUP(D12,'Master Data'!A:F,5,FALSE) -> Normal | H12: 190 | I12: x | J12: x | M12: - | N12: -
A13: =VLOOKUP(D13,'Master Data'!A:F,2,FALSE) -> Oliwia | B13: =VLOOKUP(D13,'Master Data'!A:F,3,FALSE) -> Glwcz | C13: =VLOOKUP(D13,'Master Data'!A:F,6,FALSE) -> oliwia.glwcz@gmail.com | D13: 0033699328876 | E13: Leader | F13: m | G13: =VLOOKUP(D13,'Master Data'!A:F,5,FALSE) -> Normal | H13: 190 | I13: x | J13: x | M13: x
A14: =VLOOKUP(D14,'Master Data'!A:F,2,FALSE) -> Ben | B14: =VLOOKUP(D14,'Master Data'!A:F,3,FALSE) -> Böke | C14: =VLOOKUP(D14,'Master Data'!A:F,6,FALSE) -> ben25boeke@gmail.com | D14: 00491602122888 | E14: Salsaflow Pass | F14: =VLOOKUP(D14,'Master Data'!A:F,4,FALSE) -> m | G14: =VLOOKUP(D14,'Master Data'!A:F,5,FALSE) -> Normal | I14: x | J14: x | M14: x
A15: =VLOOKUP(D15,'Master Data'!A:F,2,FALSE) -> Bülent | B15: =VLOOKUP(D15,'Master Data'!A:F,3,FALSE) -> Ekinci | C15: =VLOOKUP(D15,'Master Data'!A:F,6,FALSE) -> buelentekinci24@gamil.com | D15: 00491637919721 | E15: Salsaflow Pass | F15: m | G15: =VLOOKUP(D15,'Master Data'!A:F,5,FALSE) -> Normal | I15: x | J15: x | L15: - | M15: x
A16: =VLOOKUP(D16,'Master Data'!A:F,2,FALSE) -> Ricarda | B16: =VLOOKUP(D16,'Master Data'!A:F,3,FALSE) -> Studer | C16: =VLOOKUP(D16,'Master Data'!A:F,6,FALSE) -> ricardastuder@yahoo.com | D16: 0794579616 | F16: =VLOOKUP(D16,'Master Data'!A:F,4,FALSE) -> w | G16: =VLOOKUP(D16,'Master Data'!A:F,5,FALSE) -> Normal | H16: 160 | I16: x | J16: x | M16: x | O16: -
A17: =VLOOKUP(D17,'Master Data'!A:F,2,FALSE) -> Riccardo | B17: =VLOOKUP(D17,'Master Data'!A:F,3,FALSE) -> Scaglioni | C17: =VLOOKUP(D17,'Master Data'!A:F,6,FALSE) -> R.scaglioni@gmx.ch | D17: 0767288555 | F17: =VLOOKUP(D17,'Master Data'!A:F,4,FALSE) -> m | G17: =VLOOKUP(D17,'Master Data'!A:F,5,FALSE) -> Normal | H17: 160 | I17: x | J17: x | M17: x | O17: -
A18: =VLOOKUP(D18,'Master Data'!A:F,2,FALSE) -> Manuel | B18: =VLOOKUP(D18,'Master Data'!A:F,3,FALSE) -> Ramseier | C18: =VLOOKUP(D18,'Master Data'!A:F,6,FALSE) -> ramseiermanuel@gmail.com | D18: 0788902648 | E18: Nachholen | F18: =VLOOKUP(D18,'Master Data'!A:F,4,FALSE) -> m | G18: =VLOOKUP(D18,'Master Data'!A:F,5,FALSE) -> Normal | I18: - | J18: - | K18: - | L18: - | M18: - | N18: - | O18: - | P18: x
A19: =VLOOKUP(D19,'Master Data'!A:F,2,FALSE) -> #N/A | B19: =VLOOKUP(D19,'Master Data'!A:F,3,FALSE) -> #N/A | C19: =VLOOKUP(D19,'Master Data'!A:F,6,FALSE) -> #N/A | F19: =VLOOKUP(D19,'Master Data'!A:F,4,FALSE) -> #N/A | G19: =VLOOKUP(D19,'Master Data'!A:F,5,FALSE) -> #N/A
A20: =VLOOKUP(D20,'Master Data'!A:F,2,FALSE) -> #N/A | B20: =VLOOKUP(D20,'Master Data'!A:F,3,FALSE) -> #N/A | C20: =VLOOKUP(D20,'Master Data'!A:F,6,FALSE) -> #N/A | F20: =VLOOKUP(D20,'Master Data'!A:F,4,FALSE) -> #N/A | G20: =VLOOKUP(D20,'Master Data'!A:F,5,FALSE) -> #N/A
A21: =VLOOKUP(D21,'Master Data'!A:F,2,FALSE) -> #N/A | B21: =VLOOKUP(D21,'Master Data'!A:F,3,FALSE) -> #N/A | C21: =VLOOKUP(D21,'Master Data'!A:F,6,FALSE) -> #N/A | F21: =VLOOKUP(D21,'Master Data'!A:F,4,FALSE) -> #N/A | G21: =VLOOKUP(D21,'Master Data'!A:F,5,FALSE) -> #N/A
A22: =VLOOKUP(D22,'Master Data'!A:F,2,FALSE) -> #N/A | B22: =VLOOKUP(D22,'Master Data'!A:F,3,FALSE) -> #N/A | C22: =VLOOKUP(D22,'Master Data'!A:F,6,FALSE) -> #N/A | F22: =VLOOKUP(D22,'Master Data'!A:F,4,FALSE) -> #N/A | G22: =VLOOKUP(D22,'Master Data'!A:F,5,FALSE) -> #N/A
A23: =VLOOKUP(D23,'Master Data'!A:F,2,FALSE) -> #N/A | B23: =VLOOKUP(D23,'Master Data'!A:F,3,FALSE) -> #N/A | C23: =VLOOKUP(D23,'Master Data'!A:F,6,FALSE) -> #N/A | F23: =VLOOKUP(D23,'Master Data'!A:F,4,FALSE) -> #N/A | G23: =VLOOKUP(D23,'Master Data'!A:F,5,FALSE) -> #N/A
A24: =VLOOKUP(D24,'Master Data'!A:F,2,FALSE) -> #N/A | B24: =VLOOKUP(D24,'Master Data'!A:F,3,FALSE) -> #N/A | C24: =VLOOKUP(D24,'Master Data'!A:F,6,FALSE) -> #N/A | F24: =VLOOKUP(D24,'Master Data'!A:F,4,FALSE) -> #N/A | G24: =VLOOKUP(D24,'Master Data'!A:F,5,FALSE) -> #N/A
